import java.util.Collections;
import java.util.List;

public final class el
  extends qf
  implements eo
{
  public static qC<el> a = new em();
  private static final el c;
  private static volatile qB x = null;
  private final pT d;
  private int e;
  private qu f;
  private List<ev> g;
  private List<eh> h;
  private List<ed> i;
  private List<ed> j;
  private List<ed> k;
  private List<ep> l;
  private Object m;
  private Object n;
  private Object o;
  private Object p;
  private dX q;
  private float r;
  private boolean s;
  private qu t;
  private int u;
  private byte v = -1;
  private int w = -1;
  
  static
  {
    c = new el(true);
    c.S();
  }
  
  /* Error */
  private el(pW parampW, qa paramqa)
  {
    // Byte code:
    //   0: aload_0
    //   1: invokespecial 72	qf:<init>	()V
    //   4: aload_0
    //   5: iconst_m1
    //   6: putfield 74	el:v	B
    //   9: aload_0
    //   10: iconst_m1
    //   11: putfield 76	el:w	I
    //   14: aload_0
    //   15: invokespecial 65	el:S	()V
    //   18: iconst_0
    //   19: istore_3
    //   20: invokestatic 81	pT:i	()LpV;
    //   23: astore 9
    //   25: aload 9
    //   27: invokestatic 86	pY:a	(Ljava/io/OutputStream;)LpY;
    //   30: astore 10
    //   32: iconst_0
    //   33: istore 4
    //   35: iload 4
    //   37: ifne +1123 -> 1160
    //   40: iload_3
    //   41: istore 5
    //   43: aload_1
    //   44: invokevirtual 91	pW:a	()I
    //   47: istore 6
    //   49: iload 6
    //   51: lookupswitch	default:+1640->1691, 0:+1656->1707, 10:+173->224, 18:+240->291, 26:+305->356, 34:+370->421, 42:+438->489, 50:+506->557, 58:+574->625, 74:+642->693, 82:+686->737, 98:+730->781, 106:+774->825, 114:+819->870, 125:+921->972, 130:+959->1010, 136:+1032->1083, 144:+1071->1122
    //   196: iload_3
    //   197: istore 5
    //   199: aload_0
    //   200: aload_1
    //   201: aload 10
    //   203: aload_2
    //   204: iload 6
    //   206: invokevirtual 94	el:a	(LpW;LpY;Lqa;I)Z
    //   209: ifne +938 -> 1147
    //   212: iconst_1
    //   213: istore 5
    //   215: iload_3
    //   216: istore 4
    //   218: iload 5
    //   220: istore_3
    //   221: goto +1473 -> 1694
    //   224: iload_3
    //   225: istore 5
    //   227: aload_1
    //   228: invokevirtual 97	pW:l	()LpT;
    //   231: astore 8
    //   233: iload_3
    //   234: iconst_1
    //   235: iand
    //   236: iconst_1
    //   237: if_icmpeq +1448 -> 1685
    //   240: iload_3
    //   241: istore 5
    //   243: aload_0
    //   244: new 99	qt
    //   247: dup
    //   248: invokespecial 100	qt:<init>	()V
    //   251: putfield 102	el:f	Lqu;
    //   254: iload_3
    //   255: iconst_1
    //   256: ior
    //   257: istore 7
    //   259: iload 7
    //   261: istore_3
    //   262: iload 7
    //   264: istore 5
    //   266: iload 7
    //   268: istore 6
    //   270: aload_0
    //   271: getfield 102	el:f	Lqu;
    //   274: aload 8
    //   276: invokeinterface 107 2 0
    //   281: iload 4
    //   283: istore_3
    //   284: iload 7
    //   286: istore 4
    //   288: goto +1406 -> 1694
    //   291: iload_3
    //   292: iconst_2
    //   293: iand
    //   294: iconst_2
    //   295: if_icmpeq +1384 -> 1679
    //   298: iload_3
    //   299: istore 5
    //   301: aload_0
    //   302: new 109	java/util/ArrayList
    //   305: dup
    //   306: invokespecial 110	java/util/ArrayList:<init>	()V
    //   309: putfield 112	el:g	Ljava/util/List;
    //   312: iload_3
    //   313: iconst_2
    //   314: ior
    //   315: istore 7
    //   317: iload 7
    //   319: istore_3
    //   320: iload 7
    //   322: istore 5
    //   324: iload 7
    //   326: istore 6
    //   328: aload_0
    //   329: getfield 112	el:g	Ljava/util/List;
    //   332: aload_1
    //   333: getstatic 115	ev:a	LqC;
    //   336: aload_2
    //   337: invokevirtual 118	pW:a	(LqC;Lqa;)Lqy;
    //   340: invokeinterface 124 2 0
    //   345: pop
    //   346: iload 4
    //   348: istore_3
    //   349: iload 7
    //   351: istore 4
    //   353: goto +1341 -> 1694
    //   356: iload_3
    //   357: iconst_4
    //   358: iand
    //   359: iconst_4
    //   360: if_icmpeq +1313 -> 1673
    //   363: iload_3
    //   364: istore 5
    //   366: aload_0
    //   367: new 109	java/util/ArrayList
    //   370: dup
    //   371: invokespecial 110	java/util/ArrayList:<init>	()V
    //   374: putfield 126	el:h	Ljava/util/List;
    //   377: iload_3
    //   378: iconst_4
    //   379: ior
    //   380: istore 7
    //   382: iload 7
    //   384: istore_3
    //   385: iload 7
    //   387: istore 5
    //   389: iload 7
    //   391: istore 6
    //   393: aload_0
    //   394: getfield 126	el:h	Ljava/util/List;
    //   397: aload_1
    //   398: getstatic 129	eh:a	LqC;
    //   401: aload_2
    //   402: invokevirtual 118	pW:a	(LqC;Lqa;)Lqy;
    //   405: invokeinterface 124 2 0
    //   410: pop
    //   411: iload 4
    //   413: istore_3
    //   414: iload 7
    //   416: istore 4
    //   418: goto +1276 -> 1694
    //   421: iload_3
    //   422: bipush 8
    //   424: iand
    //   425: bipush 8
    //   427: if_icmpeq +1240 -> 1667
    //   430: iload_3
    //   431: istore 5
    //   433: aload_0
    //   434: new 109	java/util/ArrayList
    //   437: dup
    //   438: invokespecial 110	java/util/ArrayList:<init>	()V
    //   441: putfield 131	el:i	Ljava/util/List;
    //   444: iload_3
    //   445: bipush 8
    //   447: ior
    //   448: istore 7
    //   450: iload 7
    //   452: istore_3
    //   453: iload 7
    //   455: istore 5
    //   457: iload 7
    //   459: istore 6
    //   461: aload_0
    //   462: getfield 131	el:i	Ljava/util/List;
    //   465: aload_1
    //   466: getstatic 134	ed:a	LqC;
    //   469: aload_2
    //   470: invokevirtual 118	pW:a	(LqC;Lqa;)Lqy;
    //   473: invokeinterface 124 2 0
    //   478: pop
    //   479: iload 4
    //   481: istore_3
    //   482: iload 7
    //   484: istore 4
    //   486: goto +1208 -> 1694
    //   489: iload_3
    //   490: bipush 16
    //   492: iand
    //   493: bipush 16
    //   495: if_icmpeq +1166 -> 1661
    //   498: iload_3
    //   499: istore 5
    //   501: aload_0
    //   502: new 109	java/util/ArrayList
    //   505: dup
    //   506: invokespecial 110	java/util/ArrayList:<init>	()V
    //   509: putfield 136	el:j	Ljava/util/List;
    //   512: iload_3
    //   513: bipush 16
    //   515: ior
    //   516: istore 7
    //   518: iload 7
    //   520: istore_3
    //   521: iload 7
    //   523: istore 5
    //   525: iload 7
    //   527: istore 6
    //   529: aload_0
    //   530: getfield 136	el:j	Ljava/util/List;
    //   533: aload_1
    //   534: getstatic 134	ed:a	LqC;
    //   537: aload_2
    //   538: invokevirtual 118	pW:a	(LqC;Lqa;)Lqy;
    //   541: invokeinterface 124 2 0
    //   546: pop
    //   547: iload 4
    //   549: istore_3
    //   550: iload 7
    //   552: istore 4
    //   554: goto +1140 -> 1694
    //   557: iload_3
    //   558: bipush 32
    //   560: iand
    //   561: bipush 32
    //   563: if_icmpeq +1092 -> 1655
    //   566: iload_3
    //   567: istore 5
    //   569: aload_0
    //   570: new 109	java/util/ArrayList
    //   573: dup
    //   574: invokespecial 110	java/util/ArrayList:<init>	()V
    //   577: putfield 138	el:k	Ljava/util/List;
    //   580: iload_3
    //   581: bipush 32
    //   583: ior
    //   584: istore 7
    //   586: iload 7
    //   588: istore_3
    //   589: iload 7
    //   591: istore 5
    //   593: iload 7
    //   595: istore 6
    //   597: aload_0
    //   598: getfield 138	el:k	Ljava/util/List;
    //   601: aload_1
    //   602: getstatic 134	ed:a	LqC;
    //   605: aload_2
    //   606: invokevirtual 118	pW:a	(LqC;Lqa;)Lqy;
    //   609: invokeinterface 124 2 0
    //   614: pop
    //   615: iload 4
    //   617: istore_3
    //   618: iload 7
    //   620: istore 4
    //   622: goto +1072 -> 1694
    //   625: iload_3
    //   626: bipush 64
    //   628: iand
    //   629: bipush 64
    //   631: if_icmpeq +1018 -> 1649
    //   634: iload_3
    //   635: istore 5
    //   637: aload_0
    //   638: new 109	java/util/ArrayList
    //   641: dup
    //   642: invokespecial 110	java/util/ArrayList:<init>	()V
    //   645: putfield 140	el:l	Ljava/util/List;
    //   648: iload_3
    //   649: bipush 64
    //   651: ior
    //   652: istore 7
    //   654: iload 7
    //   656: istore_3
    //   657: iload 7
    //   659: istore 5
    //   661: iload 7
    //   663: istore 6
    //   665: aload_0
    //   666: getfield 140	el:l	Ljava/util/List;
    //   669: aload_1
    //   670: getstatic 143	ep:a	LqC;
    //   673: aload_2
    //   674: invokevirtual 118	pW:a	(LqC;Lqa;)Lqy;
    //   677: invokeinterface 124 2 0
    //   682: pop
    //   683: iload 4
    //   685: istore_3
    //   686: iload 7
    //   688: istore 4
    //   690: goto +1004 -> 1694
    //   693: iload_3
    //   694: istore 5
    //   696: aload_1
    //   697: invokevirtual 97	pW:l	()LpT;
    //   700: astore 8
    //   702: iload_3
    //   703: istore 5
    //   705: aload_0
    //   706: aload_0
    //   707: getfield 145	el:e	I
    //   710: iconst_1
    //   711: ior
    //   712: putfield 145	el:e	I
    //   715: iload_3
    //   716: istore 5
    //   718: aload_0
    //   719: aload 8
    //   721: putfield 147	el:m	Ljava/lang/Object;
    //   724: iload_3
    //   725: istore 5
    //   727: iload 4
    //   729: istore_3
    //   730: iload 5
    //   732: istore 4
    //   734: goto +960 -> 1694
    //   737: iload_3
    //   738: istore 5
    //   740: aload_1
    //   741: invokevirtual 97	pW:l	()LpT;
    //   744: astore 8
    //   746: iload_3
    //   747: istore 5
    //   749: aload_0
    //   750: aload_0
    //   751: getfield 145	el:e	I
    //   754: iconst_2
    //   755: ior
    //   756: putfield 145	el:e	I
    //   759: iload_3
    //   760: istore 5
    //   762: aload_0
    //   763: aload 8
    //   765: putfield 149	el:n	Ljava/lang/Object;
    //   768: iload_3
    //   769: istore 5
    //   771: iload 4
    //   773: istore_3
    //   774: iload 5
    //   776: istore 4
    //   778: goto +916 -> 1694
    //   781: iload_3
    //   782: istore 5
    //   784: aload_1
    //   785: invokevirtual 97	pW:l	()LpT;
    //   788: astore 8
    //   790: iload_3
    //   791: istore 5
    //   793: aload_0
    //   794: aload_0
    //   795: getfield 145	el:e	I
    //   798: iconst_4
    //   799: ior
    //   800: putfield 145	el:e	I
    //   803: iload_3
    //   804: istore 5
    //   806: aload_0
    //   807: aload 8
    //   809: putfield 151	el:o	Ljava/lang/Object;
    //   812: iload_3
    //   813: istore 5
    //   815: iload 4
    //   817: istore_3
    //   818: iload 5
    //   820: istore 4
    //   822: goto +872 -> 1694
    //   825: iload_3
    //   826: istore 5
    //   828: aload_1
    //   829: invokevirtual 97	pW:l	()LpT;
    //   832: astore 8
    //   834: iload_3
    //   835: istore 5
    //   837: aload_0
    //   838: aload_0
    //   839: getfield 145	el:e	I
    //   842: bipush 8
    //   844: ior
    //   845: putfield 145	el:e	I
    //   848: iload_3
    //   849: istore 5
    //   851: aload_0
    //   852: aload 8
    //   854: putfield 153	el:p	Ljava/lang/Object;
    //   857: iload_3
    //   858: istore 5
    //   860: iload 4
    //   862: istore_3
    //   863: iload 5
    //   865: istore 4
    //   867: goto +827 -> 1694
    //   870: iload_3
    //   871: istore 5
    //   873: aload_0
    //   874: getfield 145	el:e	I
    //   877: bipush 16
    //   879: iand
    //   880: bipush 16
    //   882: if_icmpne +761 -> 1643
    //   885: iload_3
    //   886: istore 5
    //   888: aload_0
    //   889: getfield 155	el:q	LdX;
    //   892: invokevirtual 160	dX:m	()LdZ;
    //   895: astore 8
    //   897: iload_3
    //   898: istore 5
    //   900: aload_0
    //   901: aload_1
    //   902: getstatic 161	dX:a	LqC;
    //   905: aload_2
    //   906: invokevirtual 118	pW:a	(LqC;Lqa;)Lqy;
    //   909: checkcast 157	dX
    //   912: putfield 155	el:q	LdX;
    //   915: aload 8
    //   917: ifnull +28 -> 945
    //   920: iload_3
    //   921: istore 5
    //   923: aload 8
    //   925: aload_0
    //   926: getfield 155	el:q	LdX;
    //   929: invokevirtual 166	dZ:a	(LdX;)LdZ;
    //   932: pop
    //   933: iload_3
    //   934: istore 5
    //   936: aload_0
    //   937: aload 8
    //   939: invokevirtual 169	dZ:d	()LdX;
    //   942: putfield 155	el:q	LdX;
    //   945: iload_3
    //   946: istore 5
    //   948: aload_0
    //   949: aload_0
    //   950: getfield 145	el:e	I
    //   953: bipush 16
    //   955: ior
    //   956: putfield 145	el:e	I
    //   959: iload_3
    //   960: istore 5
    //   962: iload 4
    //   964: istore_3
    //   965: iload 5
    //   967: istore 4
    //   969: goto +725 -> 1694
    //   972: iload_3
    //   973: istore 5
    //   975: aload_0
    //   976: aload_0
    //   977: getfield 145	el:e	I
    //   980: bipush 32
    //   982: ior
    //   983: putfield 145	el:e	I
    //   986: iload_3
    //   987: istore 5
    //   989: aload_0
    //   990: aload_1
    //   991: invokevirtual 172	pW:c	()F
    //   994: putfield 174	el:r	F
    //   997: iload_3
    //   998: istore 5
    //   1000: iload 4
    //   1002: istore_3
    //   1003: iload 5
    //   1005: istore 4
    //   1007: goto +687 -> 1694
    //   1010: iload_3
    //   1011: istore 5
    //   1013: aload_1
    //   1014: invokevirtual 97	pW:l	()LpT;
    //   1017: astore 8
    //   1019: iload_3
    //   1020: sipush 16384
    //   1023: iand
    //   1024: sipush 16384
    //   1027: if_icmpeq +610 -> 1637
    //   1030: iload_3
    //   1031: istore 5
    //   1033: aload_0
    //   1034: new 99	qt
    //   1037: dup
    //   1038: invokespecial 100	qt:<init>	()V
    //   1041: putfield 176	el:t	Lqu;
    //   1044: iload_3
    //   1045: sipush 16384
    //   1048: ior
    //   1049: istore 7
    //   1051: iload 7
    //   1053: istore_3
    //   1054: iload 7
    //   1056: istore 5
    //   1058: iload 7
    //   1060: istore 6
    //   1062: aload_0
    //   1063: getfield 176	el:t	Lqu;
    //   1066: aload 8
    //   1068: invokeinterface 107 2 0
    //   1073: iload 4
    //   1075: istore_3
    //   1076: iload 7
    //   1078: istore 4
    //   1080: goto +614 -> 1694
    //   1083: iload_3
    //   1084: istore 5
    //   1086: aload_0
    //   1087: aload_0
    //   1088: getfield 145	el:e	I
    //   1091: sipush 128
    //   1094: ior
    //   1095: putfield 145	el:e	I
    //   1098: iload_3
    //   1099: istore 5
    //   1101: aload_0
    //   1102: aload_1
    //   1103: invokevirtual 178	pW:f	()I
    //   1106: putfield 180	el:u	I
    //   1109: iload_3
    //   1110: istore 5
    //   1112: iload 4
    //   1114: istore_3
    //   1115: iload 5
    //   1117: istore 4
    //   1119: goto +575 -> 1694
    //   1122: iload_3
    //   1123: istore 5
    //   1125: aload_0
    //   1126: aload_0
    //   1127: getfield 145	el:e	I
    //   1130: bipush 64
    //   1132: ior
    //   1133: putfield 145	el:e	I
    //   1136: iload_3
    //   1137: istore 5
    //   1139: aload_0
    //   1140: aload_1
    //   1141: invokevirtual 183	pW:i	()Z
    //   1144: putfield 185	el:s	Z
    //   1147: iload_3
    //   1148: istore 5
    //   1150: iload 4
    //   1152: istore_3
    //   1153: iload 5
    //   1155: istore 4
    //   1157: goto +537 -> 1694
    //   1160: iload_3
    //   1161: iconst_1
    //   1162: iand
    //   1163: iconst_1
    //   1164: if_icmpne +18 -> 1182
    //   1167: aload_0
    //   1168: new 187	qS
    //   1171: dup
    //   1172: aload_0
    //   1173: getfield 102	el:f	Lqu;
    //   1176: invokespecial 190	qS:<init>	(Lqu;)V
    //   1179: putfield 102	el:f	Lqu;
    //   1182: iload_3
    //   1183: iconst_2
    //   1184: iand
    //   1185: iconst_2
    //   1186: if_icmpne +14 -> 1200
    //   1189: aload_0
    //   1190: aload_0
    //   1191: getfield 112	el:g	Ljava/util/List;
    //   1194: invokestatic 196	java/util/Collections:unmodifiableList	(Ljava/util/List;)Ljava/util/List;
    //   1197: putfield 112	el:g	Ljava/util/List;
    //   1200: iload_3
    //   1201: iconst_4
    //   1202: iand
    //   1203: iconst_4
    //   1204: if_icmpne +14 -> 1218
    //   1207: aload_0
    //   1208: aload_0
    //   1209: getfield 126	el:h	Ljava/util/List;
    //   1212: invokestatic 196	java/util/Collections:unmodifiableList	(Ljava/util/List;)Ljava/util/List;
    //   1215: putfield 126	el:h	Ljava/util/List;
    //   1218: iload_3
    //   1219: bipush 8
    //   1221: iand
    //   1222: bipush 8
    //   1224: if_icmpne +14 -> 1238
    //   1227: aload_0
    //   1228: aload_0
    //   1229: getfield 131	el:i	Ljava/util/List;
    //   1232: invokestatic 196	java/util/Collections:unmodifiableList	(Ljava/util/List;)Ljava/util/List;
    //   1235: putfield 131	el:i	Ljava/util/List;
    //   1238: iload_3
    //   1239: bipush 16
    //   1241: iand
    //   1242: bipush 16
    //   1244: if_icmpne +14 -> 1258
    //   1247: aload_0
    //   1248: aload_0
    //   1249: getfield 136	el:j	Ljava/util/List;
    //   1252: invokestatic 196	java/util/Collections:unmodifiableList	(Ljava/util/List;)Ljava/util/List;
    //   1255: putfield 136	el:j	Ljava/util/List;
    //   1258: iload_3
    //   1259: bipush 32
    //   1261: iand
    //   1262: bipush 32
    //   1264: if_icmpne +14 -> 1278
    //   1267: aload_0
    //   1268: aload_0
    //   1269: getfield 138	el:k	Ljava/util/List;
    //   1272: invokestatic 196	java/util/Collections:unmodifiableList	(Ljava/util/List;)Ljava/util/List;
    //   1275: putfield 138	el:k	Ljava/util/List;
    //   1278: iload_3
    //   1279: bipush 64
    //   1281: iand
    //   1282: bipush 64
    //   1284: if_icmpne +14 -> 1298
    //   1287: aload_0
    //   1288: aload_0
    //   1289: getfield 140	el:l	Ljava/util/List;
    //   1292: invokestatic 196	java/util/Collections:unmodifiableList	(Ljava/util/List;)Ljava/util/List;
    //   1295: putfield 140	el:l	Ljava/util/List;
    //   1298: iload_3
    //   1299: sipush 16384
    //   1302: iand
    //   1303: sipush 16384
    //   1306: if_icmpne +18 -> 1324
    //   1309: aload_0
    //   1310: new 187	qS
    //   1313: dup
    //   1314: aload_0
    //   1315: getfield 176	el:t	Lqu;
    //   1318: invokespecial 190	qS:<init>	(Lqu;)V
    //   1321: putfield 176	el:t	Lqu;
    //   1324: aload 10
    //   1326: invokevirtual 198	pY:a	()V
    //   1329: aload_0
    //   1330: aload 9
    //   1332: invokevirtual 202	pV:a	()LpT;
    //   1335: putfield 204	el:d	LpT;
    //   1338: aload_0
    //   1339: invokevirtual 207	el:R	()V
    //   1342: return
    //   1343: astore_1
    //   1344: aload_0
    //   1345: aload 9
    //   1347: invokevirtual 202	pV:a	()LpT;
    //   1350: putfield 204	el:d	LpT;
    //   1353: goto -15 -> 1338
    //   1356: astore_1
    //   1357: aload_0
    //   1358: aload 9
    //   1360: invokevirtual 202	pV:a	()LpT;
    //   1363: putfield 204	el:d	LpT;
    //   1366: aload_1
    //   1367: athrow
    //   1368: astore_1
    //   1369: iload_3
    //   1370: istore 5
    //   1372: aload_1
    //   1373: aload_0
    //   1374: invokevirtual 210	qr:a	(Lqy;)Lqr;
    //   1377: athrow
    //   1378: astore_1
    //   1379: iload 5
    //   1381: iconst_1
    //   1382: iand
    //   1383: iconst_1
    //   1384: if_icmpne +18 -> 1402
    //   1387: aload_0
    //   1388: new 187	qS
    //   1391: dup
    //   1392: aload_0
    //   1393: getfield 102	el:f	Lqu;
    //   1396: invokespecial 190	qS:<init>	(Lqu;)V
    //   1399: putfield 102	el:f	Lqu;
    //   1402: iload 5
    //   1404: iconst_2
    //   1405: iand
    //   1406: iconst_2
    //   1407: if_icmpne +14 -> 1421
    //   1410: aload_0
    //   1411: aload_0
    //   1412: getfield 112	el:g	Ljava/util/List;
    //   1415: invokestatic 196	java/util/Collections:unmodifiableList	(Ljava/util/List;)Ljava/util/List;
    //   1418: putfield 112	el:g	Ljava/util/List;
    //   1421: iload 5
    //   1423: iconst_4
    //   1424: iand
    //   1425: iconst_4
    //   1426: if_icmpne +14 -> 1440
    //   1429: aload_0
    //   1430: aload_0
    //   1431: getfield 126	el:h	Ljava/util/List;
    //   1434: invokestatic 196	java/util/Collections:unmodifiableList	(Ljava/util/List;)Ljava/util/List;
    //   1437: putfield 126	el:h	Ljava/util/List;
    //   1440: iload 5
    //   1442: bipush 8
    //   1444: iand
    //   1445: bipush 8
    //   1447: if_icmpne +14 -> 1461
    //   1450: aload_0
    //   1451: aload_0
    //   1452: getfield 131	el:i	Ljava/util/List;
    //   1455: invokestatic 196	java/util/Collections:unmodifiableList	(Ljava/util/List;)Ljava/util/List;
    //   1458: putfield 131	el:i	Ljava/util/List;
    //   1461: iload 5
    //   1463: bipush 16
    //   1465: iand
    //   1466: bipush 16
    //   1468: if_icmpne +14 -> 1482
    //   1471: aload_0
    //   1472: aload_0
    //   1473: getfield 136	el:j	Ljava/util/List;
    //   1476: invokestatic 196	java/util/Collections:unmodifiableList	(Ljava/util/List;)Ljava/util/List;
    //   1479: putfield 136	el:j	Ljava/util/List;
    //   1482: iload 5
    //   1484: bipush 32
    //   1486: iand
    //   1487: bipush 32
    //   1489: if_icmpne +14 -> 1503
    //   1492: aload_0
    //   1493: aload_0
    //   1494: getfield 138	el:k	Ljava/util/List;
    //   1497: invokestatic 196	java/util/Collections:unmodifiableList	(Ljava/util/List;)Ljava/util/List;
    //   1500: putfield 138	el:k	Ljava/util/List;
    //   1503: iload 5
    //   1505: bipush 64
    //   1507: iand
    //   1508: bipush 64
    //   1510: if_icmpne +14 -> 1524
    //   1513: aload_0
    //   1514: aload_0
    //   1515: getfield 140	el:l	Ljava/util/List;
    //   1518: invokestatic 196	java/util/Collections:unmodifiableList	(Ljava/util/List;)Ljava/util/List;
    //   1521: putfield 140	el:l	Ljava/util/List;
    //   1524: iload 5
    //   1526: sipush 16384
    //   1529: iand
    //   1530: sipush 16384
    //   1533: if_icmpne +18 -> 1551
    //   1536: aload_0
    //   1537: new 187	qS
    //   1540: dup
    //   1541: aload_0
    //   1542: getfield 176	el:t	Lqu;
    //   1545: invokespecial 190	qS:<init>	(Lqu;)V
    //   1548: putfield 176	el:t	Lqu;
    //   1551: aload 10
    //   1553: invokevirtual 198	pY:a	()V
    //   1556: aload_0
    //   1557: aload 9
    //   1559: invokevirtual 202	pV:a	()LpT;
    //   1562: putfield 204	el:d	LpT;
    //   1565: aload_0
    //   1566: invokevirtual 207	el:R	()V
    //   1569: aload_1
    //   1570: athrow
    //   1571: astore_1
    //   1572: iload_3
    //   1573: istore 5
    //   1575: new 69	qr
    //   1578: dup
    //   1579: aload_1
    //   1580: invokevirtual 214	java/io/IOException:getMessage	()Ljava/lang/String;
    //   1583: invokespecial 217	qr:<init>	(Ljava/lang/String;)V
    //   1586: aload_0
    //   1587: invokevirtual 210	qr:a	(Lqy;)Lqr;
    //   1590: athrow
    //   1591: astore_2
    //   1592: aload_0
    //   1593: aload 9
    //   1595: invokevirtual 202	pV:a	()LpT;
    //   1598: putfield 204	el:d	LpT;
    //   1601: goto -36 -> 1565
    //   1604: astore_1
    //   1605: aload_0
    //   1606: aload 9
    //   1608: invokevirtual 202	pV:a	()LpT;
    //   1611: putfield 204	el:d	LpT;
    //   1614: aload_1
    //   1615: athrow
    //   1616: astore_1
    //   1617: iload_3
    //   1618: istore 5
    //   1620: goto -241 -> 1379
    //   1623: astore_1
    //   1624: iload 5
    //   1626: istore_3
    //   1627: goto -55 -> 1572
    //   1630: astore_1
    //   1631: iload 6
    //   1633: istore_3
    //   1634: goto -265 -> 1369
    //   1637: iload_3
    //   1638: istore 7
    //   1640: goto -589 -> 1051
    //   1643: aconst_null
    //   1644: astore 8
    //   1646: goto -749 -> 897
    //   1649: iload_3
    //   1650: istore 7
    //   1652: goto -998 -> 654
    //   1655: iload_3
    //   1656: istore 7
    //   1658: goto -1072 -> 586
    //   1661: iload_3
    //   1662: istore 7
    //   1664: goto -1146 -> 518
    //   1667: iload_3
    //   1668: istore 7
    //   1670: goto -1220 -> 450
    //   1673: iload_3
    //   1674: istore 7
    //   1676: goto -1294 -> 382
    //   1679: iload_3
    //   1680: istore 7
    //   1682: goto -1365 -> 317
    //   1685: iload_3
    //   1686: istore 7
    //   1688: goto -1429 -> 259
    //   1691: goto -1495 -> 196
    //   1694: iload 4
    //   1696: istore 5
    //   1698: iload_3
    //   1699: istore 4
    //   1701: iload 5
    //   1703: istore_3
    //   1704: goto -1669 -> 35
    //   1707: iconst_1
    //   1708: istore 5
    //   1710: iload_3
    //   1711: istore 4
    //   1713: iload 5
    //   1715: istore_3
    //   1716: goto -22 -> 1694
    // Local variable table:
    //   start	length	slot	name	signature
    //   0	1719	0	this	el
    //   0	1719	1	parampW	pW
    //   0	1719	2	paramqa	qa
    //   19	1697	3	i1	int
    //   33	1679	4	i2	int
    //   41	1673	5	i3	int
    //   47	1585	6	i4	int
    //   257	1430	7	i5	int
    //   231	1414	8	localObject	Object
    //   23	1584	9	localpV	pV
    //   30	1522	10	localpY	pY
    // Exception table:
    //   from	to	target	type
    //   1324	1329	1343	java/io/IOException
    //   1324	1329	1356	finally
    //   43	49	1368	qr
    //   199	212	1368	qr
    //   227	233	1368	qr
    //   243	254	1368	qr
    //   301	312	1368	qr
    //   366	377	1368	qr
    //   433	444	1368	qr
    //   501	512	1368	qr
    //   569	580	1368	qr
    //   637	648	1368	qr
    //   696	702	1368	qr
    //   705	715	1368	qr
    //   718	724	1368	qr
    //   740	746	1368	qr
    //   749	759	1368	qr
    //   762	768	1368	qr
    //   784	790	1368	qr
    //   793	803	1368	qr
    //   806	812	1368	qr
    //   828	834	1368	qr
    //   837	848	1368	qr
    //   851	857	1368	qr
    //   873	885	1368	qr
    //   888	897	1368	qr
    //   900	915	1368	qr
    //   923	933	1368	qr
    //   936	945	1368	qr
    //   948	959	1368	qr
    //   975	986	1368	qr
    //   989	997	1368	qr
    //   1013	1019	1368	qr
    //   1033	1044	1368	qr
    //   1086	1098	1368	qr
    //   1101	1109	1368	qr
    //   1125	1136	1368	qr
    //   1139	1147	1368	qr
    //   43	49	1378	finally
    //   199	212	1378	finally
    //   227	233	1378	finally
    //   243	254	1378	finally
    //   301	312	1378	finally
    //   366	377	1378	finally
    //   433	444	1378	finally
    //   501	512	1378	finally
    //   569	580	1378	finally
    //   637	648	1378	finally
    //   696	702	1378	finally
    //   705	715	1378	finally
    //   718	724	1378	finally
    //   740	746	1378	finally
    //   749	759	1378	finally
    //   762	768	1378	finally
    //   784	790	1378	finally
    //   793	803	1378	finally
    //   806	812	1378	finally
    //   828	834	1378	finally
    //   837	848	1378	finally
    //   851	857	1378	finally
    //   873	885	1378	finally
    //   888	897	1378	finally
    //   900	915	1378	finally
    //   923	933	1378	finally
    //   936	945	1378	finally
    //   948	959	1378	finally
    //   975	986	1378	finally
    //   989	997	1378	finally
    //   1013	1019	1378	finally
    //   1033	1044	1378	finally
    //   1086	1098	1378	finally
    //   1101	1109	1378	finally
    //   1125	1136	1378	finally
    //   1139	1147	1378	finally
    //   1372	1378	1378	finally
    //   1575	1591	1378	finally
    //   43	49	1571	java/io/IOException
    //   199	212	1571	java/io/IOException
    //   227	233	1571	java/io/IOException
    //   243	254	1571	java/io/IOException
    //   301	312	1571	java/io/IOException
    //   366	377	1571	java/io/IOException
    //   433	444	1571	java/io/IOException
    //   501	512	1571	java/io/IOException
    //   569	580	1571	java/io/IOException
    //   637	648	1571	java/io/IOException
    //   696	702	1571	java/io/IOException
    //   705	715	1571	java/io/IOException
    //   718	724	1571	java/io/IOException
    //   740	746	1571	java/io/IOException
    //   749	759	1571	java/io/IOException
    //   762	768	1571	java/io/IOException
    //   784	790	1571	java/io/IOException
    //   793	803	1571	java/io/IOException
    //   806	812	1571	java/io/IOException
    //   828	834	1571	java/io/IOException
    //   837	848	1571	java/io/IOException
    //   851	857	1571	java/io/IOException
    //   873	885	1571	java/io/IOException
    //   888	897	1571	java/io/IOException
    //   900	915	1571	java/io/IOException
    //   923	933	1571	java/io/IOException
    //   936	945	1571	java/io/IOException
    //   948	959	1571	java/io/IOException
    //   975	986	1571	java/io/IOException
    //   989	997	1571	java/io/IOException
    //   1013	1019	1571	java/io/IOException
    //   1033	1044	1571	java/io/IOException
    //   1086	1098	1571	java/io/IOException
    //   1101	1109	1571	java/io/IOException
    //   1125	1136	1571	java/io/IOException
    //   1139	1147	1571	java/io/IOException
    //   1551	1556	1591	java/io/IOException
    //   1551	1556	1604	finally
    //   270	281	1616	finally
    //   328	346	1616	finally
    //   393	411	1616	finally
    //   461	479	1616	finally
    //   529	547	1616	finally
    //   597	615	1616	finally
    //   665	683	1616	finally
    //   1062	1073	1616	finally
    //   270	281	1623	java/io/IOException
    //   328	346	1623	java/io/IOException
    //   393	411	1623	java/io/IOException
    //   461	479	1623	java/io/IOException
    //   529	547	1623	java/io/IOException
    //   597	615	1623	java/io/IOException
    //   665	683	1623	java/io/IOException
    //   1062	1073	1623	java/io/IOException
    //   270	281	1630	qr
    //   328	346	1630	qr
    //   393	411	1630	qr
    //   461	479	1630	qr
    //   529	547	1630	qr
    //   597	615	1630	qr
    //   665	683	1630	qr
    //   1062	1073	1630	qr
  }
  
  private el(qh paramqh)
  {
    super(paramqh);
    d = paramqh.r();
  }
  
  private el(boolean paramBoolean)
  {
    d = pT.a;
  }
  
  public static en N()
  {
    return en.o();
  }
  
  private void S()
  {
    f = qt.a;
    g = Collections.emptyList();
    h = Collections.emptyList();
    i = Collections.emptyList();
    j = Collections.emptyList();
    k = Collections.emptyList();
    l = Collections.emptyList();
    m = "";
    n = "";
    o = "0";
    p = "";
    q = dX.a();
    r = 0.0F;
    s = false;
    t = qt.a;
    u = 0;
  }
  
  public static el a()
  {
    return c;
  }
  
  public static en a(el paramel)
  {
    return N().a(paramel);
  }
  
  public String A()
  {
    Object localObject = o;
    if ((localObject instanceof String)) {
      return (String)localObject;
    }
    localObject = (pT)localObject;
    String str = ((pT)localObject).f();
    if (((pT)localObject).g()) {
      o = str;
    }
    return str;
  }
  
  public boolean B()
  {
    return (e & 0x8) == 8;
  }
  
  public String C()
  {
    Object localObject = p;
    if ((localObject instanceof String)) {
      return (String)localObject;
    }
    localObject = (pT)localObject;
    String str = ((pT)localObject).f();
    if (((pT)localObject).g()) {
      p = str;
    }
    return str;
  }
  
  public boolean D()
  {
    return (e & 0x10) == 16;
  }
  
  public dX E()
  {
    return q;
  }
  
  public boolean F()
  {
    return (e & 0x20) == 32;
  }
  
  public float G()
  {
    return r;
  }
  
  public boolean H()
  {
    return (e & 0x40) == 64;
  }
  
  public boolean I()
  {
    return s;
  }
  
  public List<String> J()
  {
    return t;
  }
  
  public int K()
  {
    return t.size();
  }
  
  public boolean L()
  {
    return (e & 0x80) == 128;
  }
  
  public int M()
  {
    return u;
  }
  
  public en O()
  {
    return N();
  }
  
  public en P()
  {
    return a(this);
  }
  
  public ev a(int paramInt)
  {
    return (ev)g.get(paramInt);
  }
  
  public eh b(int paramInt)
  {
    return (eh)h.get(paramInt);
  }
  
  public el b()
  {
    return c;
  }
  
  public ed c(int paramInt)
  {
    return (ed)i.get(paramInt);
  }
  
  public qC<el> c()
  {
    return a;
  }
  
  public ed d(int paramInt)
  {
    return (ed)j.get(paramInt);
  }
  
  public List<String> d()
  {
    return f;
  }
  
  public int e()
  {
    return f.size();
  }
  
  public ed e(int paramInt)
  {
    return (ed)k.get(paramInt);
  }
  
  public boolean equals(Object paramObject)
  {
    if (paramObject == this) {
      return true;
    }
    if (!(paramObject instanceof el)) {
      return super.equals(paramObject);
    }
    paramObject = (el)paramObject;
    int i1;
    label43:
    label65:
    label87:
    label109:
    label131:
    label153:
    label175:
    label192:
    int i2;
    if (d().equals(((el)paramObject).d()))
    {
      i1 = 1;
      if ((i1 == 0) || (!f().equals(((el)paramObject).f()))) {
        break label567;
      }
      i1 = 1;
      if ((i1 == 0) || (!h().equals(((el)paramObject).h()))) {
        break label572;
      }
      i1 = 1;
      if ((i1 == 0) || (!k().equals(((el)paramObject).k()))) {
        break label577;
      }
      i1 = 1;
      if ((i1 == 0) || (!m().equals(((el)paramObject).m()))) {
        break label582;
      }
      i1 = 1;
      if ((i1 == 0) || (!r().equals(((el)paramObject).r()))) {
        break label587;
      }
      i1 = 1;
      if ((i1 == 0) || (!t().equals(((el)paramObject).t()))) {
        break label592;
      }
      i1 = 1;
      if ((i1 == 0) || (v() != ((el)paramObject).v())) {
        break label597;
      }
      i1 = 1;
      i2 = i1;
      if (v())
      {
        if ((i1 == 0) || (!w().equals(((el)paramObject).w()))) {
          break label602;
        }
        i2 = 1;
      }
      label221:
      if ((i2 == 0) || (x() != ((el)paramObject).x())) {
        break label607;
      }
      i1 = 1;
      label238:
      i2 = i1;
      if (x())
      {
        if ((i1 == 0) || (!y().equals(((el)paramObject).y()))) {
          break label612;
        }
        i2 = 1;
      }
      label267:
      if ((i2 == 0) || (z() != ((el)paramObject).z())) {
        break label617;
      }
      i1 = 1;
      label284:
      i2 = i1;
      if (z())
      {
        if ((i1 == 0) || (!A().equals(((el)paramObject).A()))) {
          break label622;
        }
        i2 = 1;
      }
      label313:
      if ((i2 == 0) || (B() != ((el)paramObject).B())) {
        break label627;
      }
      i1 = 1;
      label330:
      i2 = i1;
      if (B())
      {
        if ((i1 == 0) || (!C().equals(((el)paramObject).C()))) {
          break label632;
        }
        i2 = 1;
      }
      label359:
      if ((i2 == 0) || (D() != ((el)paramObject).D())) {
        break label637;
      }
      i1 = 1;
      label376:
      i2 = i1;
      if (D())
      {
        if ((i1 == 0) || (!E().equals(((el)paramObject).E()))) {
          break label642;
        }
        i2 = 1;
      }
      label405:
      if ((i2 == 0) || (F() != ((el)paramObject).F())) {
        break label647;
      }
      i1 = 1;
      label422:
      i2 = i1;
      if (F())
      {
        if ((i1 == 0) || (Float.floatToIntBits(G()) != Float.floatToIntBits(((el)paramObject).G()))) {
          break label652;
        }
        i2 = 1;
      }
      label454:
      if ((i2 == 0) || (H() != ((el)paramObject).H())) {
        break label657;
      }
      i1 = 1;
      label471:
      i2 = i1;
      if (H())
      {
        if ((i1 == 0) || (I() != ((el)paramObject).I())) {
          break label662;
        }
        i2 = 1;
      }
      label497:
      if ((i2 == 0) || (!J().equals(((el)paramObject).J()))) {
        break label667;
      }
      i1 = 1;
      label519:
      if ((i1 == 0) || (L() != ((el)paramObject).L())) {
        break label672;
      }
    }
    label567:
    label572:
    label577:
    label582:
    label587:
    label592:
    label597:
    label602:
    label607:
    label612:
    label617:
    label622:
    label627:
    label632:
    label637:
    label642:
    label647:
    label652:
    label657:
    label662:
    label667:
    label672:
    for (boolean bool = true;; bool = false)
    {
      if (!L()) {
        break label678;
      }
      if ((bool) && (M() == ((el)paramObject).M())) {
        break;
      }
      return false;
      i1 = 0;
      break label43;
      i1 = 0;
      break label65;
      i1 = 0;
      break label87;
      i1 = 0;
      break label109;
      i1 = 0;
      break label131;
      i1 = 0;
      break label153;
      i1 = 0;
      break label175;
      i1 = 0;
      break label192;
      i2 = 0;
      break label221;
      i1 = 0;
      break label238;
      i2 = 0;
      break label267;
      i1 = 0;
      break label284;
      i2 = 0;
      break label313;
      i1 = 0;
      break label330;
      i2 = 0;
      break label359;
      i1 = 0;
      break label376;
      i2 = 0;
      break label405;
      i1 = 0;
      break label422;
      i2 = 0;
      break label454;
      i1 = 0;
      break label471;
      i2 = 0;
      break label497;
      i1 = 0;
      break label519;
    }
    label678:
    return bool;
  }
  
  public List<ev> f()
  {
    return g;
  }
  
  public int g()
  {
    return g.size();
  }
  
  public List<eh> h()
  {
    return h;
  }
  
  public int hashCode()
  {
    if (b != 0) {
      return b;
    }
    int i2 = el.class.hashCode() + 779;
    int i1 = i2;
    if (e() > 0) {
      i1 = (i2 * 37 + 1) * 53 + d().hashCode();
    }
    i2 = i1;
    if (g() > 0) {
      i2 = (i1 * 37 + 2) * 53 + f().hashCode();
    }
    i1 = i2;
    if (i() > 0) {
      i1 = (i2 * 37 + 3) * 53 + h().hashCode();
    }
    i2 = i1;
    if (l() > 0) {
      i2 = (i1 * 37 + 4) * 53 + k().hashCode();
    }
    i1 = i2;
    if (q() > 0) {
      i1 = (i2 * 37 + 5) * 53 + m().hashCode();
    }
    i2 = i1;
    if (s() > 0) {
      i2 = (i1 * 37 + 6) * 53 + r().hashCode();
    }
    i1 = i2;
    if (u() > 0) {
      i1 = (i2 * 37 + 7) * 53 + t().hashCode();
    }
    i2 = i1;
    if (v()) {
      i2 = (i1 * 37 + 9) * 53 + w().hashCode();
    }
    i1 = i2;
    if (x()) {
      i1 = (i2 * 37 + 10) * 53 + y().hashCode();
    }
    i2 = i1;
    if (z()) {
      i2 = (i1 * 37 + 12) * 53 + A().hashCode();
    }
    i1 = i2;
    if (B()) {
      i1 = (i2 * 37 + 13) * 53 + C().hashCode();
    }
    i2 = i1;
    if (D()) {
      i2 = (i1 * 37 + 14) * 53 + E().hashCode();
    }
    i1 = i2;
    if (F()) {
      i1 = (i2 * 37 + 15) * 53 + Float.floatToIntBits(G());
    }
    i2 = i1;
    if (H()) {
      i2 = (i1 * 37 + 18) * 53 + qo.a(I());
    }
    i1 = i2;
    if (K() > 0) {
      i1 = (i2 * 37 + 16) * 53 + J().hashCode();
    }
    i2 = i1;
    if (L()) {
      i2 = (i1 * 37 + 17) * 53 + M();
    }
    i1 = i2 * 29 + d.hashCode();
    b = i1;
    return i1;
  }
  
  public int i()
  {
    return h.size();
  }
  
  public final boolean j()
  {
    boolean bool = true;
    int i1 = v;
    if (i1 != -1)
    {
      if (i1 == 1) {}
      for (;;)
      {
        return bool;
        bool = false;
      }
    }
    i1 = 0;
    while (i1 < g())
    {
      if (!a(i1).j())
      {
        v = 0;
        return false;
      }
      i1 += 1;
    }
    i1 = 0;
    while (i1 < i())
    {
      if (!b(i1).j())
      {
        v = 0;
        return false;
      }
      i1 += 1;
    }
    i1 = 0;
    while (i1 < l())
    {
      if (!c(i1).j())
      {
        v = 0;
        return false;
      }
      i1 += 1;
    }
    i1 = 0;
    while (i1 < q())
    {
      if (!d(i1).j())
      {
        v = 0;
        return false;
      }
      i1 += 1;
    }
    i1 = 0;
    while (i1 < s())
    {
      if (!e(i1).j())
      {
        v = 0;
        return false;
      }
      i1 += 1;
    }
    v = 1;
    return true;
  }
  
  public List<ed> k()
  {
    return i;
  }
  
  public int l()
  {
    return i.size();
  }
  
  public List<ed> m()
  {
    return j;
  }
  
  public int q()
  {
    return j.size();
  }
  
  public List<ed> r()
  {
    return k;
  }
  
  public int s()
  {
    return k.size();
  }
  
  public List<ep> t()
  {
    return l;
  }
  
  public int u()
  {
    return l.size();
  }
  
  public boolean v()
  {
    return (e & 0x1) == 1;
  }
  
  public String w()
  {
    Object localObject = m;
    if ((localObject instanceof String)) {
      return (String)localObject;
    }
    localObject = (pT)localObject;
    String str = ((pT)localObject).f();
    if (((pT)localObject).g()) {
      m = str;
    }
    return str;
  }
  
  public boolean x()
  {
    return (e & 0x2) == 2;
  }
  
  public String y()
  {
    Object localObject = n;
    if ((localObject instanceof String)) {
      return (String)localObject;
    }
    localObject = (pT)localObject;
    String str = ((pT)localObject).f();
    if (((pT)localObject).g()) {
      n = str;
    }
    return str;
  }
  
  public boolean z()
  {
    return (e & 0x4) == 4;
  }
}

/* Location:
 * Qualified Name:     el
 * Java Class Version: 6 (50.0)
 * JD-Core Version:    0.7.1
 */