import java.util.Collections;
import java.util.List;

public final class el
  extends qi
  implements eo
{
  public static qF<el> a = new em();
  private static final el c;
  private static volatile qE q = null;
  private final pW d;
  private List<Integer> e;
  private List<Integer> f;
  private List<Integer> g;
  private List<Integer> h;
  private List<Integer> i;
  private List<Integer> j;
  private List<Integer> k;
  private List<Integer> l;
  private List<Integer> m;
  private List<Integer> n;
  private byte o = -1;
  private int p = -1;
  
  static
  {
    c = new el(true);
    c.E();
  }
  
  /* Error */
  private el(pZ parampZ, qd paramqd)
  {
    // Byte code:
    //   0: aload_0
    //   1: invokespecial 57	qi:<init>	()V
    //   4: aload_0
    //   5: iconst_m1
    //   6: putfield 59	el:o	B
    //   9: aload_0
    //   10: iconst_m1
    //   11: putfield 61	el:p	I
    //   14: aload_0
    //   15: invokespecial 50	el:E	()V
    //   18: iconst_0
    //   19: istore_3
    //   20: invokestatic 66	pW:i	()LpY;
    //   23: astore 10
    //   25: aload 10
    //   27: invokestatic 71	qb:a	(Ljava/io/OutputStream;)Lqb;
    //   30: astore 11
    //   32: iconst_0
    //   33: istore 8
    //   35: iload 8
    //   37: ifne +2730 -> 2767
    //   40: iload_3
    //   41: istore 5
    //   43: iload_3
    //   44: istore 4
    //   46: iload_3
    //   47: istore 6
    //   49: aload_1
    //   50: invokevirtual 76	pZ:a	()I
    //   53: istore 7
    //   55: iload 7
    //   57: lookupswitch	default:+2979->3036, 0:+2982->3039, 8:+207->264, 10:+519->576, 16:+688->745, 18:+758->815, 24:+906->963, 26:+976->1033, 32:+1124->1181, 34:+1197->1254, 40:+1348->1405, 42:+1421->1478, 48:+1572->1629, 50:+1645->1702, 56:+1796->1853, 58:+1869->1926, 64:+2020->2077, 66:+2096->2153, 72:+2250->2307, 74:+2326->2383, 80:+2480->2537, 82:+2556->2613
    //   236: iload_3
    //   237: istore 5
    //   239: iload_3
    //   240: istore 4
    //   242: iload_3
    //   243: istore 6
    //   245: aload_0
    //   246: aload_1
    //   247: aload 11
    //   249: aload_2
    //   250: iload 7
    //   252: invokevirtual 79	el:a	(LpZ;Lqb;Lqd;I)Z
    //   255: ifne -220 -> 35
    //   258: iconst_1
    //   259: istore 8
    //   261: goto -226 -> 35
    //   264: iload_3
    //   265: istore 7
    //   267: iload_3
    //   268: iconst_1
    //   269: iand
    //   270: iconst_1
    //   271: if_icmpeq +28 -> 299
    //   274: iload_3
    //   275: istore 5
    //   277: iload_3
    //   278: istore 4
    //   280: iload_3
    //   281: istore 6
    //   283: aload_0
    //   284: new 81	java/util/ArrayList
    //   287: dup
    //   288: invokespecial 82	java/util/ArrayList:<init>	()V
    //   291: putfield 84	el:e	Ljava/util/List;
    //   294: iload_3
    //   295: iconst_1
    //   296: ior
    //   297: istore 7
    //   299: iload 7
    //   301: istore 5
    //   303: iload 7
    //   305: istore 4
    //   307: iload 7
    //   309: istore 6
    //   311: aload_0
    //   312: getfield 84	el:e	Ljava/util/List;
    //   315: aload_1
    //   316: invokevirtual 86	pZ:f	()I
    //   319: invokestatic 92	java/lang/Integer:valueOf	(I)Ljava/lang/Integer;
    //   322: invokeinterface 98 2 0
    //   327: pop
    //   328: iload 7
    //   330: istore_3
    //   331: goto -296 -> 35
    //   334: astore_1
    //   335: iload 5
    //   337: istore 4
    //   339: aload_1
    //   340: aload_0
    //   341: invokevirtual 101	qu:a	(LqB;)Lqu;
    //   344: athrow
    //   345: astore_1
    //   346: iload 4
    //   348: iconst_1
    //   349: iand
    //   350: iconst_1
    //   351: if_icmpne +14 -> 365
    //   354: aload_0
    //   355: aload_0
    //   356: getfield 84	el:e	Ljava/util/List;
    //   359: invokestatic 107	java/util/Collections:unmodifiableList	(Ljava/util/List;)Ljava/util/List;
    //   362: putfield 84	el:e	Ljava/util/List;
    //   365: iload 4
    //   367: iconst_2
    //   368: iand
    //   369: iconst_2
    //   370: if_icmpne +14 -> 384
    //   373: aload_0
    //   374: aload_0
    //   375: getfield 109	el:f	Ljava/util/List;
    //   378: invokestatic 107	java/util/Collections:unmodifiableList	(Ljava/util/List;)Ljava/util/List;
    //   381: putfield 109	el:f	Ljava/util/List;
    //   384: iload 4
    //   386: iconst_4
    //   387: iand
    //   388: iconst_4
    //   389: if_icmpne +14 -> 403
    //   392: aload_0
    //   393: aload_0
    //   394: getfield 111	el:g	Ljava/util/List;
    //   397: invokestatic 107	java/util/Collections:unmodifiableList	(Ljava/util/List;)Ljava/util/List;
    //   400: putfield 111	el:g	Ljava/util/List;
    //   403: iload 4
    //   405: bipush 8
    //   407: iand
    //   408: bipush 8
    //   410: if_icmpne +14 -> 424
    //   413: aload_0
    //   414: aload_0
    //   415: getfield 113	el:h	Ljava/util/List;
    //   418: invokestatic 107	java/util/Collections:unmodifiableList	(Ljava/util/List;)Ljava/util/List;
    //   421: putfield 113	el:h	Ljava/util/List;
    //   424: iload 4
    //   426: bipush 16
    //   428: iand
    //   429: bipush 16
    //   431: if_icmpne +14 -> 445
    //   434: aload_0
    //   435: aload_0
    //   436: getfield 115	el:i	Ljava/util/List;
    //   439: invokestatic 107	java/util/Collections:unmodifiableList	(Ljava/util/List;)Ljava/util/List;
    //   442: putfield 115	el:i	Ljava/util/List;
    //   445: iload 4
    //   447: bipush 32
    //   449: iand
    //   450: bipush 32
    //   452: if_icmpne +14 -> 466
    //   455: aload_0
    //   456: aload_0
    //   457: getfield 117	el:j	Ljava/util/List;
    //   460: invokestatic 107	java/util/Collections:unmodifiableList	(Ljava/util/List;)Ljava/util/List;
    //   463: putfield 117	el:j	Ljava/util/List;
    //   466: iload 4
    //   468: bipush 64
    //   470: iand
    //   471: bipush 64
    //   473: if_icmpne +14 -> 487
    //   476: aload_0
    //   477: aload_0
    //   478: getfield 119	el:k	Ljava/util/List;
    //   481: invokestatic 107	java/util/Collections:unmodifiableList	(Ljava/util/List;)Ljava/util/List;
    //   484: putfield 119	el:k	Ljava/util/List;
    //   487: iload 4
    //   489: sipush 128
    //   492: iand
    //   493: sipush 128
    //   496: if_icmpne +14 -> 510
    //   499: aload_0
    //   500: aload_0
    //   501: getfield 121	el:l	Ljava/util/List;
    //   504: invokestatic 107	java/util/Collections:unmodifiableList	(Ljava/util/List;)Ljava/util/List;
    //   507: putfield 121	el:l	Ljava/util/List;
    //   510: iload 4
    //   512: sipush 256
    //   515: iand
    //   516: sipush 256
    //   519: if_icmpne +14 -> 533
    //   522: aload_0
    //   523: aload_0
    //   524: getfield 123	el:m	Ljava/util/List;
    //   527: invokestatic 107	java/util/Collections:unmodifiableList	(Ljava/util/List;)Ljava/util/List;
    //   530: putfield 123	el:m	Ljava/util/List;
    //   533: iload 4
    //   535: sipush 512
    //   538: iand
    //   539: sipush 512
    //   542: if_icmpne +14 -> 556
    //   545: aload_0
    //   546: aload_0
    //   547: getfield 125	el:n	Ljava/util/List;
    //   550: invokestatic 107	java/util/Collections:unmodifiableList	(Ljava/util/List;)Ljava/util/List;
    //   553: putfield 125	el:n	Ljava/util/List;
    //   556: aload 11
    //   558: invokevirtual 127	qb:a	()V
    //   561: aload_0
    //   562: aload 10
    //   564: invokevirtual 132	pY:a	()LpW;
    //   567: putfield 134	el:d	LpW;
    //   570: aload_0
    //   571: invokevirtual 137	el:R	()V
    //   574: aload_1
    //   575: athrow
    //   576: iload_3
    //   577: istore 5
    //   579: iload_3
    //   580: istore 4
    //   582: iload_3
    //   583: istore 6
    //   585: aload_1
    //   586: aload_1
    //   587: invokevirtual 140	pZ:s	()I
    //   590: invokevirtual 143	pZ:c	(I)I
    //   593: istore 9
    //   595: iload_3
    //   596: istore 7
    //   598: iload_3
    //   599: iconst_1
    //   600: iand
    //   601: iconst_1
    //   602: if_icmpeq +47 -> 649
    //   605: iload_3
    //   606: istore 5
    //   608: iload_3
    //   609: istore 4
    //   611: iload_3
    //   612: istore 7
    //   614: iload_3
    //   615: istore 6
    //   617: aload_1
    //   618: invokevirtual 146	pZ:w	()I
    //   621: ifle +28 -> 649
    //   624: iload_3
    //   625: istore 5
    //   627: iload_3
    //   628: istore 4
    //   630: iload_3
    //   631: istore 6
    //   633: aload_0
    //   634: new 81	java/util/ArrayList
    //   637: dup
    //   638: invokespecial 82	java/util/ArrayList:<init>	()V
    //   641: putfield 84	el:e	Ljava/util/List;
    //   644: iload_3
    //   645: iconst_1
    //   646: ior
    //   647: istore 7
    //   649: iload 7
    //   651: istore 5
    //   653: iload 7
    //   655: istore 4
    //   657: iload 7
    //   659: istore 6
    //   661: aload_1
    //   662: invokevirtual 146	pZ:w	()I
    //   665: ifle +56 -> 721
    //   668: iload 7
    //   670: istore 5
    //   672: iload 7
    //   674: istore 4
    //   676: iload 7
    //   678: istore 6
    //   680: aload_0
    //   681: getfield 84	el:e	Ljava/util/List;
    //   684: aload_1
    //   685: invokevirtual 86	pZ:f	()I
    //   688: invokestatic 92	java/lang/Integer:valueOf	(I)Ljava/lang/Integer;
    //   691: invokeinterface 98 2 0
    //   696: pop
    //   697: goto -48 -> 649
    //   700: astore_1
    //   701: iload 6
    //   703: istore 4
    //   705: new 54	qu
    //   708: dup
    //   709: aload_1
    //   710: invokevirtual 150	java/io/IOException:getMessage	()Ljava/lang/String;
    //   713: invokespecial 153	qu:<init>	(Ljava/lang/String;)V
    //   716: aload_0
    //   717: invokevirtual 101	qu:a	(LqB;)Lqu;
    //   720: athrow
    //   721: iload 7
    //   723: istore 5
    //   725: iload 7
    //   727: istore 4
    //   729: iload 7
    //   731: istore 6
    //   733: aload_1
    //   734: iload 9
    //   736: invokevirtual 156	pZ:d	(I)V
    //   739: iload 7
    //   741: istore_3
    //   742: goto -707 -> 35
    //   745: iload_3
    //   746: istore 7
    //   748: iload_3
    //   749: iconst_2
    //   750: iand
    //   751: iconst_2
    //   752: if_icmpeq +28 -> 780
    //   755: iload_3
    //   756: istore 5
    //   758: iload_3
    //   759: istore 4
    //   761: iload_3
    //   762: istore 6
    //   764: aload_0
    //   765: new 81	java/util/ArrayList
    //   768: dup
    //   769: invokespecial 82	java/util/ArrayList:<init>	()V
    //   772: putfield 109	el:f	Ljava/util/List;
    //   775: iload_3
    //   776: iconst_2
    //   777: ior
    //   778: istore 7
    //   780: iload 7
    //   782: istore 5
    //   784: iload 7
    //   786: istore 4
    //   788: iload 7
    //   790: istore 6
    //   792: aload_0
    //   793: getfield 109	el:f	Ljava/util/List;
    //   796: aload_1
    //   797: invokevirtual 86	pZ:f	()I
    //   800: invokestatic 92	java/lang/Integer:valueOf	(I)Ljava/lang/Integer;
    //   803: invokeinterface 98 2 0
    //   808: pop
    //   809: iload 7
    //   811: istore_3
    //   812: goto -777 -> 35
    //   815: iload_3
    //   816: istore 5
    //   818: iload_3
    //   819: istore 4
    //   821: iload_3
    //   822: istore 6
    //   824: aload_1
    //   825: aload_1
    //   826: invokevirtual 140	pZ:s	()I
    //   829: invokevirtual 143	pZ:c	(I)I
    //   832: istore 9
    //   834: iload_3
    //   835: istore 7
    //   837: iload_3
    //   838: iconst_2
    //   839: iand
    //   840: iconst_2
    //   841: if_icmpeq +47 -> 888
    //   844: iload_3
    //   845: istore 5
    //   847: iload_3
    //   848: istore 4
    //   850: iload_3
    //   851: istore 6
    //   853: iload_3
    //   854: istore 7
    //   856: aload_1
    //   857: invokevirtual 146	pZ:w	()I
    //   860: ifle +28 -> 888
    //   863: iload_3
    //   864: istore 5
    //   866: iload_3
    //   867: istore 4
    //   869: iload_3
    //   870: istore 6
    //   872: aload_0
    //   873: new 81	java/util/ArrayList
    //   876: dup
    //   877: invokespecial 82	java/util/ArrayList:<init>	()V
    //   880: putfield 109	el:f	Ljava/util/List;
    //   883: iload_3
    //   884: iconst_2
    //   885: ior
    //   886: istore 7
    //   888: iload 7
    //   890: istore 5
    //   892: iload 7
    //   894: istore 4
    //   896: iload 7
    //   898: istore 6
    //   900: aload_1
    //   901: invokevirtual 146	pZ:w	()I
    //   904: ifle +35 -> 939
    //   907: iload 7
    //   909: istore 5
    //   911: iload 7
    //   913: istore 4
    //   915: iload 7
    //   917: istore 6
    //   919: aload_0
    //   920: getfield 109	el:f	Ljava/util/List;
    //   923: aload_1
    //   924: invokevirtual 86	pZ:f	()I
    //   927: invokestatic 92	java/lang/Integer:valueOf	(I)Ljava/lang/Integer;
    //   930: invokeinterface 98 2 0
    //   935: pop
    //   936: goto -48 -> 888
    //   939: iload 7
    //   941: istore 5
    //   943: iload 7
    //   945: istore 4
    //   947: iload 7
    //   949: istore 6
    //   951: aload_1
    //   952: iload 9
    //   954: invokevirtual 156	pZ:d	(I)V
    //   957: iload 7
    //   959: istore_3
    //   960: goto -925 -> 35
    //   963: iload_3
    //   964: istore 7
    //   966: iload_3
    //   967: iconst_4
    //   968: iand
    //   969: iconst_4
    //   970: if_icmpeq +28 -> 998
    //   973: iload_3
    //   974: istore 5
    //   976: iload_3
    //   977: istore 4
    //   979: iload_3
    //   980: istore 6
    //   982: aload_0
    //   983: new 81	java/util/ArrayList
    //   986: dup
    //   987: invokespecial 82	java/util/ArrayList:<init>	()V
    //   990: putfield 111	el:g	Ljava/util/List;
    //   993: iload_3
    //   994: iconst_4
    //   995: ior
    //   996: istore 7
    //   998: iload 7
    //   1000: istore 5
    //   1002: iload 7
    //   1004: istore 4
    //   1006: iload 7
    //   1008: istore 6
    //   1010: aload_0
    //   1011: getfield 111	el:g	Ljava/util/List;
    //   1014: aload_1
    //   1015: invokevirtual 86	pZ:f	()I
    //   1018: invokestatic 92	java/lang/Integer:valueOf	(I)Ljava/lang/Integer;
    //   1021: invokeinterface 98 2 0
    //   1026: pop
    //   1027: iload 7
    //   1029: istore_3
    //   1030: goto -995 -> 35
    //   1033: iload_3
    //   1034: istore 5
    //   1036: iload_3
    //   1037: istore 4
    //   1039: iload_3
    //   1040: istore 6
    //   1042: aload_1
    //   1043: aload_1
    //   1044: invokevirtual 140	pZ:s	()I
    //   1047: invokevirtual 143	pZ:c	(I)I
    //   1050: istore 9
    //   1052: iload_3
    //   1053: istore 7
    //   1055: iload_3
    //   1056: iconst_4
    //   1057: iand
    //   1058: iconst_4
    //   1059: if_icmpeq +47 -> 1106
    //   1062: iload_3
    //   1063: istore 5
    //   1065: iload_3
    //   1066: istore 4
    //   1068: iload_3
    //   1069: istore 6
    //   1071: iload_3
    //   1072: istore 7
    //   1074: aload_1
    //   1075: invokevirtual 146	pZ:w	()I
    //   1078: ifle +28 -> 1106
    //   1081: iload_3
    //   1082: istore 5
    //   1084: iload_3
    //   1085: istore 4
    //   1087: iload_3
    //   1088: istore 6
    //   1090: aload_0
    //   1091: new 81	java/util/ArrayList
    //   1094: dup
    //   1095: invokespecial 82	java/util/ArrayList:<init>	()V
    //   1098: putfield 111	el:g	Ljava/util/List;
    //   1101: iload_3
    //   1102: iconst_4
    //   1103: ior
    //   1104: istore 7
    //   1106: iload 7
    //   1108: istore 5
    //   1110: iload 7
    //   1112: istore 4
    //   1114: iload 7
    //   1116: istore 6
    //   1118: aload_1
    //   1119: invokevirtual 146	pZ:w	()I
    //   1122: ifle +35 -> 1157
    //   1125: iload 7
    //   1127: istore 5
    //   1129: iload 7
    //   1131: istore 4
    //   1133: iload 7
    //   1135: istore 6
    //   1137: aload_0
    //   1138: getfield 111	el:g	Ljava/util/List;
    //   1141: aload_1
    //   1142: invokevirtual 86	pZ:f	()I
    //   1145: invokestatic 92	java/lang/Integer:valueOf	(I)Ljava/lang/Integer;
    //   1148: invokeinterface 98 2 0
    //   1153: pop
    //   1154: goto -48 -> 1106
    //   1157: iload 7
    //   1159: istore 5
    //   1161: iload 7
    //   1163: istore 4
    //   1165: iload 7
    //   1167: istore 6
    //   1169: aload_1
    //   1170: iload 9
    //   1172: invokevirtual 156	pZ:d	(I)V
    //   1175: iload 7
    //   1177: istore_3
    //   1178: goto -1143 -> 35
    //   1181: iload_3
    //   1182: istore 7
    //   1184: iload_3
    //   1185: bipush 8
    //   1187: iand
    //   1188: bipush 8
    //   1190: if_icmpeq +29 -> 1219
    //   1193: iload_3
    //   1194: istore 5
    //   1196: iload_3
    //   1197: istore 4
    //   1199: iload_3
    //   1200: istore 6
    //   1202: aload_0
    //   1203: new 81	java/util/ArrayList
    //   1206: dup
    //   1207: invokespecial 82	java/util/ArrayList:<init>	()V
    //   1210: putfield 113	el:h	Ljava/util/List;
    //   1213: iload_3
    //   1214: bipush 8
    //   1216: ior
    //   1217: istore 7
    //   1219: iload 7
    //   1221: istore 5
    //   1223: iload 7
    //   1225: istore 4
    //   1227: iload 7
    //   1229: istore 6
    //   1231: aload_0
    //   1232: getfield 113	el:h	Ljava/util/List;
    //   1235: aload_1
    //   1236: invokevirtual 86	pZ:f	()I
    //   1239: invokestatic 92	java/lang/Integer:valueOf	(I)Ljava/lang/Integer;
    //   1242: invokeinterface 98 2 0
    //   1247: pop
    //   1248: iload 7
    //   1250: istore_3
    //   1251: goto -1216 -> 35
    //   1254: iload_3
    //   1255: istore 5
    //   1257: iload_3
    //   1258: istore 4
    //   1260: iload_3
    //   1261: istore 6
    //   1263: aload_1
    //   1264: aload_1
    //   1265: invokevirtual 140	pZ:s	()I
    //   1268: invokevirtual 143	pZ:c	(I)I
    //   1271: istore 9
    //   1273: iload_3
    //   1274: istore 7
    //   1276: iload_3
    //   1277: bipush 8
    //   1279: iand
    //   1280: bipush 8
    //   1282: if_icmpeq +48 -> 1330
    //   1285: iload_3
    //   1286: istore 5
    //   1288: iload_3
    //   1289: istore 4
    //   1291: iload_3
    //   1292: istore 6
    //   1294: iload_3
    //   1295: istore 7
    //   1297: aload_1
    //   1298: invokevirtual 146	pZ:w	()I
    //   1301: ifle +29 -> 1330
    //   1304: iload_3
    //   1305: istore 5
    //   1307: iload_3
    //   1308: istore 4
    //   1310: iload_3
    //   1311: istore 6
    //   1313: aload_0
    //   1314: new 81	java/util/ArrayList
    //   1317: dup
    //   1318: invokespecial 82	java/util/ArrayList:<init>	()V
    //   1321: putfield 113	el:h	Ljava/util/List;
    //   1324: iload_3
    //   1325: bipush 8
    //   1327: ior
    //   1328: istore 7
    //   1330: iload 7
    //   1332: istore 5
    //   1334: iload 7
    //   1336: istore 4
    //   1338: iload 7
    //   1340: istore 6
    //   1342: aload_1
    //   1343: invokevirtual 146	pZ:w	()I
    //   1346: ifle +35 -> 1381
    //   1349: iload 7
    //   1351: istore 5
    //   1353: iload 7
    //   1355: istore 4
    //   1357: iload 7
    //   1359: istore 6
    //   1361: aload_0
    //   1362: getfield 113	el:h	Ljava/util/List;
    //   1365: aload_1
    //   1366: invokevirtual 86	pZ:f	()I
    //   1369: invokestatic 92	java/lang/Integer:valueOf	(I)Ljava/lang/Integer;
    //   1372: invokeinterface 98 2 0
    //   1377: pop
    //   1378: goto -48 -> 1330
    //   1381: iload 7
    //   1383: istore 5
    //   1385: iload 7
    //   1387: istore 4
    //   1389: iload 7
    //   1391: istore 6
    //   1393: aload_1
    //   1394: iload 9
    //   1396: invokevirtual 156	pZ:d	(I)V
    //   1399: iload 7
    //   1401: istore_3
    //   1402: goto -1367 -> 35
    //   1405: iload_3
    //   1406: istore 7
    //   1408: iload_3
    //   1409: bipush 16
    //   1411: iand
    //   1412: bipush 16
    //   1414: if_icmpeq +29 -> 1443
    //   1417: iload_3
    //   1418: istore 5
    //   1420: iload_3
    //   1421: istore 4
    //   1423: iload_3
    //   1424: istore 6
    //   1426: aload_0
    //   1427: new 81	java/util/ArrayList
    //   1430: dup
    //   1431: invokespecial 82	java/util/ArrayList:<init>	()V
    //   1434: putfield 115	el:i	Ljava/util/List;
    //   1437: iload_3
    //   1438: bipush 16
    //   1440: ior
    //   1441: istore 7
    //   1443: iload 7
    //   1445: istore 5
    //   1447: iload 7
    //   1449: istore 4
    //   1451: iload 7
    //   1453: istore 6
    //   1455: aload_0
    //   1456: getfield 115	el:i	Ljava/util/List;
    //   1459: aload_1
    //   1460: invokevirtual 86	pZ:f	()I
    //   1463: invokestatic 92	java/lang/Integer:valueOf	(I)Ljava/lang/Integer;
    //   1466: invokeinterface 98 2 0
    //   1471: pop
    //   1472: iload 7
    //   1474: istore_3
    //   1475: goto -1440 -> 35
    //   1478: iload_3
    //   1479: istore 5
    //   1481: iload_3
    //   1482: istore 4
    //   1484: iload_3
    //   1485: istore 6
    //   1487: aload_1
    //   1488: aload_1
    //   1489: invokevirtual 140	pZ:s	()I
    //   1492: invokevirtual 143	pZ:c	(I)I
    //   1495: istore 9
    //   1497: iload_3
    //   1498: istore 7
    //   1500: iload_3
    //   1501: bipush 16
    //   1503: iand
    //   1504: bipush 16
    //   1506: if_icmpeq +48 -> 1554
    //   1509: iload_3
    //   1510: istore 5
    //   1512: iload_3
    //   1513: istore 4
    //   1515: iload_3
    //   1516: istore 6
    //   1518: iload_3
    //   1519: istore 7
    //   1521: aload_1
    //   1522: invokevirtual 146	pZ:w	()I
    //   1525: ifle +29 -> 1554
    //   1528: iload_3
    //   1529: istore 5
    //   1531: iload_3
    //   1532: istore 4
    //   1534: iload_3
    //   1535: istore 6
    //   1537: aload_0
    //   1538: new 81	java/util/ArrayList
    //   1541: dup
    //   1542: invokespecial 82	java/util/ArrayList:<init>	()V
    //   1545: putfield 115	el:i	Ljava/util/List;
    //   1548: iload_3
    //   1549: bipush 16
    //   1551: ior
    //   1552: istore 7
    //   1554: iload 7
    //   1556: istore 5
    //   1558: iload 7
    //   1560: istore 4
    //   1562: iload 7
    //   1564: istore 6
    //   1566: aload_1
    //   1567: invokevirtual 146	pZ:w	()I
    //   1570: ifle +35 -> 1605
    //   1573: iload 7
    //   1575: istore 5
    //   1577: iload 7
    //   1579: istore 4
    //   1581: iload 7
    //   1583: istore 6
    //   1585: aload_0
    //   1586: getfield 115	el:i	Ljava/util/List;
    //   1589: aload_1
    //   1590: invokevirtual 86	pZ:f	()I
    //   1593: invokestatic 92	java/lang/Integer:valueOf	(I)Ljava/lang/Integer;
    //   1596: invokeinterface 98 2 0
    //   1601: pop
    //   1602: goto -48 -> 1554
    //   1605: iload 7
    //   1607: istore 5
    //   1609: iload 7
    //   1611: istore 4
    //   1613: iload 7
    //   1615: istore 6
    //   1617: aload_1
    //   1618: iload 9
    //   1620: invokevirtual 156	pZ:d	(I)V
    //   1623: iload 7
    //   1625: istore_3
    //   1626: goto -1591 -> 35
    //   1629: iload_3
    //   1630: istore 7
    //   1632: iload_3
    //   1633: bipush 32
    //   1635: iand
    //   1636: bipush 32
    //   1638: if_icmpeq +29 -> 1667
    //   1641: iload_3
    //   1642: istore 5
    //   1644: iload_3
    //   1645: istore 4
    //   1647: iload_3
    //   1648: istore 6
    //   1650: aload_0
    //   1651: new 81	java/util/ArrayList
    //   1654: dup
    //   1655: invokespecial 82	java/util/ArrayList:<init>	()V
    //   1658: putfield 117	el:j	Ljava/util/List;
    //   1661: iload_3
    //   1662: bipush 32
    //   1664: ior
    //   1665: istore 7
    //   1667: iload 7
    //   1669: istore 5
    //   1671: iload 7
    //   1673: istore 4
    //   1675: iload 7
    //   1677: istore 6
    //   1679: aload_0
    //   1680: getfield 117	el:j	Ljava/util/List;
    //   1683: aload_1
    //   1684: invokevirtual 86	pZ:f	()I
    //   1687: invokestatic 92	java/lang/Integer:valueOf	(I)Ljava/lang/Integer;
    //   1690: invokeinterface 98 2 0
    //   1695: pop
    //   1696: iload 7
    //   1698: istore_3
    //   1699: goto -1664 -> 35
    //   1702: iload_3
    //   1703: istore 5
    //   1705: iload_3
    //   1706: istore 4
    //   1708: iload_3
    //   1709: istore 6
    //   1711: aload_1
    //   1712: aload_1
    //   1713: invokevirtual 140	pZ:s	()I
    //   1716: invokevirtual 143	pZ:c	(I)I
    //   1719: istore 9
    //   1721: iload_3
    //   1722: istore 7
    //   1724: iload_3
    //   1725: bipush 32
    //   1727: iand
    //   1728: bipush 32
    //   1730: if_icmpeq +48 -> 1778
    //   1733: iload_3
    //   1734: istore 5
    //   1736: iload_3
    //   1737: istore 4
    //   1739: iload_3
    //   1740: istore 6
    //   1742: iload_3
    //   1743: istore 7
    //   1745: aload_1
    //   1746: invokevirtual 146	pZ:w	()I
    //   1749: ifle +29 -> 1778
    //   1752: iload_3
    //   1753: istore 5
    //   1755: iload_3
    //   1756: istore 4
    //   1758: iload_3
    //   1759: istore 6
    //   1761: aload_0
    //   1762: new 81	java/util/ArrayList
    //   1765: dup
    //   1766: invokespecial 82	java/util/ArrayList:<init>	()V
    //   1769: putfield 117	el:j	Ljava/util/List;
    //   1772: iload_3
    //   1773: bipush 32
    //   1775: ior
    //   1776: istore 7
    //   1778: iload 7
    //   1780: istore 5
    //   1782: iload 7
    //   1784: istore 4
    //   1786: iload 7
    //   1788: istore 6
    //   1790: aload_1
    //   1791: invokevirtual 146	pZ:w	()I
    //   1794: ifle +35 -> 1829
    //   1797: iload 7
    //   1799: istore 5
    //   1801: iload 7
    //   1803: istore 4
    //   1805: iload 7
    //   1807: istore 6
    //   1809: aload_0
    //   1810: getfield 117	el:j	Ljava/util/List;
    //   1813: aload_1
    //   1814: invokevirtual 86	pZ:f	()I
    //   1817: invokestatic 92	java/lang/Integer:valueOf	(I)Ljava/lang/Integer;
    //   1820: invokeinterface 98 2 0
    //   1825: pop
    //   1826: goto -48 -> 1778
    //   1829: iload 7
    //   1831: istore 5
    //   1833: iload 7
    //   1835: istore 4
    //   1837: iload 7
    //   1839: istore 6
    //   1841: aload_1
    //   1842: iload 9
    //   1844: invokevirtual 156	pZ:d	(I)V
    //   1847: iload 7
    //   1849: istore_3
    //   1850: goto -1815 -> 35
    //   1853: iload_3
    //   1854: istore 7
    //   1856: iload_3
    //   1857: bipush 64
    //   1859: iand
    //   1860: bipush 64
    //   1862: if_icmpeq +29 -> 1891
    //   1865: iload_3
    //   1866: istore 5
    //   1868: iload_3
    //   1869: istore 4
    //   1871: iload_3
    //   1872: istore 6
    //   1874: aload_0
    //   1875: new 81	java/util/ArrayList
    //   1878: dup
    //   1879: invokespecial 82	java/util/ArrayList:<init>	()V
    //   1882: putfield 119	el:k	Ljava/util/List;
    //   1885: iload_3
    //   1886: bipush 64
    //   1888: ior
    //   1889: istore 7
    //   1891: iload 7
    //   1893: istore 5
    //   1895: iload 7
    //   1897: istore 4
    //   1899: iload 7
    //   1901: istore 6
    //   1903: aload_0
    //   1904: getfield 119	el:k	Ljava/util/List;
    //   1907: aload_1
    //   1908: invokevirtual 86	pZ:f	()I
    //   1911: invokestatic 92	java/lang/Integer:valueOf	(I)Ljava/lang/Integer;
    //   1914: invokeinterface 98 2 0
    //   1919: pop
    //   1920: iload 7
    //   1922: istore_3
    //   1923: goto -1888 -> 35
    //   1926: iload_3
    //   1927: istore 5
    //   1929: iload_3
    //   1930: istore 4
    //   1932: iload_3
    //   1933: istore 6
    //   1935: aload_1
    //   1936: aload_1
    //   1937: invokevirtual 140	pZ:s	()I
    //   1940: invokevirtual 143	pZ:c	(I)I
    //   1943: istore 9
    //   1945: iload_3
    //   1946: istore 7
    //   1948: iload_3
    //   1949: bipush 64
    //   1951: iand
    //   1952: bipush 64
    //   1954: if_icmpeq +48 -> 2002
    //   1957: iload_3
    //   1958: istore 5
    //   1960: iload_3
    //   1961: istore 4
    //   1963: iload_3
    //   1964: istore 6
    //   1966: iload_3
    //   1967: istore 7
    //   1969: aload_1
    //   1970: invokevirtual 146	pZ:w	()I
    //   1973: ifle +29 -> 2002
    //   1976: iload_3
    //   1977: istore 5
    //   1979: iload_3
    //   1980: istore 4
    //   1982: iload_3
    //   1983: istore 6
    //   1985: aload_0
    //   1986: new 81	java/util/ArrayList
    //   1989: dup
    //   1990: invokespecial 82	java/util/ArrayList:<init>	()V
    //   1993: putfield 119	el:k	Ljava/util/List;
    //   1996: iload_3
    //   1997: bipush 64
    //   1999: ior
    //   2000: istore 7
    //   2002: iload 7
    //   2004: istore 5
    //   2006: iload 7
    //   2008: istore 4
    //   2010: iload 7
    //   2012: istore 6
    //   2014: aload_1
    //   2015: invokevirtual 146	pZ:w	()I
    //   2018: ifle +35 -> 2053
    //   2021: iload 7
    //   2023: istore 5
    //   2025: iload 7
    //   2027: istore 4
    //   2029: iload 7
    //   2031: istore 6
    //   2033: aload_0
    //   2034: getfield 119	el:k	Ljava/util/List;
    //   2037: aload_1
    //   2038: invokevirtual 86	pZ:f	()I
    //   2041: invokestatic 92	java/lang/Integer:valueOf	(I)Ljava/lang/Integer;
    //   2044: invokeinterface 98 2 0
    //   2049: pop
    //   2050: goto -48 -> 2002
    //   2053: iload 7
    //   2055: istore 5
    //   2057: iload 7
    //   2059: istore 4
    //   2061: iload 7
    //   2063: istore 6
    //   2065: aload_1
    //   2066: iload 9
    //   2068: invokevirtual 156	pZ:d	(I)V
    //   2071: iload 7
    //   2073: istore_3
    //   2074: goto -2039 -> 35
    //   2077: iload_3
    //   2078: istore 7
    //   2080: iload_3
    //   2081: sipush 128
    //   2084: iand
    //   2085: sipush 128
    //   2088: if_icmpeq +30 -> 2118
    //   2091: iload_3
    //   2092: istore 5
    //   2094: iload_3
    //   2095: istore 4
    //   2097: iload_3
    //   2098: istore 6
    //   2100: aload_0
    //   2101: new 81	java/util/ArrayList
    //   2104: dup
    //   2105: invokespecial 82	java/util/ArrayList:<init>	()V
    //   2108: putfield 121	el:l	Ljava/util/List;
    //   2111: iload_3
    //   2112: sipush 128
    //   2115: ior
    //   2116: istore 7
    //   2118: iload 7
    //   2120: istore 5
    //   2122: iload 7
    //   2124: istore 4
    //   2126: iload 7
    //   2128: istore 6
    //   2130: aload_0
    //   2131: getfield 121	el:l	Ljava/util/List;
    //   2134: aload_1
    //   2135: invokevirtual 86	pZ:f	()I
    //   2138: invokestatic 92	java/lang/Integer:valueOf	(I)Ljava/lang/Integer;
    //   2141: invokeinterface 98 2 0
    //   2146: pop
    //   2147: iload 7
    //   2149: istore_3
    //   2150: goto -2115 -> 35
    //   2153: iload_3
    //   2154: istore 5
    //   2156: iload_3
    //   2157: istore 4
    //   2159: iload_3
    //   2160: istore 6
    //   2162: aload_1
    //   2163: aload_1
    //   2164: invokevirtual 140	pZ:s	()I
    //   2167: invokevirtual 143	pZ:c	(I)I
    //   2170: istore 9
    //   2172: iload_3
    //   2173: istore 7
    //   2175: iload_3
    //   2176: sipush 128
    //   2179: iand
    //   2180: sipush 128
    //   2183: if_icmpeq +49 -> 2232
    //   2186: iload_3
    //   2187: istore 5
    //   2189: iload_3
    //   2190: istore 4
    //   2192: iload_3
    //   2193: istore 6
    //   2195: iload_3
    //   2196: istore 7
    //   2198: aload_1
    //   2199: invokevirtual 146	pZ:w	()I
    //   2202: ifle +30 -> 2232
    //   2205: iload_3
    //   2206: istore 5
    //   2208: iload_3
    //   2209: istore 4
    //   2211: iload_3
    //   2212: istore 6
    //   2214: aload_0
    //   2215: new 81	java/util/ArrayList
    //   2218: dup
    //   2219: invokespecial 82	java/util/ArrayList:<init>	()V
    //   2222: putfield 121	el:l	Ljava/util/List;
    //   2225: iload_3
    //   2226: sipush 128
    //   2229: ior
    //   2230: istore 7
    //   2232: iload 7
    //   2234: istore 5
    //   2236: iload 7
    //   2238: istore 4
    //   2240: iload 7
    //   2242: istore 6
    //   2244: aload_1
    //   2245: invokevirtual 146	pZ:w	()I
    //   2248: ifle +35 -> 2283
    //   2251: iload 7
    //   2253: istore 5
    //   2255: iload 7
    //   2257: istore 4
    //   2259: iload 7
    //   2261: istore 6
    //   2263: aload_0
    //   2264: getfield 121	el:l	Ljava/util/List;
    //   2267: aload_1
    //   2268: invokevirtual 86	pZ:f	()I
    //   2271: invokestatic 92	java/lang/Integer:valueOf	(I)Ljava/lang/Integer;
    //   2274: invokeinterface 98 2 0
    //   2279: pop
    //   2280: goto -48 -> 2232
    //   2283: iload 7
    //   2285: istore 5
    //   2287: iload 7
    //   2289: istore 4
    //   2291: iload 7
    //   2293: istore 6
    //   2295: aload_1
    //   2296: iload 9
    //   2298: invokevirtual 156	pZ:d	(I)V
    //   2301: iload 7
    //   2303: istore_3
    //   2304: goto -2269 -> 35
    //   2307: iload_3
    //   2308: istore 7
    //   2310: iload_3
    //   2311: sipush 256
    //   2314: iand
    //   2315: sipush 256
    //   2318: if_icmpeq +30 -> 2348
    //   2321: iload_3
    //   2322: istore 5
    //   2324: iload_3
    //   2325: istore 4
    //   2327: iload_3
    //   2328: istore 6
    //   2330: aload_0
    //   2331: new 81	java/util/ArrayList
    //   2334: dup
    //   2335: invokespecial 82	java/util/ArrayList:<init>	()V
    //   2338: putfield 123	el:m	Ljava/util/List;
    //   2341: iload_3
    //   2342: sipush 256
    //   2345: ior
    //   2346: istore 7
    //   2348: iload 7
    //   2350: istore 5
    //   2352: iload 7
    //   2354: istore 4
    //   2356: iload 7
    //   2358: istore 6
    //   2360: aload_0
    //   2361: getfield 123	el:m	Ljava/util/List;
    //   2364: aload_1
    //   2365: invokevirtual 86	pZ:f	()I
    //   2368: invokestatic 92	java/lang/Integer:valueOf	(I)Ljava/lang/Integer;
    //   2371: invokeinterface 98 2 0
    //   2376: pop
    //   2377: iload 7
    //   2379: istore_3
    //   2380: goto -2345 -> 35
    //   2383: iload_3
    //   2384: istore 5
    //   2386: iload_3
    //   2387: istore 4
    //   2389: iload_3
    //   2390: istore 6
    //   2392: aload_1
    //   2393: aload_1
    //   2394: invokevirtual 140	pZ:s	()I
    //   2397: invokevirtual 143	pZ:c	(I)I
    //   2400: istore 9
    //   2402: iload_3
    //   2403: istore 7
    //   2405: iload_3
    //   2406: sipush 256
    //   2409: iand
    //   2410: sipush 256
    //   2413: if_icmpeq +49 -> 2462
    //   2416: iload_3
    //   2417: istore 5
    //   2419: iload_3
    //   2420: istore 4
    //   2422: iload_3
    //   2423: istore 6
    //   2425: iload_3
    //   2426: istore 7
    //   2428: aload_1
    //   2429: invokevirtual 146	pZ:w	()I
    //   2432: ifle +30 -> 2462
    //   2435: iload_3
    //   2436: istore 5
    //   2438: iload_3
    //   2439: istore 4
    //   2441: iload_3
    //   2442: istore 6
    //   2444: aload_0
    //   2445: new 81	java/util/ArrayList
    //   2448: dup
    //   2449: invokespecial 82	java/util/ArrayList:<init>	()V
    //   2452: putfield 123	el:m	Ljava/util/List;
    //   2455: iload_3
    //   2456: sipush 256
    //   2459: ior
    //   2460: istore 7
    //   2462: iload 7
    //   2464: istore 5
    //   2466: iload 7
    //   2468: istore 4
    //   2470: iload 7
    //   2472: istore 6
    //   2474: aload_1
    //   2475: invokevirtual 146	pZ:w	()I
    //   2478: ifle +35 -> 2513
    //   2481: iload 7
    //   2483: istore 5
    //   2485: iload 7
    //   2487: istore 4
    //   2489: iload 7
    //   2491: istore 6
    //   2493: aload_0
    //   2494: getfield 123	el:m	Ljava/util/List;
    //   2497: aload_1
    //   2498: invokevirtual 86	pZ:f	()I
    //   2501: invokestatic 92	java/lang/Integer:valueOf	(I)Ljava/lang/Integer;
    //   2504: invokeinterface 98 2 0
    //   2509: pop
    //   2510: goto -48 -> 2462
    //   2513: iload 7
    //   2515: istore 5
    //   2517: iload 7
    //   2519: istore 4
    //   2521: iload 7
    //   2523: istore 6
    //   2525: aload_1
    //   2526: iload 9
    //   2528: invokevirtual 156	pZ:d	(I)V
    //   2531: iload 7
    //   2533: istore_3
    //   2534: goto -2499 -> 35
    //   2537: iload_3
    //   2538: istore 7
    //   2540: iload_3
    //   2541: sipush 512
    //   2544: iand
    //   2545: sipush 512
    //   2548: if_icmpeq +30 -> 2578
    //   2551: iload_3
    //   2552: istore 5
    //   2554: iload_3
    //   2555: istore 4
    //   2557: iload_3
    //   2558: istore 6
    //   2560: aload_0
    //   2561: new 81	java/util/ArrayList
    //   2564: dup
    //   2565: invokespecial 82	java/util/ArrayList:<init>	()V
    //   2568: putfield 125	el:n	Ljava/util/List;
    //   2571: iload_3
    //   2572: sipush 512
    //   2575: ior
    //   2576: istore 7
    //   2578: iload 7
    //   2580: istore 5
    //   2582: iload 7
    //   2584: istore 4
    //   2586: iload 7
    //   2588: istore 6
    //   2590: aload_0
    //   2591: getfield 125	el:n	Ljava/util/List;
    //   2594: aload_1
    //   2595: invokevirtual 86	pZ:f	()I
    //   2598: invokestatic 92	java/lang/Integer:valueOf	(I)Ljava/lang/Integer;
    //   2601: invokeinterface 98 2 0
    //   2606: pop
    //   2607: iload 7
    //   2609: istore_3
    //   2610: goto -2575 -> 35
    //   2613: iload_3
    //   2614: istore 5
    //   2616: iload_3
    //   2617: istore 4
    //   2619: iload_3
    //   2620: istore 6
    //   2622: aload_1
    //   2623: aload_1
    //   2624: invokevirtual 140	pZ:s	()I
    //   2627: invokevirtual 143	pZ:c	(I)I
    //   2630: istore 9
    //   2632: iload_3
    //   2633: istore 7
    //   2635: iload_3
    //   2636: sipush 512
    //   2639: iand
    //   2640: sipush 512
    //   2643: if_icmpeq +49 -> 2692
    //   2646: iload_3
    //   2647: istore 5
    //   2649: iload_3
    //   2650: istore 4
    //   2652: iload_3
    //   2653: istore 6
    //   2655: iload_3
    //   2656: istore 7
    //   2658: aload_1
    //   2659: invokevirtual 146	pZ:w	()I
    //   2662: ifle +30 -> 2692
    //   2665: iload_3
    //   2666: istore 5
    //   2668: iload_3
    //   2669: istore 4
    //   2671: iload_3
    //   2672: istore 6
    //   2674: aload_0
    //   2675: new 81	java/util/ArrayList
    //   2678: dup
    //   2679: invokespecial 82	java/util/ArrayList:<init>	()V
    //   2682: putfield 125	el:n	Ljava/util/List;
    //   2685: iload_3
    //   2686: sipush 512
    //   2689: ior
    //   2690: istore 7
    //   2692: iload 7
    //   2694: istore 5
    //   2696: iload 7
    //   2698: istore 4
    //   2700: iload 7
    //   2702: istore 6
    //   2704: aload_1
    //   2705: invokevirtual 146	pZ:w	()I
    //   2708: ifle +35 -> 2743
    //   2711: iload 7
    //   2713: istore 5
    //   2715: iload 7
    //   2717: istore 4
    //   2719: iload 7
    //   2721: istore 6
    //   2723: aload_0
    //   2724: getfield 125	el:n	Ljava/util/List;
    //   2727: aload_1
    //   2728: invokevirtual 86	pZ:f	()I
    //   2731: invokestatic 92	java/lang/Integer:valueOf	(I)Ljava/lang/Integer;
    //   2734: invokeinterface 98 2 0
    //   2739: pop
    //   2740: goto -48 -> 2692
    //   2743: iload 7
    //   2745: istore 5
    //   2747: iload 7
    //   2749: istore 4
    //   2751: iload 7
    //   2753: istore 6
    //   2755: aload_1
    //   2756: iload 9
    //   2758: invokevirtual 156	pZ:d	(I)V
    //   2761: iload 7
    //   2763: istore_3
    //   2764: goto -2729 -> 35
    //   2767: iload_3
    //   2768: iconst_1
    //   2769: iand
    //   2770: iconst_1
    //   2771: if_icmpne +14 -> 2785
    //   2774: aload_0
    //   2775: aload_0
    //   2776: getfield 84	el:e	Ljava/util/List;
    //   2779: invokestatic 107	java/util/Collections:unmodifiableList	(Ljava/util/List;)Ljava/util/List;
    //   2782: putfield 84	el:e	Ljava/util/List;
    //   2785: iload_3
    //   2786: iconst_2
    //   2787: iand
    //   2788: iconst_2
    //   2789: if_icmpne +14 -> 2803
    //   2792: aload_0
    //   2793: aload_0
    //   2794: getfield 109	el:f	Ljava/util/List;
    //   2797: invokestatic 107	java/util/Collections:unmodifiableList	(Ljava/util/List;)Ljava/util/List;
    //   2800: putfield 109	el:f	Ljava/util/List;
    //   2803: iload_3
    //   2804: iconst_4
    //   2805: iand
    //   2806: iconst_4
    //   2807: if_icmpne +14 -> 2821
    //   2810: aload_0
    //   2811: aload_0
    //   2812: getfield 111	el:g	Ljava/util/List;
    //   2815: invokestatic 107	java/util/Collections:unmodifiableList	(Ljava/util/List;)Ljava/util/List;
    //   2818: putfield 111	el:g	Ljava/util/List;
    //   2821: iload_3
    //   2822: bipush 8
    //   2824: iand
    //   2825: bipush 8
    //   2827: if_icmpne +14 -> 2841
    //   2830: aload_0
    //   2831: aload_0
    //   2832: getfield 113	el:h	Ljava/util/List;
    //   2835: invokestatic 107	java/util/Collections:unmodifiableList	(Ljava/util/List;)Ljava/util/List;
    //   2838: putfield 113	el:h	Ljava/util/List;
    //   2841: iload_3
    //   2842: bipush 16
    //   2844: iand
    //   2845: bipush 16
    //   2847: if_icmpne +14 -> 2861
    //   2850: aload_0
    //   2851: aload_0
    //   2852: getfield 115	el:i	Ljava/util/List;
    //   2855: invokestatic 107	java/util/Collections:unmodifiableList	(Ljava/util/List;)Ljava/util/List;
    //   2858: putfield 115	el:i	Ljava/util/List;
    //   2861: iload_3
    //   2862: bipush 32
    //   2864: iand
    //   2865: bipush 32
    //   2867: if_icmpne +14 -> 2881
    //   2870: aload_0
    //   2871: aload_0
    //   2872: getfield 117	el:j	Ljava/util/List;
    //   2875: invokestatic 107	java/util/Collections:unmodifiableList	(Ljava/util/List;)Ljava/util/List;
    //   2878: putfield 117	el:j	Ljava/util/List;
    //   2881: iload_3
    //   2882: bipush 64
    //   2884: iand
    //   2885: bipush 64
    //   2887: if_icmpne +14 -> 2901
    //   2890: aload_0
    //   2891: aload_0
    //   2892: getfield 119	el:k	Ljava/util/List;
    //   2895: invokestatic 107	java/util/Collections:unmodifiableList	(Ljava/util/List;)Ljava/util/List;
    //   2898: putfield 119	el:k	Ljava/util/List;
    //   2901: iload_3
    //   2902: sipush 128
    //   2905: iand
    //   2906: sipush 128
    //   2909: if_icmpne +14 -> 2923
    //   2912: aload_0
    //   2913: aload_0
    //   2914: getfield 121	el:l	Ljava/util/List;
    //   2917: invokestatic 107	java/util/Collections:unmodifiableList	(Ljava/util/List;)Ljava/util/List;
    //   2920: putfield 121	el:l	Ljava/util/List;
    //   2923: iload_3
    //   2924: sipush 256
    //   2927: iand
    //   2928: sipush 256
    //   2931: if_icmpne +14 -> 2945
    //   2934: aload_0
    //   2935: aload_0
    //   2936: getfield 123	el:m	Ljava/util/List;
    //   2939: invokestatic 107	java/util/Collections:unmodifiableList	(Ljava/util/List;)Ljava/util/List;
    //   2942: putfield 123	el:m	Ljava/util/List;
    //   2945: iload_3
    //   2946: sipush 512
    //   2949: iand
    //   2950: sipush 512
    //   2953: if_icmpne +14 -> 2967
    //   2956: aload_0
    //   2957: aload_0
    //   2958: getfield 125	el:n	Ljava/util/List;
    //   2961: invokestatic 107	java/util/Collections:unmodifiableList	(Ljava/util/List;)Ljava/util/List;
    //   2964: putfield 125	el:n	Ljava/util/List;
    //   2967: aload 11
    //   2969: invokevirtual 127	qb:a	()V
    //   2972: aload_0
    //   2973: aload 10
    //   2975: invokevirtual 132	pY:a	()LpW;
    //   2978: putfield 134	el:d	LpW;
    //   2981: aload_0
    //   2982: invokevirtual 137	el:R	()V
    //   2985: return
    //   2986: astore_1
    //   2987: aload_0
    //   2988: aload 10
    //   2990: invokevirtual 132	pY:a	()LpW;
    //   2993: putfield 134	el:d	LpW;
    //   2996: goto -15 -> 2981
    //   2999: astore_1
    //   3000: aload_0
    //   3001: aload 10
    //   3003: invokevirtual 132	pY:a	()LpW;
    //   3006: putfield 134	el:d	LpW;
    //   3009: aload_1
    //   3010: athrow
    //   3011: astore_2
    //   3012: aload_0
    //   3013: aload 10
    //   3015: invokevirtual 132	pY:a	()LpW;
    //   3018: putfield 134	el:d	LpW;
    //   3021: goto -2451 -> 570
    //   3024: astore_1
    //   3025: aload_0
    //   3026: aload 10
    //   3028: invokevirtual 132	pY:a	()LpW;
    //   3031: putfield 134	el:d	LpW;
    //   3034: aload_1
    //   3035: athrow
    //   3036: goto -2800 -> 236
    //   3039: iconst_1
    //   3040: istore 8
    //   3042: goto -3007 -> 35
    // Local variable table:
    //   start	length	slot	name	signature
    //   0	3045	0	this	el
    //   0	3045	1	parampZ	pZ
    //   0	3045	2	paramqd	qd
    //   19	2931	3	i1	int
    //   44	2706	4	i2	int
    //   41	2705	5	i3	int
    //   47	2707	6	i4	int
    //   53	2709	7	i5	int
    //   33	3008	8	i6	int
    //   593	2164	9	i7	int
    //   23	3004	10	localpY	pY
    //   30	2938	11	localqb	qb
    // Exception table:
    //   from	to	target	type
    //   49	55	334	qu
    //   245	258	334	qu
    //   283	294	334	qu
    //   311	328	334	qu
    //   585	595	334	qu
    //   617	624	334	qu
    //   633	644	334	qu
    //   661	668	334	qu
    //   680	697	334	qu
    //   733	739	334	qu
    //   764	775	334	qu
    //   792	809	334	qu
    //   824	834	334	qu
    //   856	863	334	qu
    //   872	883	334	qu
    //   900	907	334	qu
    //   919	936	334	qu
    //   951	957	334	qu
    //   982	993	334	qu
    //   1010	1027	334	qu
    //   1042	1052	334	qu
    //   1074	1081	334	qu
    //   1090	1101	334	qu
    //   1118	1125	334	qu
    //   1137	1154	334	qu
    //   1169	1175	334	qu
    //   1202	1213	334	qu
    //   1231	1248	334	qu
    //   1263	1273	334	qu
    //   1297	1304	334	qu
    //   1313	1324	334	qu
    //   1342	1349	334	qu
    //   1361	1378	334	qu
    //   1393	1399	334	qu
    //   1426	1437	334	qu
    //   1455	1472	334	qu
    //   1487	1497	334	qu
    //   1521	1528	334	qu
    //   1537	1548	334	qu
    //   1566	1573	334	qu
    //   1585	1602	334	qu
    //   1617	1623	334	qu
    //   1650	1661	334	qu
    //   1679	1696	334	qu
    //   1711	1721	334	qu
    //   1745	1752	334	qu
    //   1761	1772	334	qu
    //   1790	1797	334	qu
    //   1809	1826	334	qu
    //   1841	1847	334	qu
    //   1874	1885	334	qu
    //   1903	1920	334	qu
    //   1935	1945	334	qu
    //   1969	1976	334	qu
    //   1985	1996	334	qu
    //   2014	2021	334	qu
    //   2033	2050	334	qu
    //   2065	2071	334	qu
    //   2100	2111	334	qu
    //   2130	2147	334	qu
    //   2162	2172	334	qu
    //   2198	2205	334	qu
    //   2214	2225	334	qu
    //   2244	2251	334	qu
    //   2263	2280	334	qu
    //   2295	2301	334	qu
    //   2330	2341	334	qu
    //   2360	2377	334	qu
    //   2392	2402	334	qu
    //   2428	2435	334	qu
    //   2444	2455	334	qu
    //   2474	2481	334	qu
    //   2493	2510	334	qu
    //   2525	2531	334	qu
    //   2560	2571	334	qu
    //   2590	2607	334	qu
    //   2622	2632	334	qu
    //   2658	2665	334	qu
    //   2674	2685	334	qu
    //   2704	2711	334	qu
    //   2723	2740	334	qu
    //   2755	2761	334	qu
    //   49	55	345	finally
    //   245	258	345	finally
    //   283	294	345	finally
    //   311	328	345	finally
    //   339	345	345	finally
    //   585	595	345	finally
    //   617	624	345	finally
    //   633	644	345	finally
    //   661	668	345	finally
    //   680	697	345	finally
    //   705	721	345	finally
    //   733	739	345	finally
    //   764	775	345	finally
    //   792	809	345	finally
    //   824	834	345	finally
    //   856	863	345	finally
    //   872	883	345	finally
    //   900	907	345	finally
    //   919	936	345	finally
    //   951	957	345	finally
    //   982	993	345	finally
    //   1010	1027	345	finally
    //   1042	1052	345	finally
    //   1074	1081	345	finally
    //   1090	1101	345	finally
    //   1118	1125	345	finally
    //   1137	1154	345	finally
    //   1169	1175	345	finally
    //   1202	1213	345	finally
    //   1231	1248	345	finally
    //   1263	1273	345	finally
    //   1297	1304	345	finally
    //   1313	1324	345	finally
    //   1342	1349	345	finally
    //   1361	1378	345	finally
    //   1393	1399	345	finally
    //   1426	1437	345	finally
    //   1455	1472	345	finally
    //   1487	1497	345	finally
    //   1521	1528	345	finally
    //   1537	1548	345	finally
    //   1566	1573	345	finally
    //   1585	1602	345	finally
    //   1617	1623	345	finally
    //   1650	1661	345	finally
    //   1679	1696	345	finally
    //   1711	1721	345	finally
    //   1745	1752	345	finally
    //   1761	1772	345	finally
    //   1790	1797	345	finally
    //   1809	1826	345	finally
    //   1841	1847	345	finally
    //   1874	1885	345	finally
    //   1903	1920	345	finally
    //   1935	1945	345	finally
    //   1969	1976	345	finally
    //   1985	1996	345	finally
    //   2014	2021	345	finally
    //   2033	2050	345	finally
    //   2065	2071	345	finally
    //   2100	2111	345	finally
    //   2130	2147	345	finally
    //   2162	2172	345	finally
    //   2198	2205	345	finally
    //   2214	2225	345	finally
    //   2244	2251	345	finally
    //   2263	2280	345	finally
    //   2295	2301	345	finally
    //   2330	2341	345	finally
    //   2360	2377	345	finally
    //   2392	2402	345	finally
    //   2428	2435	345	finally
    //   2444	2455	345	finally
    //   2474	2481	345	finally
    //   2493	2510	345	finally
    //   2525	2531	345	finally
    //   2560	2571	345	finally
    //   2590	2607	345	finally
    //   2622	2632	345	finally
    //   2658	2665	345	finally
    //   2674	2685	345	finally
    //   2704	2711	345	finally
    //   2723	2740	345	finally
    //   2755	2761	345	finally
    //   49	55	700	java/io/IOException
    //   245	258	700	java/io/IOException
    //   283	294	700	java/io/IOException
    //   311	328	700	java/io/IOException
    //   585	595	700	java/io/IOException
    //   617	624	700	java/io/IOException
    //   633	644	700	java/io/IOException
    //   661	668	700	java/io/IOException
    //   680	697	700	java/io/IOException
    //   733	739	700	java/io/IOException
    //   764	775	700	java/io/IOException
    //   792	809	700	java/io/IOException
    //   824	834	700	java/io/IOException
    //   856	863	700	java/io/IOException
    //   872	883	700	java/io/IOException
    //   900	907	700	java/io/IOException
    //   919	936	700	java/io/IOException
    //   951	957	700	java/io/IOException
    //   982	993	700	java/io/IOException
    //   1010	1027	700	java/io/IOException
    //   1042	1052	700	java/io/IOException
    //   1074	1081	700	java/io/IOException
    //   1090	1101	700	java/io/IOException
    //   1118	1125	700	java/io/IOException
    //   1137	1154	700	java/io/IOException
    //   1169	1175	700	java/io/IOException
    //   1202	1213	700	java/io/IOException
    //   1231	1248	700	java/io/IOException
    //   1263	1273	700	java/io/IOException
    //   1297	1304	700	java/io/IOException
    //   1313	1324	700	java/io/IOException
    //   1342	1349	700	java/io/IOException
    //   1361	1378	700	java/io/IOException
    //   1393	1399	700	java/io/IOException
    //   1426	1437	700	java/io/IOException
    //   1455	1472	700	java/io/IOException
    //   1487	1497	700	java/io/IOException
    //   1521	1528	700	java/io/IOException
    //   1537	1548	700	java/io/IOException
    //   1566	1573	700	java/io/IOException
    //   1585	1602	700	java/io/IOException
    //   1617	1623	700	java/io/IOException
    //   1650	1661	700	java/io/IOException
    //   1679	1696	700	java/io/IOException
    //   1711	1721	700	java/io/IOException
    //   1745	1752	700	java/io/IOException
    //   1761	1772	700	java/io/IOException
    //   1790	1797	700	java/io/IOException
    //   1809	1826	700	java/io/IOException
    //   1841	1847	700	java/io/IOException
    //   1874	1885	700	java/io/IOException
    //   1903	1920	700	java/io/IOException
    //   1935	1945	700	java/io/IOException
    //   1969	1976	700	java/io/IOException
    //   1985	1996	700	java/io/IOException
    //   2014	2021	700	java/io/IOException
    //   2033	2050	700	java/io/IOException
    //   2065	2071	700	java/io/IOException
    //   2100	2111	700	java/io/IOException
    //   2130	2147	700	java/io/IOException
    //   2162	2172	700	java/io/IOException
    //   2198	2205	700	java/io/IOException
    //   2214	2225	700	java/io/IOException
    //   2244	2251	700	java/io/IOException
    //   2263	2280	700	java/io/IOException
    //   2295	2301	700	java/io/IOException
    //   2330	2341	700	java/io/IOException
    //   2360	2377	700	java/io/IOException
    //   2392	2402	700	java/io/IOException
    //   2428	2435	700	java/io/IOException
    //   2444	2455	700	java/io/IOException
    //   2474	2481	700	java/io/IOException
    //   2493	2510	700	java/io/IOException
    //   2525	2531	700	java/io/IOException
    //   2560	2571	700	java/io/IOException
    //   2590	2607	700	java/io/IOException
    //   2622	2632	700	java/io/IOException
    //   2658	2665	700	java/io/IOException
    //   2674	2685	700	java/io/IOException
    //   2704	2711	700	java/io/IOException
    //   2723	2740	700	java/io/IOException
    //   2755	2761	700	java/io/IOException
    //   2967	2972	2986	java/io/IOException
    //   2967	2972	2999	finally
    //   556	561	3011	java/io/IOException
    //   556	561	3024	finally
  }
  
  private el(qk paramqk)
  {
    super(paramqk);
    d = paramqk.r();
  }
  
  private el(boolean paramBoolean)
  {
    d = pW.a;
  }
  
  public static en B()
  {
    return en.i();
  }
  
  private void E()
  {
    e = Collections.emptyList();
    f = Collections.emptyList();
    g = Collections.emptyList();
    h = Collections.emptyList();
    i = Collections.emptyList();
    j = Collections.emptyList();
    k = Collections.emptyList();
    l = Collections.emptyList();
    m = Collections.emptyList();
    n = Collections.emptyList();
  }
  
  public static el a()
  {
    return c;
  }
  
  public static en a(el paramel)
  {
    return B().a(paramel);
  }
  
  public int A()
  {
    return n.size();
  }
  
  public en C()
  {
    return B();
  }
  
  public en D()
  {
    return a(this);
  }
  
  public el b()
  {
    return c;
  }
  
  public qF<el> c()
  {
    return a;
  }
  
  public List<Integer> d()
  {
    return e;
  }
  
  public int e()
  {
    return e.size();
  }
  
  public boolean equals(Object paramObject)
  {
    if (paramObject == this) {}
    label65:
    label87:
    label109:
    label131:
    label153:
    label175:
    label197:
    label246:
    label251:
    label256:
    label261:
    label266:
    label271:
    label276:
    label281:
    label284:
    for (;;)
    {
      return true;
      if (!(paramObject instanceof el)) {
        return super.equals(paramObject);
      }
      paramObject = (el)paramObject;
      if (d().equals(((el)paramObject).d()))
      {
        i1 = 1;
        if ((i1 == 0) || (!f().equals(((el)paramObject).f()))) {
          break label246;
        }
        i1 = 1;
        if ((i1 == 0) || (!h().equals(((el)paramObject).h()))) {
          break label251;
        }
        i1 = 1;
        if ((i1 == 0) || (!k().equals(((el)paramObject).k()))) {
          break label256;
        }
        i1 = 1;
        if ((i1 == 0) || (!m().equals(((el)paramObject).m()))) {
          break label261;
        }
        i1 = 1;
        if ((i1 == 0) || (!r().equals(((el)paramObject).r()))) {
          break label266;
        }
        i1 = 1;
        if ((i1 == 0) || (!t().equals(((el)paramObject).t()))) {
          break label271;
        }
        i1 = 1;
        if ((i1 == 0) || (!v().equals(((el)paramObject).v()))) {
          break label276;
        }
        i1 = 1;
        if ((i1 == 0) || (!x().equals(((el)paramObject).x()))) {
          break label281;
        }
      }
      for (int i1 = 1;; i1 = 0)
      {
        if ((i1 != 0) && (z().equals(((el)paramObject).z()))) {
          break label284;
        }
        return false;
        i1 = 0;
        break;
        i1 = 0;
        break label65;
        i1 = 0;
        break label87;
        i1 = 0;
        break label109;
        i1 = 0;
        break label131;
        i1 = 0;
        break label153;
        i1 = 0;
        break label175;
        i1 = 0;
        break label197;
      }
    }
  }
  
  public List<Integer> f()
  {
    return f;
  }
  
  public int g()
  {
    return f.size();
  }
  
  public List<Integer> h()
  {
    return g;
  }
  
  public int hashCode()
  {
    if (b != 0) {
      return b;
    }
    int i2 = el.class.hashCode() + 779;
    int i1 = i2;
    if (e() > 0) {
      i1 = (i2 * 37 + 1) * 53 + d().hashCode();
    }
    i2 = i1;
    if (g() > 0) {
      i2 = (i1 * 37 + 2) * 53 + f().hashCode();
    }
    i1 = i2;
    if (i() > 0) {
      i1 = (i2 * 37 + 3) * 53 + h().hashCode();
    }
    i2 = i1;
    if (l() > 0) {
      i2 = (i1 * 37 + 4) * 53 + k().hashCode();
    }
    i1 = i2;
    if (q() > 0) {
      i1 = (i2 * 37 + 5) * 53 + m().hashCode();
    }
    i2 = i1;
    if (s() > 0) {
      i2 = (i1 * 37 + 6) * 53 + r().hashCode();
    }
    i1 = i2;
    if (u() > 0) {
      i1 = (i2 * 37 + 7) * 53 + t().hashCode();
    }
    i2 = i1;
    if (w() > 0) {
      i2 = (i1 * 37 + 8) * 53 + v().hashCode();
    }
    i1 = i2;
    if (y() > 0) {
      i1 = (i2 * 37 + 9) * 53 + x().hashCode();
    }
    i2 = i1;
    if (A() > 0) {
      i2 = (i1 * 37 + 10) * 53 + z().hashCode();
    }
    i1 = i2 * 29 + d.hashCode();
    b = i1;
    return i1;
  }
  
  public int i()
  {
    return g.size();
  }
  
  public final boolean j()
  {
    int i1 = o;
    if (i1 != -1) {
      return i1 == 1;
    }
    o = 1;
    return true;
  }
  
  public List<Integer> k()
  {
    return h;
  }
  
  public int l()
  {
    return h.size();
  }
  
  public List<Integer> m()
  {
    return i;
  }
  
  public int q()
  {
    return i.size();
  }
  
  public List<Integer> r()
  {
    return j;
  }
  
  public int s()
  {
    return j.size();
  }
  
  public List<Integer> t()
  {
    return k;
  }
  
  public int u()
  {
    return k.size();
  }
  
  public List<Integer> v()
  {
    return l;
  }
  
  public int w()
  {
    return l.size();
  }
  
  public List<Integer> x()
  {
    return m;
  }
  
  public int y()
  {
    return m.size();
  }
  
  public List<Integer> z()
  {
    return n;
  }
}

/* Location:
 * Qualified Name:     el
 * Java Class Version: 6 (50.0)
 * JD-Core Version:    0.7.1
 */