import android.os.IBinder;
import android.os.Parcel;
import com.google.android.gms.maps.model.GroundOverlayOptions;
import com.google.android.gms.maps.model.MarkerOptions;
import com.google.android.gms.maps.model.internal.c;
import com.google.android.gms.maps.model.internal.e;
import com.google.android.gms.maps.model.internal.p;

class kN
  implements kL
{
  private IBinder a;
  
  kN(IBinder paramIBinder)
  {
    a = paramIBinder;
  }
  
  /* Error */
  public com.google.android.gms.maps.model.CameraPosition a()
  {
    // Byte code:
    //   0: invokestatic 23	android/os/Parcel:obtain	()Landroid/os/Parcel;
    //   3: astore_2
    //   4: invokestatic 23	android/os/Parcel:obtain	()Landroid/os/Parcel;
    //   7: astore_3
    //   8: aload_2
    //   9: ldc 25
    //   11: invokevirtual 29	android/os/Parcel:writeInterfaceToken	(Ljava/lang/String;)V
    //   14: aload_0
    //   15: getfield 15	kN:a	Landroid/os/IBinder;
    //   18: iconst_1
    //   19: aload_2
    //   20: aload_3
    //   21: iconst_0
    //   22: invokeinterface 35 5 0
    //   27: pop
    //   28: aload_3
    //   29: invokevirtual 38	android/os/Parcel:readException	()V
    //   32: aload_3
    //   33: invokevirtual 42	android/os/Parcel:readInt	()I
    //   36: ifeq +21 -> 57
    //   39: getstatic 48	com/google/android/gms/maps/model/CameraPosition:CREATOR	LmM;
    //   42: aload_3
    //   43: invokevirtual 53	mM:a	(Landroid/os/Parcel;)Lcom/google/android/gms/maps/model/CameraPosition;
    //   46: astore_1
    //   47: aload_3
    //   48: invokevirtual 56	android/os/Parcel:recycle	()V
    //   51: aload_2
    //   52: invokevirtual 56	android/os/Parcel:recycle	()V
    //   55: aload_1
    //   56: areturn
    //   57: aconst_null
    //   58: astore_1
    //   59: goto -12 -> 47
    //   62: astore_1
    //   63: aload_3
    //   64: invokevirtual 56	android/os/Parcel:recycle	()V
    //   67: aload_2
    //   68: invokevirtual 56	android/os/Parcel:recycle	()V
    //   71: aload_1
    //   72: athrow
    // Local variable table:
    //   start	length	slot	name	signature
    //   0	73	0	this	kN
    //   46	13	1	localCameraPosition	com.google.android.gms.maps.model.CameraPosition
    //   62	10	1	localObject	Object
    //   3	65	2	localParcel1	Parcel
    //   7	57	3	localParcel2	Parcel
    // Exception table:
    //   from	to	target	type
    //   8	47	62	finally
  }
  
  /* Error */
  public mV a(com.google.android.gms.maps.model.PolylineOptions paramPolylineOptions)
  {
    // Byte code:
    //   0: invokestatic 23	android/os/Parcel:obtain	()Landroid/os/Parcel;
    //   3: astore_2
    //   4: invokestatic 23	android/os/Parcel:obtain	()Landroid/os/Parcel;
    //   7: astore_3
    //   8: aload_2
    //   9: ldc 25
    //   11: invokevirtual 29	android/os/Parcel:writeInterfaceToken	(Ljava/lang/String;)V
    //   14: aload_1
    //   15: ifnull +51 -> 66
    //   18: aload_2
    //   19: iconst_1
    //   20: invokevirtual 61	android/os/Parcel:writeInt	(I)V
    //   23: aload_1
    //   24: aload_2
    //   25: iconst_0
    //   26: invokevirtual 67	com/google/android/gms/maps/model/PolylineOptions:writeToParcel	(Landroid/os/Parcel;I)V
    //   29: aload_0
    //   30: getfield 15	kN:a	Landroid/os/IBinder;
    //   33: bipush 9
    //   35: aload_2
    //   36: aload_3
    //   37: iconst_0
    //   38: invokeinterface 35 5 0
    //   43: pop
    //   44: aload_3
    //   45: invokevirtual 38	android/os/Parcel:readException	()V
    //   48: aload_3
    //   49: invokevirtual 71	android/os/Parcel:readStrongBinder	()Landroid/os/IBinder;
    //   52: invokestatic 76	mW:a	(Landroid/os/IBinder;)LmV;
    //   55: astore_1
    //   56: aload_3
    //   57: invokevirtual 56	android/os/Parcel:recycle	()V
    //   60: aload_2
    //   61: invokevirtual 56	android/os/Parcel:recycle	()V
    //   64: aload_1
    //   65: areturn
    //   66: aload_2
    //   67: iconst_0
    //   68: invokevirtual 61	android/os/Parcel:writeInt	(I)V
    //   71: goto -42 -> 29
    //   74: astore_1
    //   75: aload_3
    //   76: invokevirtual 56	android/os/Parcel:recycle	()V
    //   79: aload_2
    //   80: invokevirtual 56	android/os/Parcel:recycle	()V
    //   83: aload_1
    //   84: athrow
    // Local variable table:
    //   start	length	slot	name	signature
    //   0	85	0	this	kN
    //   0	85	1	paramPolylineOptions	com.google.android.gms.maps.model.PolylineOptions
    //   3	77	2	localParcel1	Parcel
    //   7	69	3	localParcel2	Parcel
    // Exception table:
    //   from	to	target	type
    //   8	14	74	finally
    //   18	29	74	finally
    //   29	56	74	finally
    //   66	71	74	finally
  }
  
  /* Error */
  public ne a(com.google.android.gms.maps.model.CircleOptions paramCircleOptions)
  {
    // Byte code:
    //   0: invokestatic 23	android/os/Parcel:obtain	()Landroid/os/Parcel;
    //   3: astore_2
    //   4: invokestatic 23	android/os/Parcel:obtain	()Landroid/os/Parcel;
    //   7: astore_3
    //   8: aload_2
    //   9: ldc 25
    //   11: invokevirtual 29	android/os/Parcel:writeInterfaceToken	(Ljava/lang/String;)V
    //   14: aload_1
    //   15: ifnull +51 -> 66
    //   18: aload_2
    //   19: iconst_1
    //   20: invokevirtual 61	android/os/Parcel:writeInt	(I)V
    //   23: aload_1
    //   24: aload_2
    //   25: iconst_0
    //   26: invokevirtual 80	com/google/android/gms/maps/model/CircleOptions:writeToParcel	(Landroid/os/Parcel;I)V
    //   29: aload_0
    //   30: getfield 15	kN:a	Landroid/os/IBinder;
    //   33: bipush 35
    //   35: aload_2
    //   36: aload_3
    //   37: iconst_0
    //   38: invokeinterface 35 5 0
    //   43: pop
    //   44: aload_3
    //   45: invokevirtual 38	android/os/Parcel:readException	()V
    //   48: aload_3
    //   49: invokevirtual 71	android/os/Parcel:readStrongBinder	()Landroid/os/IBinder;
    //   52: invokestatic 85	nf:a	(Landroid/os/IBinder;)Lne;
    //   55: astore_1
    //   56: aload_3
    //   57: invokevirtual 56	android/os/Parcel:recycle	()V
    //   60: aload_2
    //   61: invokevirtual 56	android/os/Parcel:recycle	()V
    //   64: aload_1
    //   65: areturn
    //   66: aload_2
    //   67: iconst_0
    //   68: invokevirtual 61	android/os/Parcel:writeInt	(I)V
    //   71: goto -42 -> 29
    //   74: astore_1
    //   75: aload_3
    //   76: invokevirtual 56	android/os/Parcel:recycle	()V
    //   79: aload_2
    //   80: invokevirtual 56	android/os/Parcel:recycle	()V
    //   83: aload_1
    //   84: athrow
    // Local variable table:
    //   start	length	slot	name	signature
    //   0	85	0	this	kN
    //   0	85	1	paramCircleOptions	com.google.android.gms.maps.model.CircleOptions
    //   3	77	2	localParcel1	Parcel
    //   7	69	3	localParcel2	Parcel
    // Exception table:
    //   from	to	target	type
    //   8	14	74	finally
    //   18	29	74	finally
    //   29	56	74	finally
    //   66	71	74	finally
  }
  
  /* Error */
  public nh a(GroundOverlayOptions paramGroundOverlayOptions)
  {
    // Byte code:
    //   0: invokestatic 23	android/os/Parcel:obtain	()Landroid/os/Parcel;
    //   3: astore_2
    //   4: invokestatic 23	android/os/Parcel:obtain	()Landroid/os/Parcel;
    //   7: astore_3
    //   8: aload_2
    //   9: ldc 25
    //   11: invokevirtual 29	android/os/Parcel:writeInterfaceToken	(Ljava/lang/String;)V
    //   14: aload_1
    //   15: ifnull +51 -> 66
    //   18: aload_2
    //   19: iconst_1
    //   20: invokevirtual 61	android/os/Parcel:writeInt	(I)V
    //   23: aload_1
    //   24: aload_2
    //   25: iconst_0
    //   26: invokevirtual 89	com/google/android/gms/maps/model/GroundOverlayOptions:writeToParcel	(Landroid/os/Parcel;I)V
    //   29: aload_0
    //   30: getfield 15	kN:a	Landroid/os/IBinder;
    //   33: bipush 12
    //   35: aload_2
    //   36: aload_3
    //   37: iconst_0
    //   38: invokeinterface 35 5 0
    //   43: pop
    //   44: aload_3
    //   45: invokevirtual 38	android/os/Parcel:readException	()V
    //   48: aload_3
    //   49: invokevirtual 71	android/os/Parcel:readStrongBinder	()Landroid/os/IBinder;
    //   52: invokestatic 94	ni:a	(Landroid/os/IBinder;)Lnh;
    //   55: astore_1
    //   56: aload_3
    //   57: invokevirtual 56	android/os/Parcel:recycle	()V
    //   60: aload_2
    //   61: invokevirtual 56	android/os/Parcel:recycle	()V
    //   64: aload_1
    //   65: areturn
    //   66: aload_2
    //   67: iconst_0
    //   68: invokevirtual 61	android/os/Parcel:writeInt	(I)V
    //   71: goto -42 -> 29
    //   74: astore_1
    //   75: aload_3
    //   76: invokevirtual 56	android/os/Parcel:recycle	()V
    //   79: aload_2
    //   80: invokevirtual 56	android/os/Parcel:recycle	()V
    //   83: aload_1
    //   84: athrow
    // Local variable table:
    //   start	length	slot	name	signature
    //   0	85	0	this	kN
    //   0	85	1	paramGroundOverlayOptions	GroundOverlayOptions
    //   3	77	2	localParcel1	Parcel
    //   7	69	3	localParcel2	Parcel
    // Exception table:
    //   from	to	target	type
    //   8	14	74	finally
    //   18	29	74	finally
    //   29	56	74	finally
    //   66	71	74	finally
  }
  
  public nh a(GroundOverlayOptions paramGroundOverlayOptions, e parame)
  {
    Parcel localParcel1 = Parcel.obtain();
    Parcel localParcel2 = Parcel.obtain();
    for (;;)
    {
      try
      {
        localParcel1.writeInterfaceToken("com.google.android.gms.maps.internal.IGoogleMapDelegate");
        if (paramGroundOverlayOptions != null)
        {
          localParcel1.writeInt(1);
          paramGroundOverlayOptions.writeToParcel(localParcel1, 0);
          if (parame != null)
          {
            localParcel1.writeInt(1);
            parame.writeToParcel(localParcel1, 0);
            a.transact(70, localParcel1, localParcel2, 0);
            localParcel2.readException();
            paramGroundOverlayOptions = ni.a(localParcel2.readStrongBinder());
            return paramGroundOverlayOptions;
          }
        }
        else
        {
          localParcel1.writeInt(0);
          continue;
        }
        localParcel1.writeInt(0);
      }
      finally
      {
        localParcel2.recycle();
        localParcel1.recycle();
      }
    }
  }
  
  /* Error */
  public nn a(MarkerOptions paramMarkerOptions)
  {
    // Byte code:
    //   0: invokestatic 23	android/os/Parcel:obtain	()Landroid/os/Parcel;
    //   3: astore_2
    //   4: invokestatic 23	android/os/Parcel:obtain	()Landroid/os/Parcel;
    //   7: astore_3
    //   8: aload_2
    //   9: ldc 25
    //   11: invokevirtual 29	android/os/Parcel:writeInterfaceToken	(Ljava/lang/String;)V
    //   14: aload_1
    //   15: ifnull +51 -> 66
    //   18: aload_2
    //   19: iconst_1
    //   20: invokevirtual 61	android/os/Parcel:writeInt	(I)V
    //   23: aload_1
    //   24: aload_2
    //   25: iconst_0
    //   26: invokevirtual 102	com/google/android/gms/maps/model/MarkerOptions:writeToParcel	(Landroid/os/Parcel;I)V
    //   29: aload_0
    //   30: getfield 15	kN:a	Landroid/os/IBinder;
    //   33: bipush 11
    //   35: aload_2
    //   36: aload_3
    //   37: iconst_0
    //   38: invokeinterface 35 5 0
    //   43: pop
    //   44: aload_3
    //   45: invokevirtual 38	android/os/Parcel:readException	()V
    //   48: aload_3
    //   49: invokevirtual 71	android/os/Parcel:readStrongBinder	()Landroid/os/IBinder;
    //   52: invokestatic 107	no:a	(Landroid/os/IBinder;)Lnn;
    //   55: astore_1
    //   56: aload_3
    //   57: invokevirtual 56	android/os/Parcel:recycle	()V
    //   60: aload_2
    //   61: invokevirtual 56	android/os/Parcel:recycle	()V
    //   64: aload_1
    //   65: areturn
    //   66: aload_2
    //   67: iconst_0
    //   68: invokevirtual 61	android/os/Parcel:writeInt	(I)V
    //   71: goto -42 -> 29
    //   74: astore_1
    //   75: aload_3
    //   76: invokevirtual 56	android/os/Parcel:recycle	()V
    //   79: aload_2
    //   80: invokevirtual 56	android/os/Parcel:recycle	()V
    //   83: aload_1
    //   84: athrow
    // Local variable table:
    //   start	length	slot	name	signature
    //   0	85	0	this	kN
    //   0	85	1	paramMarkerOptions	MarkerOptions
    //   3	77	2	localParcel1	Parcel
    //   7	69	3	localParcel2	Parcel
    // Exception table:
    //   from	to	target	type
    //   8	14	74	finally
    //   18	29	74	finally
    //   29	56	74	finally
    //   66	71	74	finally
  }
  
  public nn a(MarkerOptions paramMarkerOptions, p paramp)
  {
    Parcel localParcel1 = Parcel.obtain();
    Parcel localParcel2 = Parcel.obtain();
    for (;;)
    {
      try
      {
        localParcel1.writeInterfaceToken("com.google.android.gms.maps.internal.IGoogleMapDelegate");
        if (paramMarkerOptions != null)
        {
          localParcel1.writeInt(1);
          paramMarkerOptions.writeToParcel(localParcel1, 0);
          if (paramp != null)
          {
            localParcel1.writeInt(1);
            paramp.writeToParcel(localParcel1, 0);
            a.transact(68, localParcel1, localParcel2, 0);
            localParcel2.readException();
            paramMarkerOptions = no.a(localParcel2.readStrongBinder());
            return paramMarkerOptions;
          }
        }
        else
        {
          localParcel1.writeInt(0);
          continue;
        }
        localParcel1.writeInt(0);
      }
      finally
      {
        localParcel2.recycle();
        localParcel1.recycle();
      }
    }
  }
  
  /* Error */
  public nq a(com.google.android.gms.maps.model.PolygonOptions paramPolygonOptions)
  {
    // Byte code:
    //   0: invokestatic 23	android/os/Parcel:obtain	()Landroid/os/Parcel;
    //   3: astore_2
    //   4: invokestatic 23	android/os/Parcel:obtain	()Landroid/os/Parcel;
    //   7: astore_3
    //   8: aload_2
    //   9: ldc 25
    //   11: invokevirtual 29	android/os/Parcel:writeInterfaceToken	(Ljava/lang/String;)V
    //   14: aload_1
    //   15: ifnull +51 -> 66
    //   18: aload_2
    //   19: iconst_1
    //   20: invokevirtual 61	android/os/Parcel:writeInt	(I)V
    //   23: aload_1
    //   24: aload_2
    //   25: iconst_0
    //   26: invokevirtual 115	com/google/android/gms/maps/model/PolygonOptions:writeToParcel	(Landroid/os/Parcel;I)V
    //   29: aload_0
    //   30: getfield 15	kN:a	Landroid/os/IBinder;
    //   33: bipush 10
    //   35: aload_2
    //   36: aload_3
    //   37: iconst_0
    //   38: invokeinterface 35 5 0
    //   43: pop
    //   44: aload_3
    //   45: invokevirtual 38	android/os/Parcel:readException	()V
    //   48: aload_3
    //   49: invokevirtual 71	android/os/Parcel:readStrongBinder	()Landroid/os/IBinder;
    //   52: invokestatic 120	nr:a	(Landroid/os/IBinder;)Lnq;
    //   55: astore_1
    //   56: aload_3
    //   57: invokevirtual 56	android/os/Parcel:recycle	()V
    //   60: aload_2
    //   61: invokevirtual 56	android/os/Parcel:recycle	()V
    //   64: aload_1
    //   65: areturn
    //   66: aload_2
    //   67: iconst_0
    //   68: invokevirtual 61	android/os/Parcel:writeInt	(I)V
    //   71: goto -42 -> 29
    //   74: astore_1
    //   75: aload_3
    //   76: invokevirtual 56	android/os/Parcel:recycle	()V
    //   79: aload_2
    //   80: invokevirtual 56	android/os/Parcel:recycle	()V
    //   83: aload_1
    //   84: athrow
    // Local variable table:
    //   start	length	slot	name	signature
    //   0	85	0	this	kN
    //   0	85	1	paramPolygonOptions	com.google.android.gms.maps.model.PolygonOptions
    //   3	77	2	localParcel1	Parcel
    //   7	69	3	localParcel2	Parcel
    // Exception table:
    //   from	to	target	type
    //   8	14	74	finally
    //   18	29	74	finally
    //   29	56	74	finally
    //   66	71	74	finally
  }
  
  /* Error */
  public nt a(com.google.android.gms.maps.model.TileOverlayOptions paramTileOverlayOptions)
  {
    // Byte code:
    //   0: invokestatic 23	android/os/Parcel:obtain	()Landroid/os/Parcel;
    //   3: astore_2
    //   4: invokestatic 23	android/os/Parcel:obtain	()Landroid/os/Parcel;
    //   7: astore_3
    //   8: aload_2
    //   9: ldc 25
    //   11: invokevirtual 29	android/os/Parcel:writeInterfaceToken	(Ljava/lang/String;)V
    //   14: aload_1
    //   15: ifnull +51 -> 66
    //   18: aload_2
    //   19: iconst_1
    //   20: invokevirtual 61	android/os/Parcel:writeInt	(I)V
    //   23: aload_1
    //   24: aload_2
    //   25: iconst_0
    //   26: invokevirtual 124	com/google/android/gms/maps/model/TileOverlayOptions:writeToParcel	(Landroid/os/Parcel;I)V
    //   29: aload_0
    //   30: getfield 15	kN:a	Landroid/os/IBinder;
    //   33: bipush 13
    //   35: aload_2
    //   36: aload_3
    //   37: iconst_0
    //   38: invokeinterface 35 5 0
    //   43: pop
    //   44: aload_3
    //   45: invokevirtual 38	android/os/Parcel:readException	()V
    //   48: aload_3
    //   49: invokevirtual 71	android/os/Parcel:readStrongBinder	()Landroid/os/IBinder;
    //   52: invokestatic 129	nu:a	(Landroid/os/IBinder;)Lnt;
    //   55: astore_1
    //   56: aload_3
    //   57: invokevirtual 56	android/os/Parcel:recycle	()V
    //   60: aload_2
    //   61: invokevirtual 56	android/os/Parcel:recycle	()V
    //   64: aload_1
    //   65: areturn
    //   66: aload_2
    //   67: iconst_0
    //   68: invokevirtual 61	android/os/Parcel:writeInt	(I)V
    //   71: goto -42 -> 29
    //   74: astore_1
    //   75: aload_3
    //   76: invokevirtual 56	android/os/Parcel:recycle	()V
    //   79: aload_2
    //   80: invokevirtual 56	android/os/Parcel:recycle	()V
    //   83: aload_1
    //   84: athrow
    // Local variable table:
    //   start	length	slot	name	signature
    //   0	85	0	this	kN
    //   0	85	1	paramTileOverlayOptions	com.google.android.gms.maps.model.TileOverlayOptions
    //   3	77	2	localParcel1	Parcel
    //   7	69	3	localParcel2	Parcel
    // Exception table:
    //   from	to	target	type
    //   8	14	74	finally
    //   18	29	74	finally
    //   29	56	74	finally
    //   66	71	74	finally
  }
  
  public void a(int paramInt)
  {
    Parcel localParcel1 = Parcel.obtain();
    Parcel localParcel2 = Parcel.obtain();
    try
    {
      localParcel1.writeInterfaceToken("com.google.android.gms.maps.internal.IGoogleMapDelegate");
      localParcel1.writeInt(paramInt);
      a.transact(16, localParcel1, localParcel2, 0);
      localParcel2.readException();
      return;
    }
    finally
    {
      localParcel2.recycle();
      localParcel1.recycle();
    }
  }
  
  public void a(int paramInt1, int paramInt2, int paramInt3, int paramInt4)
  {
    Parcel localParcel1 = Parcel.obtain();
    Parcel localParcel2 = Parcel.obtain();
    try
    {
      localParcel1.writeInterfaceToken("com.google.android.gms.maps.internal.IGoogleMapDelegate");
      localParcel1.writeInt(paramInt1);
      localParcel1.writeInt(paramInt2);
      localParcel1.writeInt(paramInt3);
      localParcel1.writeInt(paramInt4);
      a.transact(39, localParcel1, localParcel2, 0);
      localParcel2.readException();
      return;
    }
    finally
    {
      localParcel2.recycle();
      localParcel1.recycle();
    }
  }
  
  /* Error */
  public void a(android.os.Bundle paramBundle)
  {
    // Byte code:
    //   0: invokestatic 23	android/os/Parcel:obtain	()Landroid/os/Parcel;
    //   3: astore_2
    //   4: invokestatic 23	android/os/Parcel:obtain	()Landroid/os/Parcel;
    //   7: astore_3
    //   8: aload_2
    //   9: ldc 25
    //   11: invokevirtual 29	android/os/Parcel:writeInterfaceToken	(Ljava/lang/String;)V
    //   14: aload_1
    //   15: ifnull +42 -> 57
    //   18: aload_2
    //   19: iconst_1
    //   20: invokevirtual 61	android/os/Parcel:writeInt	(I)V
    //   23: aload_1
    //   24: aload_2
    //   25: iconst_0
    //   26: invokevirtual 134	android/os/Bundle:writeToParcel	(Landroid/os/Parcel;I)V
    //   29: aload_0
    //   30: getfield 15	kN:a	Landroid/os/IBinder;
    //   33: bipush 54
    //   35: aload_2
    //   36: aload_3
    //   37: iconst_0
    //   38: invokeinterface 35 5 0
    //   43: pop
    //   44: aload_3
    //   45: invokevirtual 38	android/os/Parcel:readException	()V
    //   48: aload_3
    //   49: invokevirtual 56	android/os/Parcel:recycle	()V
    //   52: aload_2
    //   53: invokevirtual 56	android/os/Parcel:recycle	()V
    //   56: return
    //   57: aload_2
    //   58: iconst_0
    //   59: invokevirtual 61	android/os/Parcel:writeInt	(I)V
    //   62: goto -33 -> 29
    //   65: astore_1
    //   66: aload_3
    //   67: invokevirtual 56	android/os/Parcel:recycle	()V
    //   70: aload_2
    //   71: invokevirtual 56	android/os/Parcel:recycle	()V
    //   74: aload_1
    //   75: athrow
    // Local variable table:
    //   start	length	slot	name	signature
    //   0	76	0	this	kN
    //   0	76	1	paramBundle	android.os.Bundle
    //   3	68	2	localParcel1	Parcel
    //   7	60	3	localParcel2	Parcel
    // Exception table:
    //   from	to	target	type
    //   8	14	65	finally
    //   18	29	65	finally
    //   29	48	65	finally
    //   57	62	65	finally
  }
  
  /* Error */
  public void a(c paramc)
  {
    // Byte code:
    //   0: invokestatic 23	android/os/Parcel:obtain	()Landroid/os/Parcel;
    //   3: astore_2
    //   4: invokestatic 23	android/os/Parcel:obtain	()Landroid/os/Parcel;
    //   7: astore_3
    //   8: aload_2
    //   9: ldc 25
    //   11: invokevirtual 29	android/os/Parcel:writeInterfaceToken	(Ljava/lang/String;)V
    //   14: aload_1
    //   15: ifnull +42 -> 57
    //   18: aload_2
    //   19: iconst_1
    //   20: invokevirtual 61	android/os/Parcel:writeInt	(I)V
    //   23: aload_1
    //   24: aload_2
    //   25: iconst_0
    //   26: invokevirtual 138	com/google/android/gms/maps/model/internal/c:writeToParcel	(Landroid/os/Parcel;I)V
    //   29: aload_0
    //   30: getfield 15	kN:a	Landroid/os/IBinder;
    //   33: bipush 64
    //   35: aload_2
    //   36: aload_3
    //   37: iconst_0
    //   38: invokeinterface 35 5 0
    //   43: pop
    //   44: aload_3
    //   45: invokevirtual 38	android/os/Parcel:readException	()V
    //   48: aload_3
    //   49: invokevirtual 56	android/os/Parcel:recycle	()V
    //   52: aload_2
    //   53: invokevirtual 56	android/os/Parcel:recycle	()V
    //   56: return
    //   57: aload_2
    //   58: iconst_0
    //   59: invokevirtual 61	android/os/Parcel:writeInt	(I)V
    //   62: goto -33 -> 29
    //   65: astore_1
    //   66: aload_3
    //   67: invokevirtual 56	android/os/Parcel:recycle	()V
    //   70: aload_2
    //   71: invokevirtual 56	android/os/Parcel:recycle	()V
    //   74: aload_1
    //   75: athrow
    // Local variable table:
    //   start	length	slot	name	signature
    //   0	76	0	this	kN
    //   0	76	1	paramc	c
    //   3	68	2	localParcel1	Parcel
    //   7	60	3	localParcel2	Parcel
    // Exception table:
    //   from	to	target	type
    //   8	14	65	finally
    //   18	29	65	finally
    //   29	48	65	finally
    //   57	62	65	finally
  }
  
  public void a(c paramc, int paramInt, lq paramlq)
  {
    Parcel localParcel1 = Parcel.obtain();
    Parcel localParcel2 = Parcel.obtain();
    for (;;)
    {
      try
      {
        localParcel1.writeInterfaceToken("com.google.android.gms.maps.internal.IGoogleMapDelegate");
        if (paramc != null)
        {
          localParcel1.writeInt(1);
          paramc.writeToParcel(localParcel1, 0);
          localParcel1.writeInt(paramInt);
          if (paramlq != null)
          {
            paramc = paramlq.asBinder();
            localParcel1.writeStrongBinder(paramc);
            a.transact(67, localParcel1, localParcel2, 0);
            localParcel2.readException();
          }
        }
        else
        {
          localParcel1.writeInt(0);
          continue;
        }
        paramc = null;
      }
      finally
      {
        localParcel2.recycle();
        localParcel1.recycle();
      }
    }
  }
  
  public void a(c paramc, lq paramlq)
  {
    Parcel localParcel1 = Parcel.obtain();
    Parcel localParcel2 = Parcel.obtain();
    for (;;)
    {
      try
      {
        localParcel1.writeInterfaceToken("com.google.android.gms.maps.internal.IGoogleMapDelegate");
        if (paramc != null)
        {
          localParcel1.writeInt(1);
          paramc.writeToParcel(localParcel1, 0);
          if (paramlq != null)
          {
            paramc = paramlq.asBinder();
            localParcel1.writeStrongBinder(paramc);
            a.transact(66, localParcel1, localParcel2, 0);
            localParcel2.readException();
          }
        }
        else
        {
          localParcel1.writeInt(0);
          continue;
        }
        paramc = null;
      }
      finally
      {
        localParcel2.recycle();
        localParcel1.recycle();
      }
    }
  }
  
  /* Error */
  public void a(hz paramhz)
  {
    // Byte code:
    //   0: invokestatic 23	android/os/Parcel:obtain	()Landroid/os/Parcel;
    //   3: astore_2
    //   4: invokestatic 23	android/os/Parcel:obtain	()Landroid/os/Parcel;
    //   7: astore_3
    //   8: aload_2
    //   9: ldc 25
    //   11: invokevirtual 29	android/os/Parcel:writeInterfaceToken	(Ljava/lang/String;)V
    //   14: aload_1
    //   15: ifnull +42 -> 57
    //   18: aload_1
    //   19: invokeinterface 152 1 0
    //   24: astore_1
    //   25: aload_2
    //   26: aload_1
    //   27: invokevirtual 147	android/os/Parcel:writeStrongBinder	(Landroid/os/IBinder;)V
    //   30: aload_0
    //   31: getfield 15	kN:a	Landroid/os/IBinder;
    //   34: iconst_4
    //   35: aload_2
    //   36: aload_3
    //   37: iconst_0
    //   38: invokeinterface 35 5 0
    //   43: pop
    //   44: aload_3
    //   45: invokevirtual 38	android/os/Parcel:readException	()V
    //   48: aload_3
    //   49: invokevirtual 56	android/os/Parcel:recycle	()V
    //   52: aload_2
    //   53: invokevirtual 56	android/os/Parcel:recycle	()V
    //   56: return
    //   57: aconst_null
    //   58: astore_1
    //   59: goto -34 -> 25
    //   62: astore_1
    //   63: aload_3
    //   64: invokevirtual 56	android/os/Parcel:recycle	()V
    //   67: aload_2
    //   68: invokevirtual 56	android/os/Parcel:recycle	()V
    //   71: aload_1
    //   72: athrow
    // Local variable table:
    //   start	length	slot	name	signature
    //   0	73	0	this	kN
    //   0	73	1	paramhz	hz
    //   3	65	2	localParcel1	Parcel
    //   7	57	3	localParcel2	Parcel
    // Exception table:
    //   from	to	target	type
    //   8	14	62	finally
    //   18	25	62	finally
    //   25	48	62	finally
  }
  
  /* Error */
  public void a(hz paramhz, int paramInt, lq paramlq)
  {
    // Byte code:
    //   0: aconst_null
    //   1: astore 4
    //   3: invokestatic 23	android/os/Parcel:obtain	()Landroid/os/Parcel;
    //   6: astore 5
    //   8: invokestatic 23	android/os/Parcel:obtain	()Landroid/os/Parcel;
    //   11: astore 6
    //   13: aload 5
    //   15: ldc 25
    //   17: invokevirtual 29	android/os/Parcel:writeInterfaceToken	(Ljava/lang/String;)V
    //   20: aload_1
    //   21: ifnull +75 -> 96
    //   24: aload_1
    //   25: invokeinterface 152 1 0
    //   30: astore_1
    //   31: aload 5
    //   33: aload_1
    //   34: invokevirtual 147	android/os/Parcel:writeStrongBinder	(Landroid/os/IBinder;)V
    //   37: aload 5
    //   39: iload_2
    //   40: invokevirtual 61	android/os/Parcel:writeInt	(I)V
    //   43: aload 4
    //   45: astore_1
    //   46: aload_3
    //   47: ifnull +10 -> 57
    //   50: aload_3
    //   51: invokeinterface 144 1 0
    //   56: astore_1
    //   57: aload 5
    //   59: aload_1
    //   60: invokevirtual 147	android/os/Parcel:writeStrongBinder	(Landroid/os/IBinder;)V
    //   63: aload_0
    //   64: getfield 15	kN:a	Landroid/os/IBinder;
    //   67: bipush 7
    //   69: aload 5
    //   71: aload 6
    //   73: iconst_0
    //   74: invokeinterface 35 5 0
    //   79: pop
    //   80: aload 6
    //   82: invokevirtual 38	android/os/Parcel:readException	()V
    //   85: aload 6
    //   87: invokevirtual 56	android/os/Parcel:recycle	()V
    //   90: aload 5
    //   92: invokevirtual 56	android/os/Parcel:recycle	()V
    //   95: return
    //   96: aconst_null
    //   97: astore_1
    //   98: goto -67 -> 31
    //   101: astore_1
    //   102: aload 6
    //   104: invokevirtual 56	android/os/Parcel:recycle	()V
    //   107: aload 5
    //   109: invokevirtual 56	android/os/Parcel:recycle	()V
    //   112: aload_1
    //   113: athrow
    // Local variable table:
    //   start	length	slot	name	signature
    //   0	114	0	this	kN
    //   0	114	1	paramhz	hz
    //   0	114	2	paramInt	int
    //   0	114	3	paramlq	lq
    //   1	43	4	localObject	Object
    //   6	102	5	localParcel1	Parcel
    //   11	92	6	localParcel2	Parcel
    // Exception table:
    //   from	to	target	type
    //   13	20	101	finally
    //   24	31	101	finally
    //   31	43	101	finally
    //   50	57	101	finally
    //   57	85	101	finally
  }
  
  /* Error */
  public void a(hz paramhz, lq paramlq)
  {
    // Byte code:
    //   0: aconst_null
    //   1: astore_3
    //   2: invokestatic 23	android/os/Parcel:obtain	()Landroid/os/Parcel;
    //   5: astore 4
    //   7: invokestatic 23	android/os/Parcel:obtain	()Landroid/os/Parcel;
    //   10: astore 5
    //   12: aload 4
    //   14: ldc 25
    //   16: invokevirtual 29	android/os/Parcel:writeInterfaceToken	(Ljava/lang/String;)V
    //   19: aload_1
    //   20: ifnull +68 -> 88
    //   23: aload_1
    //   24: invokeinterface 152 1 0
    //   29: astore_1
    //   30: aload 4
    //   32: aload_1
    //   33: invokevirtual 147	android/os/Parcel:writeStrongBinder	(Landroid/os/IBinder;)V
    //   36: aload_3
    //   37: astore_1
    //   38: aload_2
    //   39: ifnull +10 -> 49
    //   42: aload_2
    //   43: invokeinterface 144 1 0
    //   48: astore_1
    //   49: aload 4
    //   51: aload_1
    //   52: invokevirtual 147	android/os/Parcel:writeStrongBinder	(Landroid/os/IBinder;)V
    //   55: aload_0
    //   56: getfield 15	kN:a	Landroid/os/IBinder;
    //   59: bipush 6
    //   61: aload 4
    //   63: aload 5
    //   65: iconst_0
    //   66: invokeinterface 35 5 0
    //   71: pop
    //   72: aload 5
    //   74: invokevirtual 38	android/os/Parcel:readException	()V
    //   77: aload 5
    //   79: invokevirtual 56	android/os/Parcel:recycle	()V
    //   82: aload 4
    //   84: invokevirtual 56	android/os/Parcel:recycle	()V
    //   87: return
    //   88: aconst_null
    //   89: astore_1
    //   90: goto -60 -> 30
    //   93: astore_1
    //   94: aload 5
    //   96: invokevirtual 56	android/os/Parcel:recycle	()V
    //   99: aload 4
    //   101: invokevirtual 56	android/os/Parcel:recycle	()V
    //   104: aload_1
    //   105: athrow
    // Local variable table:
    //   start	length	slot	name	signature
    //   0	106	0	this	kN
    //   0	106	1	paramhz	hz
    //   0	106	2	paramlq	lq
    //   1	36	3	localObject	Object
    //   5	95	4	localParcel1	Parcel
    //   10	85	5	localParcel2	Parcel
    // Exception table:
    //   from	to	target	type
    //   12	19	93	finally
    //   23	30	93	finally
    //   30	36	93	finally
    //   42	49	93	finally
    //   49	77	93	finally
  }
  
  public void a(String paramString)
  {
    Parcel localParcel1 = Parcel.obtain();
    Parcel localParcel2 = Parcel.obtain();
    try
    {
      localParcel1.writeInterfaceToken("com.google.android.gms.maps.internal.IGoogleMapDelegate");
      localParcel1.writeString(paramString);
      a.transact(61, localParcel1, localParcel2, 0);
      localParcel2.readException();
      return;
    }
    finally
    {
      localParcel2.recycle();
      localParcel1.recycle();
    }
  }
  
  /* Error */
  public void a(kO paramkO)
  {
    // Byte code:
    //   0: invokestatic 23	android/os/Parcel:obtain	()Landroid/os/Parcel;
    //   3: astore_2
    //   4: invokestatic 23	android/os/Parcel:obtain	()Landroid/os/Parcel;
    //   7: astore_3
    //   8: aload_2
    //   9: ldc 25
    //   11: invokevirtual 29	android/os/Parcel:writeInterfaceToken	(Ljava/lang/String;)V
    //   14: aload_1
    //   15: ifnull +43 -> 58
    //   18: aload_1
    //   19: invokeinterface 161 1 0
    //   24: astore_1
    //   25: aload_2
    //   26: aload_1
    //   27: invokevirtual 147	android/os/Parcel:writeStrongBinder	(Landroid/os/IBinder;)V
    //   30: aload_0
    //   31: getfield 15	kN:a	Landroid/os/IBinder;
    //   34: bipush 24
    //   36: aload_2
    //   37: aload_3
    //   38: iconst_0
    //   39: invokeinterface 35 5 0
    //   44: pop
    //   45: aload_3
    //   46: invokevirtual 38	android/os/Parcel:readException	()V
    //   49: aload_3
    //   50: invokevirtual 56	android/os/Parcel:recycle	()V
    //   53: aload_2
    //   54: invokevirtual 56	android/os/Parcel:recycle	()V
    //   57: return
    //   58: aconst_null
    //   59: astore_1
    //   60: goto -35 -> 25
    //   63: astore_1
    //   64: aload_3
    //   65: invokevirtual 56	android/os/Parcel:recycle	()V
    //   68: aload_2
    //   69: invokevirtual 56	android/os/Parcel:recycle	()V
    //   72: aload_1
    //   73: athrow
    // Local variable table:
    //   start	length	slot	name	signature
    //   0	74	0	this	kN
    //   0	74	1	paramkO	kO
    //   3	66	2	localParcel1	Parcel
    //   7	58	3	localParcel2	Parcel
    // Exception table:
    //   from	to	target	type
    //   8	14	63	finally
    //   18	25	63	finally
    //   25	49	63	finally
  }
  
  /* Error */
  public void a(lC paramlC)
  {
    // Byte code:
    //   0: invokestatic 23	android/os/Parcel:obtain	()Landroid/os/Parcel;
    //   3: astore_2
    //   4: invokestatic 23	android/os/Parcel:obtain	()Landroid/os/Parcel;
    //   7: astore_3
    //   8: aload_2
    //   9: ldc 25
    //   11: invokevirtual 29	android/os/Parcel:writeInterfaceToken	(Ljava/lang/String;)V
    //   14: aload_1
    //   15: ifnull +43 -> 58
    //   18: aload_1
    //   19: invokeinterface 165 1 0
    //   24: astore_1
    //   25: aload_2
    //   26: aload_1
    //   27: invokevirtual 147	android/os/Parcel:writeStrongBinder	(Landroid/os/IBinder;)V
    //   30: aload_0
    //   31: getfield 15	kN:a	Landroid/os/IBinder;
    //   34: bipush 27
    //   36: aload_2
    //   37: aload_3
    //   38: iconst_0
    //   39: invokeinterface 35 5 0
    //   44: pop
    //   45: aload_3
    //   46: invokevirtual 38	android/os/Parcel:readException	()V
    //   49: aload_3
    //   50: invokevirtual 56	android/os/Parcel:recycle	()V
    //   53: aload_2
    //   54: invokevirtual 56	android/os/Parcel:recycle	()V
    //   57: return
    //   58: aconst_null
    //   59: astore_1
    //   60: goto -35 -> 25
    //   63: astore_1
    //   64: aload_3
    //   65: invokevirtual 56	android/os/Parcel:recycle	()V
    //   68: aload_2
    //   69: invokevirtual 56	android/os/Parcel:recycle	()V
    //   72: aload_1
    //   73: athrow
    // Local variable table:
    //   start	length	slot	name	signature
    //   0	74	0	this	kN
    //   0	74	1	paramlC	lC
    //   3	66	2	localParcel1	Parcel
    //   7	58	3	localParcel2	Parcel
    // Exception table:
    //   from	to	target	type
    //   8	14	63	finally
    //   18	25	63	finally
    //   25	49	63	finally
  }
  
  /* Error */
  public void a(lF paramlF)
  {
    // Byte code:
    //   0: invokestatic 23	android/os/Parcel:obtain	()Landroid/os/Parcel;
    //   3: astore_2
    //   4: invokestatic 23	android/os/Parcel:obtain	()Landroid/os/Parcel;
    //   7: astore_3
    //   8: aload_2
    //   9: ldc 25
    //   11: invokevirtual 29	android/os/Parcel:writeInterfaceToken	(Ljava/lang/String;)V
    //   14: aload_1
    //   15: ifnull +43 -> 58
    //   18: aload_1
    //   19: invokeinterface 169 1 0
    //   24: astore_1
    //   25: aload_2
    //   26: aload_1
    //   27: invokevirtual 147	android/os/Parcel:writeStrongBinder	(Landroid/os/IBinder;)V
    //   30: aload_0
    //   31: getfield 15	kN:a	Landroid/os/IBinder;
    //   34: bipush 45
    //   36: aload_2
    //   37: aload_3
    //   38: iconst_0
    //   39: invokeinterface 35 5 0
    //   44: pop
    //   45: aload_3
    //   46: invokevirtual 38	android/os/Parcel:readException	()V
    //   49: aload_3
    //   50: invokevirtual 56	android/os/Parcel:recycle	()V
    //   53: aload_2
    //   54: invokevirtual 56	android/os/Parcel:recycle	()V
    //   57: return
    //   58: aconst_null
    //   59: astore_1
    //   60: goto -35 -> 25
    //   63: astore_1
    //   64: aload_3
    //   65: invokevirtual 56	android/os/Parcel:recycle	()V
    //   68: aload_2
    //   69: invokevirtual 56	android/os/Parcel:recycle	()V
    //   72: aload_1
    //   73: athrow
    // Local variable table:
    //   start	length	slot	name	signature
    //   0	74	0	this	kN
    //   0	74	1	paramlF	lF
    //   3	66	2	localParcel1	Parcel
    //   7	58	3	localParcel2	Parcel
    // Exception table:
    //   from	to	target	type
    //   8	14	63	finally
    //   18	25	63	finally
    //   25	49	63	finally
  }
  
  /* Error */
  public void a(lI paramlI)
  {
    // Byte code:
    //   0: invokestatic 23	android/os/Parcel:obtain	()Landroid/os/Parcel;
    //   3: astore_2
    //   4: invokestatic 23	android/os/Parcel:obtain	()Landroid/os/Parcel;
    //   7: astore_3
    //   8: aload_2
    //   9: ldc 25
    //   11: invokevirtual 29	android/os/Parcel:writeInterfaceToken	(Ljava/lang/String;)V
    //   14: aload_1
    //   15: ifnull +43 -> 58
    //   18: aload_1
    //   19: invokeinterface 173 1 0
    //   24: astore_1
    //   25: aload_2
    //   26: aload_1
    //   27: invokevirtual 147	android/os/Parcel:writeStrongBinder	(Landroid/os/IBinder;)V
    //   30: aload_0
    //   31: getfield 15	kN:a	Landroid/os/IBinder;
    //   34: bipush 32
    //   36: aload_2
    //   37: aload_3
    //   38: iconst_0
    //   39: invokeinterface 35 5 0
    //   44: pop
    //   45: aload_3
    //   46: invokevirtual 38	android/os/Parcel:readException	()V
    //   49: aload_3
    //   50: invokevirtual 56	android/os/Parcel:recycle	()V
    //   53: aload_2
    //   54: invokevirtual 56	android/os/Parcel:recycle	()V
    //   57: return
    //   58: aconst_null
    //   59: astore_1
    //   60: goto -35 -> 25
    //   63: astore_1
    //   64: aload_3
    //   65: invokevirtual 56	android/os/Parcel:recycle	()V
    //   68: aload_2
    //   69: invokevirtual 56	android/os/Parcel:recycle	()V
    //   72: aload_1
    //   73: athrow
    // Local variable table:
    //   start	length	slot	name	signature
    //   0	74	0	this	kN
    //   0	74	1	paramlI	lI
    //   3	66	2	localParcel1	Parcel
    //   7	58	3	localParcel2	Parcel
    // Exception table:
    //   from	to	target	type
    //   8	14	63	finally
    //   18	25	63	finally
    //   25	49	63	finally
  }
  
  /* Error */
  public void a(lO paramlO)
  {
    // Byte code:
    //   0: invokestatic 23	android/os/Parcel:obtain	()Landroid/os/Parcel;
    //   3: astore_2
    //   4: invokestatic 23	android/os/Parcel:obtain	()Landroid/os/Parcel;
    //   7: astore_3
    //   8: aload_2
    //   9: ldc 25
    //   11: invokevirtual 29	android/os/Parcel:writeInterfaceToken	(Ljava/lang/String;)V
    //   14: aload_1
    //   15: ifnull +43 -> 58
    //   18: aload_1
    //   19: invokeinterface 177 1 0
    //   24: astore_1
    //   25: aload_2
    //   26: aload_1
    //   27: invokevirtual 147	android/os/Parcel:writeStrongBinder	(Landroid/os/IBinder;)V
    //   30: aload_0
    //   31: getfield 15	kN:a	Landroid/os/IBinder;
    //   34: bipush 28
    //   36: aload_2
    //   37: aload_3
    //   38: iconst_0
    //   39: invokeinterface 35 5 0
    //   44: pop
    //   45: aload_3
    //   46: invokevirtual 38	android/os/Parcel:readException	()V
    //   49: aload_3
    //   50: invokevirtual 56	android/os/Parcel:recycle	()V
    //   53: aload_2
    //   54: invokevirtual 56	android/os/Parcel:recycle	()V
    //   57: return
    //   58: aconst_null
    //   59: astore_1
    //   60: goto -35 -> 25
    //   63: astore_1
    //   64: aload_3
    //   65: invokevirtual 56	android/os/Parcel:recycle	()V
    //   68: aload_2
    //   69: invokevirtual 56	android/os/Parcel:recycle	()V
    //   72: aload_1
    //   73: athrow
    // Local variable table:
    //   start	length	slot	name	signature
    //   0	74	0	this	kN
    //   0	74	1	paramlO	lO
    //   3	66	2	localParcel1	Parcel
    //   7	58	3	localParcel2	Parcel
    // Exception table:
    //   from	to	target	type
    //   8	14	63	finally
    //   18	25	63	finally
    //   25	49	63	finally
  }
  
  /* Error */
  public void a(lR paramlR)
  {
    // Byte code:
    //   0: invokestatic 23	android/os/Parcel:obtain	()Landroid/os/Parcel;
    //   3: astore_2
    //   4: invokestatic 23	android/os/Parcel:obtain	()Landroid/os/Parcel;
    //   7: astore_3
    //   8: aload_2
    //   9: ldc 25
    //   11: invokevirtual 29	android/os/Parcel:writeInterfaceToken	(Ljava/lang/String;)V
    //   14: aload_1
    //   15: ifnull +43 -> 58
    //   18: aload_1
    //   19: invokeinterface 181 1 0
    //   24: astore_1
    //   25: aload_2
    //   26: aload_1
    //   27: invokevirtual 147	android/os/Parcel:writeStrongBinder	(Landroid/os/IBinder;)V
    //   30: aload_0
    //   31: getfield 15	kN:a	Landroid/os/IBinder;
    //   34: bipush 42
    //   36: aload_2
    //   37: aload_3
    //   38: iconst_0
    //   39: invokeinterface 35 5 0
    //   44: pop
    //   45: aload_3
    //   46: invokevirtual 38	android/os/Parcel:readException	()V
    //   49: aload_3
    //   50: invokevirtual 56	android/os/Parcel:recycle	()V
    //   53: aload_2
    //   54: invokevirtual 56	android/os/Parcel:recycle	()V
    //   57: return
    //   58: aconst_null
    //   59: astore_1
    //   60: goto -35 -> 25
    //   63: astore_1
    //   64: aload_3
    //   65: invokevirtual 56	android/os/Parcel:recycle	()V
    //   68: aload_2
    //   69: invokevirtual 56	android/os/Parcel:recycle	()V
    //   72: aload_1
    //   73: athrow
    // Local variable table:
    //   start	length	slot	name	signature
    //   0	74	0	this	kN
    //   0	74	1	paramlR	lR
    //   3	66	2	localParcel1	Parcel
    //   7	58	3	localParcel2	Parcel
    // Exception table:
    //   from	to	target	type
    //   8	14	63	finally
    //   18	25	63	finally
    //   25	49	63	finally
  }
  
  /* Error */
  public void a(lU paramlU)
  {
    // Byte code:
    //   0: invokestatic 23	android/os/Parcel:obtain	()Landroid/os/Parcel;
    //   3: astore_2
    //   4: invokestatic 23	android/os/Parcel:obtain	()Landroid/os/Parcel;
    //   7: astore_3
    //   8: aload_2
    //   9: ldc 25
    //   11: invokevirtual 29	android/os/Parcel:writeInterfaceToken	(Ljava/lang/String;)V
    //   14: aload_1
    //   15: ifnull +43 -> 58
    //   18: aload_1
    //   19: invokeinterface 185 1 0
    //   24: astore_1
    //   25: aload_2
    //   26: aload_1
    //   27: invokevirtual 147	android/os/Parcel:writeStrongBinder	(Landroid/os/IBinder;)V
    //   30: aload_0
    //   31: getfield 15	kN:a	Landroid/os/IBinder;
    //   34: bipush 29
    //   36: aload_2
    //   37: aload_3
    //   38: iconst_0
    //   39: invokeinterface 35 5 0
    //   44: pop
    //   45: aload_3
    //   46: invokevirtual 38	android/os/Parcel:readException	()V
    //   49: aload_3
    //   50: invokevirtual 56	android/os/Parcel:recycle	()V
    //   53: aload_2
    //   54: invokevirtual 56	android/os/Parcel:recycle	()V
    //   57: return
    //   58: aconst_null
    //   59: astore_1
    //   60: goto -35 -> 25
    //   63: astore_1
    //   64: aload_3
    //   65: invokevirtual 56	android/os/Parcel:recycle	()V
    //   68: aload_2
    //   69: invokevirtual 56	android/os/Parcel:recycle	()V
    //   72: aload_1
    //   73: athrow
    // Local variable table:
    //   start	length	slot	name	signature
    //   0	74	0	this	kN
    //   0	74	1	paramlU	lU
    //   3	66	2	localParcel1	Parcel
    //   7	58	3	localParcel2	Parcel
    // Exception table:
    //   from	to	target	type
    //   8	14	63	finally
    //   18	25	63	finally
    //   25	49	63	finally
  }
  
  /* Error */
  public void a(lX paramlX)
  {
    // Byte code:
    //   0: invokestatic 23	android/os/Parcel:obtain	()Landroid/os/Parcel;
    //   3: astore_2
    //   4: invokestatic 23	android/os/Parcel:obtain	()Landroid/os/Parcel;
    //   7: astore_3
    //   8: aload_2
    //   9: ldc 25
    //   11: invokevirtual 29	android/os/Parcel:writeInterfaceToken	(Ljava/lang/String;)V
    //   14: aload_1
    //   15: ifnull +43 -> 58
    //   18: aload_1
    //   19: invokeinterface 189 1 0
    //   24: astore_1
    //   25: aload_2
    //   26: aload_1
    //   27: invokevirtual 147	android/os/Parcel:writeStrongBinder	(Landroid/os/IBinder;)V
    //   30: aload_0
    //   31: getfield 15	kN:a	Landroid/os/IBinder;
    //   34: bipush 53
    //   36: aload_2
    //   37: aload_3
    //   38: iconst_0
    //   39: invokeinterface 35 5 0
    //   44: pop
    //   45: aload_3
    //   46: invokevirtual 38	android/os/Parcel:readException	()V
    //   49: aload_3
    //   50: invokevirtual 56	android/os/Parcel:recycle	()V
    //   53: aload_2
    //   54: invokevirtual 56	android/os/Parcel:recycle	()V
    //   57: return
    //   58: aconst_null
    //   59: astore_1
    //   60: goto -35 -> 25
    //   63: astore_1
    //   64: aload_3
    //   65: invokevirtual 56	android/os/Parcel:recycle	()V
    //   68: aload_2
    //   69: invokevirtual 56	android/os/Parcel:recycle	()V
    //   72: aload_1
    //   73: athrow
    // Local variable table:
    //   start	length	slot	name	signature
    //   0	74	0	this	kN
    //   0	74	1	paramlX	lX
    //   3	66	2	localParcel1	Parcel
    //   7	58	3	localParcel2	Parcel
    // Exception table:
    //   from	to	target	type
    //   8	14	63	finally
    //   18	25	63	finally
    //   25	49	63	finally
  }
  
  /* Error */
  public void a(lw paramlw)
  {
    // Byte code:
    //   0: invokestatic 23	android/os/Parcel:obtain	()Landroid/os/Parcel;
    //   3: astore_2
    //   4: invokestatic 23	android/os/Parcel:obtain	()Landroid/os/Parcel;
    //   7: astore_3
    //   8: aload_2
    //   9: ldc 25
    //   11: invokevirtual 29	android/os/Parcel:writeInterfaceToken	(Ljava/lang/String;)V
    //   14: aload_1
    //   15: ifnull +43 -> 58
    //   18: aload_1
    //   19: invokeinterface 193 1 0
    //   24: astore_1
    //   25: aload_2
    //   26: aload_1
    //   27: invokevirtual 147	android/os/Parcel:writeStrongBinder	(Landroid/os/IBinder;)V
    //   30: aload_0
    //   31: getfield 15	kN:a	Landroid/os/IBinder;
    //   34: bipush 33
    //   36: aload_2
    //   37: aload_3
    //   38: iconst_0
    //   39: invokeinterface 35 5 0
    //   44: pop
    //   45: aload_3
    //   46: invokevirtual 38	android/os/Parcel:readException	()V
    //   49: aload_3
    //   50: invokevirtual 56	android/os/Parcel:recycle	()V
    //   53: aload_2
    //   54: invokevirtual 56	android/os/Parcel:recycle	()V
    //   57: return
    //   58: aconst_null
    //   59: astore_1
    //   60: goto -35 -> 25
    //   63: astore_1
    //   64: aload_3
    //   65: invokevirtual 56	android/os/Parcel:recycle	()V
    //   68: aload_2
    //   69: invokevirtual 56	android/os/Parcel:recycle	()V
    //   72: aload_1
    //   73: athrow
    // Local variable table:
    //   start	length	slot	name	signature
    //   0	74	0	this	kN
    //   0	74	1	paramlw	lw
    //   3	66	2	localParcel1	Parcel
    //   7	58	3	localParcel2	Parcel
    // Exception table:
    //   from	to	target	type
    //   8	14	63	finally
    //   18	25	63	finally
    //   25	49	63	finally
  }
  
  /* Error */
  public void a(lz paramlz)
  {
    // Byte code:
    //   0: invokestatic 23	android/os/Parcel:obtain	()Landroid/os/Parcel;
    //   3: astore_2
    //   4: invokestatic 23	android/os/Parcel:obtain	()Landroid/os/Parcel;
    //   7: astore_3
    //   8: aload_2
    //   9: ldc 25
    //   11: invokevirtual 29	android/os/Parcel:writeInterfaceToken	(Ljava/lang/String;)V
    //   14: aload_1
    //   15: ifnull +43 -> 58
    //   18: aload_1
    //   19: invokeinterface 197 1 0
    //   24: astore_1
    //   25: aload_2
    //   26: aload_1
    //   27: invokevirtual 147	android/os/Parcel:writeStrongBinder	(Landroid/os/IBinder;)V
    //   30: aload_0
    //   31: getfield 15	kN:a	Landroid/os/IBinder;
    //   34: bipush 69
    //   36: aload_2
    //   37: aload_3
    //   38: iconst_0
    //   39: invokeinterface 35 5 0
    //   44: pop
    //   45: aload_3
    //   46: invokevirtual 38	android/os/Parcel:readException	()V
    //   49: aload_3
    //   50: invokevirtual 56	android/os/Parcel:recycle	()V
    //   53: aload_2
    //   54: invokevirtual 56	android/os/Parcel:recycle	()V
    //   57: return
    //   58: aconst_null
    //   59: astore_1
    //   60: goto -35 -> 25
    //   63: astore_1
    //   64: aload_3
    //   65: invokevirtual 56	android/os/Parcel:recycle	()V
    //   68: aload_2
    //   69: invokevirtual 56	android/os/Parcel:recycle	()V
    //   72: aload_1
    //   73: athrow
    // Local variable table:
    //   start	length	slot	name	signature
    //   0	74	0	this	kN
    //   0	74	1	paramlz	lz
    //   3	66	2	localParcel1	Parcel
    //   7	58	3	localParcel2	Parcel
    // Exception table:
    //   from	to	target	type
    //   8	14	63	finally
    //   18	25	63	finally
    //   25	49	63	finally
  }
  
  /* Error */
  public void a(ma paramma)
  {
    // Byte code:
    //   0: invokestatic 23	android/os/Parcel:obtain	()Landroid/os/Parcel;
    //   3: astore_2
    //   4: invokestatic 23	android/os/Parcel:obtain	()Landroid/os/Parcel;
    //   7: astore_3
    //   8: aload_2
    //   9: ldc 25
    //   11: invokevirtual 29	android/os/Parcel:writeInterfaceToken	(Ljava/lang/String;)V
    //   14: aload_1
    //   15: ifnull +43 -> 58
    //   18: aload_1
    //   19: invokeinterface 201 1 0
    //   24: astore_1
    //   25: aload_2
    //   26: aload_1
    //   27: invokevirtual 147	android/os/Parcel:writeStrongBinder	(Landroid/os/IBinder;)V
    //   30: aload_0
    //   31: getfield 15	kN:a	Landroid/os/IBinder;
    //   34: bipush 30
    //   36: aload_2
    //   37: aload_3
    //   38: iconst_0
    //   39: invokeinterface 35 5 0
    //   44: pop
    //   45: aload_3
    //   46: invokevirtual 38	android/os/Parcel:readException	()V
    //   49: aload_3
    //   50: invokevirtual 56	android/os/Parcel:recycle	()V
    //   53: aload_2
    //   54: invokevirtual 56	android/os/Parcel:recycle	()V
    //   57: return
    //   58: aconst_null
    //   59: astore_1
    //   60: goto -35 -> 25
    //   63: astore_1
    //   64: aload_3
    //   65: invokevirtual 56	android/os/Parcel:recycle	()V
    //   68: aload_2
    //   69: invokevirtual 56	android/os/Parcel:recycle	()V
    //   72: aload_1
    //   73: athrow
    // Local variable table:
    //   start	length	slot	name	signature
    //   0	74	0	this	kN
    //   0	74	1	paramma	ma
    //   3	66	2	localParcel1	Parcel
    //   7	58	3	localParcel2	Parcel
    // Exception table:
    //   from	to	target	type
    //   8	14	63	finally
    //   18	25	63	finally
    //   25	49	63	finally
  }
  
  /* Error */
  public void a(md parammd)
  {
    // Byte code:
    //   0: invokestatic 23	android/os/Parcel:obtain	()Landroid/os/Parcel;
    //   3: astore_2
    //   4: invokestatic 23	android/os/Parcel:obtain	()Landroid/os/Parcel;
    //   7: astore_3
    //   8: aload_2
    //   9: ldc 25
    //   11: invokevirtual 29	android/os/Parcel:writeInterfaceToken	(Ljava/lang/String;)V
    //   14: aload_1
    //   15: ifnull +43 -> 58
    //   18: aload_1
    //   19: invokeinterface 205 1 0
    //   24: astore_1
    //   25: aload_2
    //   26: aload_1
    //   27: invokevirtual 147	android/os/Parcel:writeStrongBinder	(Landroid/os/IBinder;)V
    //   30: aload_0
    //   31: getfield 15	kN:a	Landroid/os/IBinder;
    //   34: bipush 31
    //   36: aload_2
    //   37: aload_3
    //   38: iconst_0
    //   39: invokeinterface 35 5 0
    //   44: pop
    //   45: aload_3
    //   46: invokevirtual 38	android/os/Parcel:readException	()V
    //   49: aload_3
    //   50: invokevirtual 56	android/os/Parcel:recycle	()V
    //   53: aload_2
    //   54: invokevirtual 56	android/os/Parcel:recycle	()V
    //   57: return
    //   58: aconst_null
    //   59: astore_1
    //   60: goto -35 -> 25
    //   63: astore_1
    //   64: aload_3
    //   65: invokevirtual 56	android/os/Parcel:recycle	()V
    //   68: aload_2
    //   69: invokevirtual 56	android/os/Parcel:recycle	()V
    //   72: aload_1
    //   73: athrow
    // Local variable table:
    //   start	length	slot	name	signature
    //   0	74	0	this	kN
    //   0	74	1	parammd	md
    //   3	66	2	localParcel1	Parcel
    //   7	58	3	localParcel2	Parcel
    // Exception table:
    //   from	to	target	type
    //   8	14	63	finally
    //   18	25	63	finally
    //   25	49	63	finally
  }
  
  /* Error */
  public void a(mg parammg)
  {
    // Byte code:
    //   0: invokestatic 23	android/os/Parcel:obtain	()Landroid/os/Parcel;
    //   3: astore_2
    //   4: invokestatic 23	android/os/Parcel:obtain	()Landroid/os/Parcel;
    //   7: astore_3
    //   8: aload_2
    //   9: ldc 25
    //   11: invokevirtual 29	android/os/Parcel:writeInterfaceToken	(Ljava/lang/String;)V
    //   14: aload_1
    //   15: ifnull +43 -> 58
    //   18: aload_1
    //   19: invokeinterface 209 1 0
    //   24: astore_1
    //   25: aload_2
    //   26: aload_1
    //   27: invokevirtual 147	android/os/Parcel:writeStrongBinder	(Landroid/os/IBinder;)V
    //   30: aload_0
    //   31: getfield 15	kN:a	Landroid/os/IBinder;
    //   34: bipush 37
    //   36: aload_2
    //   37: aload_3
    //   38: iconst_0
    //   39: invokeinterface 35 5 0
    //   44: pop
    //   45: aload_3
    //   46: invokevirtual 38	android/os/Parcel:readException	()V
    //   49: aload_3
    //   50: invokevirtual 56	android/os/Parcel:recycle	()V
    //   53: aload_2
    //   54: invokevirtual 56	android/os/Parcel:recycle	()V
    //   57: return
    //   58: aconst_null
    //   59: astore_1
    //   60: goto -35 -> 25
    //   63: astore_1
    //   64: aload_3
    //   65: invokevirtual 56	android/os/Parcel:recycle	()V
    //   68: aload_2
    //   69: invokevirtual 56	android/os/Parcel:recycle	()V
    //   72: aload_1
    //   73: athrow
    // Local variable table:
    //   start	length	slot	name	signature
    //   0	74	0	this	kN
    //   0	74	1	parammg	mg
    //   3	66	2	localParcel1	Parcel
    //   7	58	3	localParcel2	Parcel
    // Exception table:
    //   from	to	target	type
    //   8	14	63	finally
    //   18	25	63	finally
    //   25	49	63	finally
  }
  
  /* Error */
  public void a(mj parammj)
  {
    // Byte code:
    //   0: invokestatic 23	android/os/Parcel:obtain	()Landroid/os/Parcel;
    //   3: astore_2
    //   4: invokestatic 23	android/os/Parcel:obtain	()Landroid/os/Parcel;
    //   7: astore_3
    //   8: aload_2
    //   9: ldc 25
    //   11: invokevirtual 29	android/os/Parcel:writeInterfaceToken	(Ljava/lang/String;)V
    //   14: aload_1
    //   15: ifnull +43 -> 58
    //   18: aload_1
    //   19: invokeinterface 213 1 0
    //   24: astore_1
    //   25: aload_2
    //   26: aload_1
    //   27: invokevirtual 147	android/os/Parcel:writeStrongBinder	(Landroid/os/IBinder;)V
    //   30: aload_0
    //   31: getfield 15	kN:a	Landroid/os/IBinder;
    //   34: bipush 36
    //   36: aload_2
    //   37: aload_3
    //   38: iconst_0
    //   39: invokeinterface 35 5 0
    //   44: pop
    //   45: aload_3
    //   46: invokevirtual 38	android/os/Parcel:readException	()V
    //   49: aload_3
    //   50: invokevirtual 56	android/os/Parcel:recycle	()V
    //   53: aload_2
    //   54: invokevirtual 56	android/os/Parcel:recycle	()V
    //   57: return
    //   58: aconst_null
    //   59: astore_1
    //   60: goto -35 -> 25
    //   63: astore_1
    //   64: aload_3
    //   65: invokevirtual 56	android/os/Parcel:recycle	()V
    //   68: aload_2
    //   69: invokevirtual 56	android/os/Parcel:recycle	()V
    //   72: aload_1
    //   73: athrow
    // Local variable table:
    //   start	length	slot	name	signature
    //   0	74	0	this	kN
    //   0	74	1	parammj	mj
    //   3	66	2	localParcel1	Parcel
    //   7	58	3	localParcel2	Parcel
    // Exception table:
    //   from	to	target	type
    //   8	14	63	finally
    //   18	25	63	finally
    //   25	49	63	finally
  }
  
  /* Error */
  public void a(my parammy, hz paramhz)
  {
    // Byte code:
    //   0: aconst_null
    //   1: astore_3
    //   2: invokestatic 23	android/os/Parcel:obtain	()Landroid/os/Parcel;
    //   5: astore 4
    //   7: invokestatic 23	android/os/Parcel:obtain	()Landroid/os/Parcel;
    //   10: astore 5
    //   12: aload 4
    //   14: ldc 25
    //   16: invokevirtual 29	android/os/Parcel:writeInterfaceToken	(Ljava/lang/String;)V
    //   19: aload_1
    //   20: ifnull +68 -> 88
    //   23: aload_1
    //   24: invokeinterface 217 1 0
    //   29: astore_1
    //   30: aload 4
    //   32: aload_1
    //   33: invokevirtual 147	android/os/Parcel:writeStrongBinder	(Landroid/os/IBinder;)V
    //   36: aload_3
    //   37: astore_1
    //   38: aload_2
    //   39: ifnull +10 -> 49
    //   42: aload_2
    //   43: invokeinterface 152 1 0
    //   48: astore_1
    //   49: aload 4
    //   51: aload_1
    //   52: invokevirtual 147	android/os/Parcel:writeStrongBinder	(Landroid/os/IBinder;)V
    //   55: aload_0
    //   56: getfield 15	kN:a	Landroid/os/IBinder;
    //   59: bipush 38
    //   61: aload 4
    //   63: aload 5
    //   65: iconst_0
    //   66: invokeinterface 35 5 0
    //   71: pop
    //   72: aload 5
    //   74: invokevirtual 38	android/os/Parcel:readException	()V
    //   77: aload 5
    //   79: invokevirtual 56	android/os/Parcel:recycle	()V
    //   82: aload 4
    //   84: invokevirtual 56	android/os/Parcel:recycle	()V
    //   87: return
    //   88: aconst_null
    //   89: astore_1
    //   90: goto -60 -> 30
    //   93: astore_1
    //   94: aload 5
    //   96: invokevirtual 56	android/os/Parcel:recycle	()V
    //   99: aload 4
    //   101: invokevirtual 56	android/os/Parcel:recycle	()V
    //   104: aload_1
    //   105: athrow
    // Local variable table:
    //   start	length	slot	name	signature
    //   0	106	0	this	kN
    //   0	106	1	parammy	my
    //   0	106	2	paramhz	hz
    //   1	36	3	localObject	Object
    //   5	95	4	localParcel1	Parcel
    //   10	85	5	localParcel2	Parcel
    // Exception table:
    //   from	to	target	type
    //   12	19	93	finally
    //   23	30	93	finally
    //   30	36	93	finally
    //   42	49	93	finally
    //   49	77	93	finally
  }
  
  public void a(boolean paramBoolean)
  {
    int i = 0;
    Parcel localParcel1 = Parcel.obtain();
    Parcel localParcel2 = Parcel.obtain();
    try
    {
      localParcel1.writeInterfaceToken("com.google.android.gms.maps.internal.IGoogleMapDelegate");
      if (paramBoolean) {
        i = 1;
      }
      localParcel1.writeInt(i);
      a.transact(18, localParcel1, localParcel2, 0);
      localParcel2.readException();
      return;
    }
    finally
    {
      localParcel2.recycle();
      localParcel1.recycle();
    }
  }
  
  public IBinder asBinder()
  {
    return a;
  }
  
  public float b()
  {
    Parcel localParcel1 = Parcel.obtain();
    Parcel localParcel2 = Parcel.obtain();
    try
    {
      localParcel1.writeInterfaceToken("com.google.android.gms.maps.internal.IGoogleMapDelegate");
      a.transact(2, localParcel1, localParcel2, 0);
      localParcel2.readException();
      float f = localParcel2.readFloat();
      return f;
    }
    finally
    {
      localParcel2.recycle();
      localParcel1.recycle();
    }
  }
  
  /* Error */
  public void b(android.os.Bundle paramBundle)
  {
    // Byte code:
    //   0: invokestatic 23	android/os/Parcel:obtain	()Landroid/os/Parcel;
    //   3: astore_2
    //   4: invokestatic 23	android/os/Parcel:obtain	()Landroid/os/Parcel;
    //   7: astore_3
    //   8: aload_2
    //   9: ldc 25
    //   11: invokevirtual 29	android/os/Parcel:writeInterfaceToken	(Ljava/lang/String;)V
    //   14: aload_1
    //   15: ifnull +54 -> 69
    //   18: aload_2
    //   19: iconst_1
    //   20: invokevirtual 61	android/os/Parcel:writeInt	(I)V
    //   23: aload_1
    //   24: aload_2
    //   25: iconst_0
    //   26: invokevirtual 134	android/os/Bundle:writeToParcel	(Landroid/os/Parcel;I)V
    //   29: aload_0
    //   30: getfield 15	kN:a	Landroid/os/IBinder;
    //   33: bipush 60
    //   35: aload_2
    //   36: aload_3
    //   37: iconst_0
    //   38: invokeinterface 35 5 0
    //   43: pop
    //   44: aload_3
    //   45: invokevirtual 38	android/os/Parcel:readException	()V
    //   48: aload_3
    //   49: invokevirtual 42	android/os/Parcel:readInt	()I
    //   52: ifeq +8 -> 60
    //   55: aload_1
    //   56: aload_3
    //   57: invokevirtual 227	android/os/Bundle:readFromParcel	(Landroid/os/Parcel;)V
    //   60: aload_3
    //   61: invokevirtual 56	android/os/Parcel:recycle	()V
    //   64: aload_2
    //   65: invokevirtual 56	android/os/Parcel:recycle	()V
    //   68: return
    //   69: aload_2
    //   70: iconst_0
    //   71: invokevirtual 61	android/os/Parcel:writeInt	(I)V
    //   74: goto -45 -> 29
    //   77: astore_1
    //   78: aload_3
    //   79: invokevirtual 56	android/os/Parcel:recycle	()V
    //   82: aload_2
    //   83: invokevirtual 56	android/os/Parcel:recycle	()V
    //   86: aload_1
    //   87: athrow
    // Local variable table:
    //   start	length	slot	name	signature
    //   0	88	0	this	kN
    //   0	88	1	paramBundle	android.os.Bundle
    //   3	80	2	localParcel1	Parcel
    //   7	72	3	localParcel2	Parcel
    // Exception table:
    //   from	to	target	type
    //   8	14	77	finally
    //   18	29	77	finally
    //   29	60	77	finally
    //   69	74	77	finally
  }
  
  /* Error */
  public void b(c paramc)
  {
    // Byte code:
    //   0: invokestatic 23	android/os/Parcel:obtain	()Landroid/os/Parcel;
    //   3: astore_2
    //   4: invokestatic 23	android/os/Parcel:obtain	()Landroid/os/Parcel;
    //   7: astore_3
    //   8: aload_2
    //   9: ldc 25
    //   11: invokevirtual 29	android/os/Parcel:writeInterfaceToken	(Ljava/lang/String;)V
    //   14: aload_1
    //   15: ifnull +42 -> 57
    //   18: aload_2
    //   19: iconst_1
    //   20: invokevirtual 61	android/os/Parcel:writeInt	(I)V
    //   23: aload_1
    //   24: aload_2
    //   25: iconst_0
    //   26: invokevirtual 138	com/google/android/gms/maps/model/internal/c:writeToParcel	(Landroid/os/Parcel;I)V
    //   29: aload_0
    //   30: getfield 15	kN:a	Landroid/os/IBinder;
    //   33: bipush 65
    //   35: aload_2
    //   36: aload_3
    //   37: iconst_0
    //   38: invokeinterface 35 5 0
    //   43: pop
    //   44: aload_3
    //   45: invokevirtual 38	android/os/Parcel:readException	()V
    //   48: aload_3
    //   49: invokevirtual 56	android/os/Parcel:recycle	()V
    //   52: aload_2
    //   53: invokevirtual 56	android/os/Parcel:recycle	()V
    //   56: return
    //   57: aload_2
    //   58: iconst_0
    //   59: invokevirtual 61	android/os/Parcel:writeInt	(I)V
    //   62: goto -33 -> 29
    //   65: astore_1
    //   66: aload_3
    //   67: invokevirtual 56	android/os/Parcel:recycle	()V
    //   70: aload_2
    //   71: invokevirtual 56	android/os/Parcel:recycle	()V
    //   74: aload_1
    //   75: athrow
    // Local variable table:
    //   start	length	slot	name	signature
    //   0	76	0	this	kN
    //   0	76	1	paramc	c
    //   3	68	2	localParcel1	Parcel
    //   7	60	3	localParcel2	Parcel
    // Exception table:
    //   from	to	target	type
    //   8	14	65	finally
    //   18	29	65	finally
    //   29	48	65	finally
    //   57	62	65	finally
  }
  
  /* Error */
  public void b(hz paramhz)
  {
    // Byte code:
    //   0: invokestatic 23	android/os/Parcel:obtain	()Landroid/os/Parcel;
    //   3: astore_2
    //   4: invokestatic 23	android/os/Parcel:obtain	()Landroid/os/Parcel;
    //   7: astore_3
    //   8: aload_2
    //   9: ldc 25
    //   11: invokevirtual 29	android/os/Parcel:writeInterfaceToken	(Ljava/lang/String;)V
    //   14: aload_1
    //   15: ifnull +42 -> 57
    //   18: aload_1
    //   19: invokeinterface 152 1 0
    //   24: astore_1
    //   25: aload_2
    //   26: aload_1
    //   27: invokevirtual 147	android/os/Parcel:writeStrongBinder	(Landroid/os/IBinder;)V
    //   30: aload_0
    //   31: getfield 15	kN:a	Landroid/os/IBinder;
    //   34: iconst_5
    //   35: aload_2
    //   36: aload_3
    //   37: iconst_0
    //   38: invokeinterface 35 5 0
    //   43: pop
    //   44: aload_3
    //   45: invokevirtual 38	android/os/Parcel:readException	()V
    //   48: aload_3
    //   49: invokevirtual 56	android/os/Parcel:recycle	()V
    //   52: aload_2
    //   53: invokevirtual 56	android/os/Parcel:recycle	()V
    //   56: return
    //   57: aconst_null
    //   58: astore_1
    //   59: goto -34 -> 25
    //   62: astore_1
    //   63: aload_3
    //   64: invokevirtual 56	android/os/Parcel:recycle	()V
    //   67: aload_2
    //   68: invokevirtual 56	android/os/Parcel:recycle	()V
    //   71: aload_1
    //   72: athrow
    // Local variable table:
    //   start	length	slot	name	signature
    //   0	73	0	this	kN
    //   0	73	1	paramhz	hz
    //   3	65	2	localParcel1	Parcel
    //   7	57	3	localParcel2	Parcel
    // Exception table:
    //   from	to	target	type
    //   8	14	62	finally
    //   18	25	62	finally
    //   25	48	62	finally
  }
  
  /* Error */
  public boolean b(boolean paramBoolean)
  {
    // Byte code:
    //   0: iconst_1
    //   1: istore_3
    //   2: invokestatic 23	android/os/Parcel:obtain	()Landroid/os/Parcel;
    //   5: astore 4
    //   7: invokestatic 23	android/os/Parcel:obtain	()Landroid/os/Parcel;
    //   10: astore 5
    //   12: aload 4
    //   14: ldc 25
    //   16: invokevirtual 29	android/os/Parcel:writeInterfaceToken	(Ljava/lang/String;)V
    //   19: iload_1
    //   20: ifeq +57 -> 77
    //   23: iconst_1
    //   24: istore_2
    //   25: aload 4
    //   27: iload_2
    //   28: invokevirtual 61	android/os/Parcel:writeInt	(I)V
    //   31: aload_0
    //   32: getfield 15	kN:a	Landroid/os/IBinder;
    //   35: bipush 20
    //   37: aload 4
    //   39: aload 5
    //   41: iconst_0
    //   42: invokeinterface 35 5 0
    //   47: pop
    //   48: aload 5
    //   50: invokevirtual 38	android/os/Parcel:readException	()V
    //   53: aload 5
    //   55: invokevirtual 42	android/os/Parcel:readInt	()I
    //   58: istore_2
    //   59: iload_2
    //   60: ifeq +22 -> 82
    //   63: iload_3
    //   64: istore_1
    //   65: aload 5
    //   67: invokevirtual 56	android/os/Parcel:recycle	()V
    //   70: aload 4
    //   72: invokevirtual 56	android/os/Parcel:recycle	()V
    //   75: iload_1
    //   76: ireturn
    //   77: iconst_0
    //   78: istore_2
    //   79: goto -54 -> 25
    //   82: iconst_0
    //   83: istore_1
    //   84: goto -19 -> 65
    //   87: astore 6
    //   89: aload 5
    //   91: invokevirtual 56	android/os/Parcel:recycle	()V
    //   94: aload 4
    //   96: invokevirtual 56	android/os/Parcel:recycle	()V
    //   99: aload 6
    //   101: athrow
    // Local variable table:
    //   start	length	slot	name	signature
    //   0	102	0	this	kN
    //   0	102	1	paramBoolean	boolean
    //   24	55	2	i	int
    //   1	63	3	bool	boolean
    //   5	90	4	localParcel1	Parcel
    //   10	80	5	localParcel2	Parcel
    //   87	13	6	localObject	Object
    // Exception table:
    //   from	to	target	type
    //   12	19	87	finally
    //   25	59	87	finally
  }
  
  public float c()
  {
    Parcel localParcel1 = Parcel.obtain();
    Parcel localParcel2 = Parcel.obtain();
    try
    {
      localParcel1.writeInterfaceToken("com.google.android.gms.maps.internal.IGoogleMapDelegate");
      a.transact(3, localParcel1, localParcel2, 0);
      localParcel2.readException();
      float f = localParcel2.readFloat();
      return f;
    }
    finally
    {
      localParcel2.recycle();
      localParcel1.recycle();
    }
  }
  
  public void c(boolean paramBoolean)
  {
    int i = 0;
    Parcel localParcel1 = Parcel.obtain();
    Parcel localParcel2 = Parcel.obtain();
    try
    {
      localParcel1.writeInterfaceToken("com.google.android.gms.maps.internal.IGoogleMapDelegate");
      if (paramBoolean) {
        i = 1;
      }
      localParcel1.writeInt(i);
      a.transact(22, localParcel1, localParcel2, 0);
      localParcel2.readException();
      return;
    }
    finally
    {
      localParcel2.recycle();
      localParcel1.recycle();
    }
  }
  
  public void d()
  {
    Parcel localParcel1 = Parcel.obtain();
    Parcel localParcel2 = Parcel.obtain();
    try
    {
      localParcel1.writeInterfaceToken("com.google.android.gms.maps.internal.IGoogleMapDelegate");
      a.transact(8, localParcel1, localParcel2, 0);
      localParcel2.readException();
      return;
    }
    finally
    {
      localParcel2.recycle();
      localParcel1.recycle();
    }
  }
  
  public void d(boolean paramBoolean)
  {
    int i = 0;
    Parcel localParcel1 = Parcel.obtain();
    Parcel localParcel2 = Parcel.obtain();
    try
    {
      localParcel1.writeInterfaceToken("com.google.android.gms.maps.internal.IGoogleMapDelegate");
      if (paramBoolean) {
        i = 1;
      }
      localParcel1.writeInt(i);
      a.transact(41, localParcel1, localParcel2, 0);
      localParcel2.readException();
      return;
    }
    finally
    {
      localParcel2.recycle();
      localParcel1.recycle();
    }
  }
  
  public void e()
  {
    Parcel localParcel1 = Parcel.obtain();
    Parcel localParcel2 = Parcel.obtain();
    try
    {
      localParcel1.writeInterfaceToken("com.google.android.gms.maps.internal.IGoogleMapDelegate");
      a.transact(14, localParcel1, localParcel2, 0);
      localParcel2.readException();
      return;
    }
    finally
    {
      localParcel2.recycle();
      localParcel1.recycle();
    }
  }
  
  public int f()
  {
    Parcel localParcel1 = Parcel.obtain();
    Parcel localParcel2 = Parcel.obtain();
    try
    {
      localParcel1.writeInterfaceToken("com.google.android.gms.maps.internal.IGoogleMapDelegate");
      a.transact(15, localParcel1, localParcel2, 0);
      localParcel2.readException();
      int i = localParcel2.readInt();
      return i;
    }
    finally
    {
      localParcel2.recycle();
      localParcel1.recycle();
    }
  }
  
  public boolean g()
  {
    boolean bool = false;
    Parcel localParcel1 = Parcel.obtain();
    Parcel localParcel2 = Parcel.obtain();
    try
    {
      localParcel1.writeInterfaceToken("com.google.android.gms.maps.internal.IGoogleMapDelegate");
      a.transact(17, localParcel1, localParcel2, 0);
      localParcel2.readException();
      int i = localParcel2.readInt();
      if (i != 0) {
        bool = true;
      }
      return bool;
    }
    finally
    {
      localParcel2.recycle();
      localParcel1.recycle();
    }
  }
  
  public boolean h()
  {
    boolean bool = false;
    Parcel localParcel1 = Parcel.obtain();
    Parcel localParcel2 = Parcel.obtain();
    try
    {
      localParcel1.writeInterfaceToken("com.google.android.gms.maps.internal.IGoogleMapDelegate");
      a.transact(19, localParcel1, localParcel2, 0);
      localParcel2.readException();
      int i = localParcel2.readInt();
      if (i != 0) {
        bool = true;
      }
      return bool;
    }
    finally
    {
      localParcel2.recycle();
      localParcel1.recycle();
    }
  }
  
  public boolean i()
  {
    boolean bool = false;
    Parcel localParcel1 = Parcel.obtain();
    Parcel localParcel2 = Parcel.obtain();
    try
    {
      localParcel1.writeInterfaceToken("com.google.android.gms.maps.internal.IGoogleMapDelegate");
      a.transact(21, localParcel1, localParcel2, 0);
      localParcel2.readException();
      int i = localParcel2.readInt();
      if (i != 0) {
        bool = true;
      }
      return bool;
    }
    finally
    {
      localParcel2.recycle();
      localParcel1.recycle();
    }
  }
  
  /* Error */
  public android.location.Location j()
  {
    // Byte code:
    //   0: invokestatic 23	android/os/Parcel:obtain	()Landroid/os/Parcel;
    //   3: astore_2
    //   4: invokestatic 23	android/os/Parcel:obtain	()Landroid/os/Parcel;
    //   7: astore_3
    //   8: aload_2
    //   9: ldc 25
    //   11: invokevirtual 29	android/os/Parcel:writeInterfaceToken	(Ljava/lang/String;)V
    //   14: aload_0
    //   15: getfield 15	kN:a	Landroid/os/IBinder;
    //   18: bipush 23
    //   20: aload_2
    //   21: aload_3
    //   22: iconst_0
    //   23: invokeinterface 35 5 0
    //   28: pop
    //   29: aload_3
    //   30: invokevirtual 38	android/os/Parcel:readException	()V
    //   33: aload_3
    //   34: invokevirtual 42	android/os/Parcel:readInt	()I
    //   37: ifeq +26 -> 63
    //   40: getstatic 243	android/location/Location:CREATOR	Landroid/os/Parcelable$Creator;
    //   43: aload_3
    //   44: invokeinterface 249 2 0
    //   49: checkcast 240	android/location/Location
    //   52: astore_1
    //   53: aload_3
    //   54: invokevirtual 56	android/os/Parcel:recycle	()V
    //   57: aload_2
    //   58: invokevirtual 56	android/os/Parcel:recycle	()V
    //   61: aload_1
    //   62: areturn
    //   63: aconst_null
    //   64: astore_1
    //   65: goto -12 -> 53
    //   68: astore_1
    //   69: aload_3
    //   70: invokevirtual 56	android/os/Parcel:recycle	()V
    //   73: aload_2
    //   74: invokevirtual 56	android/os/Parcel:recycle	()V
    //   77: aload_1
    //   78: athrow
    // Local variable table:
    //   start	length	slot	name	signature
    //   0	79	0	this	kN
    //   52	13	1	localLocation	android.location.Location
    //   68	10	1	localObject	Object
    //   3	71	2	localParcel1	Parcel
    //   7	63	3	localParcel2	Parcel
    // Exception table:
    //   from	to	target	type
    //   8	53	68	finally
  }
  
  public lj k()
  {
    Parcel localParcel1 = Parcel.obtain();
    Parcel localParcel2 = Parcel.obtain();
    try
    {
      localParcel1.writeInterfaceToken("com.google.android.gms.maps.internal.IGoogleMapDelegate");
      a.transact(25, localParcel1, localParcel2, 0);
      localParcel2.readException();
      lj locallj = lk.a(localParcel2.readStrongBinder());
      return locallj;
    }
    finally
    {
      localParcel2.recycle();
      localParcel1.recycle();
    }
  }
  
  public kX l()
  {
    Parcel localParcel1 = Parcel.obtain();
    Parcel localParcel2 = Parcel.obtain();
    try
    {
      localParcel1.writeInterfaceToken("com.google.android.gms.maps.internal.IGoogleMapDelegate");
      a.transact(26, localParcel1, localParcel2, 0);
      localParcel2.readException();
      kX localkX = kY.a(localParcel2.readStrongBinder());
      return localkX;
    }
    finally
    {
      localParcel2.recycle();
      localParcel1.recycle();
    }
  }
  
  public boolean m()
  {
    boolean bool = false;
    Parcel localParcel1 = Parcel.obtain();
    Parcel localParcel2 = Parcel.obtain();
    try
    {
      localParcel1.writeInterfaceToken("com.google.android.gms.maps.internal.IGoogleMapDelegate");
      a.transact(40, localParcel1, localParcel2, 0);
      localParcel2.readException();
      int i = localParcel2.readInt();
      if (i != 0) {
        bool = true;
      }
      return bool;
    }
    finally
    {
      localParcel2.recycle();
      localParcel1.recycle();
    }
  }
  
  public nk n()
  {
    Parcel localParcel1 = Parcel.obtain();
    Parcel localParcel2 = Parcel.obtain();
    try
    {
      localParcel1.writeInterfaceToken("com.google.android.gms.maps.internal.IGoogleMapDelegate");
      a.transact(44, localParcel1, localParcel2, 0);
      localParcel2.readException();
      nk localnk = nl.a(localParcel2.readStrongBinder());
      return localnk;
    }
    finally
    {
      localParcel2.recycle();
      localParcel1.recycle();
    }
  }
  
  public void o()
  {
    Parcel localParcel1 = Parcel.obtain();
    Parcel localParcel2 = Parcel.obtain();
    try
    {
      localParcel1.writeInterfaceToken("com.google.android.gms.maps.internal.IGoogleMapDelegate");
      a.transact(55, localParcel1, localParcel2, 0);
      localParcel2.readException();
      return;
    }
    finally
    {
      localParcel2.recycle();
      localParcel1.recycle();
    }
  }
  
  public void p()
  {
    Parcel localParcel1 = Parcel.obtain();
    Parcel localParcel2 = Parcel.obtain();
    try
    {
      localParcel1.writeInterfaceToken("com.google.android.gms.maps.internal.IGoogleMapDelegate");
      a.transact(56, localParcel1, localParcel2, 0);
      localParcel2.readException();
      return;
    }
    finally
    {
      localParcel2.recycle();
      localParcel1.recycle();
    }
  }
  
  public void q()
  {
    Parcel localParcel1 = Parcel.obtain();
    Parcel localParcel2 = Parcel.obtain();
    try
    {
      localParcel1.writeInterfaceToken("com.google.android.gms.maps.internal.IGoogleMapDelegate");
      a.transact(57, localParcel1, localParcel2, 0);
      localParcel2.readException();
      return;
    }
    finally
    {
      localParcel2.recycle();
      localParcel1.recycle();
    }
  }
  
  public void r()
  {
    Parcel localParcel1 = Parcel.obtain();
    Parcel localParcel2 = Parcel.obtain();
    try
    {
      localParcel1.writeInterfaceToken("com.google.android.gms.maps.internal.IGoogleMapDelegate");
      a.transact(58, localParcel1, localParcel2, 0);
      localParcel2.readException();
      return;
    }
    finally
    {
      localParcel2.recycle();
      localParcel1.recycle();
    }
  }
  
  public boolean s()
  {
    boolean bool = false;
    Parcel localParcel1 = Parcel.obtain();
    Parcel localParcel2 = Parcel.obtain();
    try
    {
      localParcel1.writeInterfaceToken("com.google.android.gms.maps.internal.IGoogleMapDelegate");
      a.transact(59, localParcel1, localParcel2, 0);
      localParcel2.readException();
      int i = localParcel2.readInt();
      if (i != 0) {
        bool = true;
      }
      return bool;
    }
    finally
    {
      localParcel2.recycle();
      localParcel1.recycle();
    }
  }
}

/* Location:
 * Qualified Name:     kN
 * Java Class Version: 6 (50.0)
 * JD-Core Version:    0.7.1
 */